Workbook

Sheet Index
A1: MIRAGE data inventory: every dataset, sample, model, test set and result the project uses
A2: Regenerate with: python backend/scripts/export_data_workbook.py. Cells over 2,000 characters are cut; the source file holds the full value.
A4: sheet | B4: what it holds | C4: source in the codebase | D4: rows
A5: Models | B5: Every pretrained detector: purpose, source repo, published accuracy, threshold and fusion weight | C5: app/witnesses/pretrained.py | D5: =MAX(COUNTA('Models'!A:A)-1,0)
A6: Local model files | B6: Trained or fitted artefacts stored on this machine | C6: backend/models_store/ | D6: =MAX(COUNTA('Local model files'!A:A)-1,0)
A7: External datasets | B7: Public datasets sampled for the field test (fetched with scripts/field_data.py fetch) | C7: scripts/field_data.py | D7: =MAX(COUNTA('External datasets'!A:A)-1,0)
A8: Field test files | B8: Every file in the field-test corpus (downloaded and generated) | C8: backend/var/fieldtest/ | D8: =MAX(COUNTA('Field test files'!A:A)-1,0)
A9: Field test generation | B9: Inputs used to generate synthetic field-test media | C9: scripts/field_data.py | D9: =MAX(COUNTA('Field test generation'!A:A)-1,0)
A10: Demo samples | B10: Built-in sample evidence used by scenarios, the copilot and Live Shield | C10: backend/var/samples/ | D10: =MAX(COUNTA('Demo samples'!A:A)-1,0)
A11: Scenarios | B11: Demo scenarios A–I with expected verdicts | C11: app/samples.py | D11: =MAX(COUNTA('Scenarios'!A:A)-1,0)
A12: Spoken scripts | B12: Scripts the sample voice notes and video were generated from | C12: app/samples.py | D12: =MAX(COUNTA('Spoken scripts'!A:A)-1,0)
A13: Live Shield demo | B13: Recorded per-window analysis replayed by the four Live Call Shield demo calls | C13: frontend/src/pages/app/liveDemo.ts | D13: =MAX(COUNTA('Live Shield demo'!A:A)-1,0)
A14: DB artifacts | B14: Every row of the 'artifacts' table (seed data, cases and activity) | C14: backend/var/mirage.db | D14: =MAX(COUNTA('DB artifacts'!A:A)-1,0)
A15: DB audit_log | B15: Every row of the 'audit_log' table (seed data, cases and activity) | C15: backend/var/mirage.db | D15: =MAX(COUNTA('DB audit_log'!A:A)-1,0)
A16: DB beneficiaries | B16: Every row of the 'beneficiaries' table (seed data, cases and activity) | C16: backend/var/mirage.db | D16: =MAX(COUNTA('DB beneficiaries'!A:A)-1,0)
A17: DB cases | B17: Every row of the 'cases' table (seed data, cases and activity) | C17: backend/var/mirage.db | D17: =MAX(COUNTA('DB cases'!A:A)-1,0)
A18: DB drills | B18: Every row of the 'drills' table (seed data, cases and activity) | C18: backend/var/mirage.db | D18: =MAX(COUNTA('DB drills'!A:A)-1,0)
A19: DB findings | B19: Every row of the 'findings' table (seed data, cases and activity) | C19: backend/var/mirage.db | D19: =MAX(COUNTA('DB findings'!A:A)-1,0)
A20: DB organizations | B20: Every row of the 'organizations' table (seed data, cases and activity) | C20: backend/var/mirage.db | D20: =MAX(COUNTA('DB organizations'!A:A)-1,0)
A21: DB people | B21: Every row of the 'people' table (seed data, cases and activity) | C21: backend/var/mirage.db | D21: =MAX(COUNTA('DB people'!A:A)-1,0)
A22: DB personas | B22: Every row of the 'personas' table (seed data, cases and activity) | C22: backend/var/mirage.db | D22: =MAX(COUNTA('DB personas'!A:A)-1,0)
A23: DB request_logs | B23: Every row of the 'request_logs' table (seed data, cases and activity) | C23: backend/var/mirage.db | D23: =MAX(COUNTA('DB request_logs'!A:A)-1,0)
A24: DB response_runs | B24: Every row of the 'response_runs' table (seed data, cases and activity) | C24: backend/var/mirage.db | D24: =MAX(COUNTA('DB response_runs'!A:A)-1,0)
A25: DB tribunal_messages | B25: Every row of the 'tribunal_messages' table (seed data, cases and activity) | C25: backend/var/mirage.db | D25: =MAX(COUNTA('DB tribunal_messages'!A:A)-1,0)
A26: DB verdicts | B26: Every row of the 'verdicts' table (seed data, cases and activity) | C26: backend/var/mirage.db | D26: =MAX(COUNTA('DB verdicts'!A:A)-1,0)
A27: DB verifications | B27: Every row of the 'verifications' table (seed data, cases and activity) | C27: backend/var/mirage.db | D27: =MAX(COUNTA('DB verifications'!A:A)-1,0)
A28: Text cases (tuned) | B28: Labelled scam / benign messages used to test the words witness (100) | C28: testing/text_cases.json | D28: =MAX(COUNTA('Text cases (tuned)'!A:A)-1,0)
A29: Text cases (held-out) | B29: Labelled scam / benign messages used to test the words witness (40) | C29: testing/text_cases_holdout.json | D29: =MAX(COUNTA('Text cases (held-out)'!A:A)-1,0)
A30: Copilot intents | B30: The 52 intents the copilot router is trained on | C30: app/assistant/catalog.py | D30: =MAX(COUNTA('Copilot intents'!A:A)-1,0)
A31: Copilot phrasings | B31: Every training phrasing for the copilot router | C31: app/assistant/catalog.py | D31: =MAX(COUNTA('Copilot phrasings'!A:A)-1,0)
A32: Copilot eval set | B32: Held-out questions scoring the router (never used for training) | C32: app/assistant/eval_set.py | D32: =MAX(COUNTA('Copilot eval set'!A:A)-1,0)
A33: Tactic lexicon | B33: Patterns the words witness uses to find pressure tactics (English regex and Indic words) | C33: app/witnesses/words.py | D33: =MAX(COUNTA('Tactic lexicon'!A:A)-1,0)
A34: Entity patterns | B34: Regexes for UPI IDs, accounts, URLs, phones and other identifiers | C34: app/witnesses/words.py | D34: =MAX(COUNTA('Entity patterns'!A:A)-1,0)
A35: Helplines | B35: Reporting channels shown in the emergency response card | C35: app/fusion/response.py | D35: =MAX(COUNTA('Helplines'!A:A)-1,0)
A36: Scam categories | B36: Categories a case is filed under | C36: app/fusion/response.py | D36: =MAX(COUNTA('Scam categories'!A:A)-1,0)
A37: Results benchmark | B37: Every value in benchmark.json, flattened (path = JSON key path) | C37: backend/models_store/benchmark.json | D37: =MAX(COUNTA('Results benchmark'!A:A)-1,0)
A38: Results metrics | B38: Every value in metrics.json, flattened (path = JSON key path) | C38: backend/models_store/metrics.json | D38: =MAX(COUNTA('Results metrics'!A:A)-1,0)
A39: Results fusion | B39: Every value in fusion.json, flattened (path = JSON key path) | C39: backend/models_store/fusion.json | D39: =MAX(COUNTA('Results fusion'!A:A)-1,0)
A40: Results copilot eval | B40: Every value in assistant_eval.json, flattened (path = JSON key path) | C40: backend/models_store/assistant_eval.json | D40: =MAX(COUNTA('Results copilot eval'!A:A)-1,0)
A41: Results field test | B41: Every value in field.json, flattened (path = JSON key path) | C41: testing/results/field.json | D41: =MAX(COUNTA('Results field test'!A:A)-1,0)
A42: Results end-to-end | B42: Every value in e2e.json, flattened (path = JSON key path) | C42: testing/results/e2e.json | D42: =MAX(COUNTA('Results end-to-end'!A:A)-1,0)
A43: Results voice fusion | B43: Every value in voice_fusion.json, flattened (path = JSON key path) | C43: testing/results/voice_fusion.json | D43: =MAX(COUNTA('Results voice fusion'!A:A)-1,0)
A44: Results voice candidates | B44: Every value in voice_candidates.json, flattened (path = JSON key path) | C44: testing/results/voice_candidates.json | D44: =MAX(COUNTA('Results voice candidates'!A:A)-1,0)
A45: Total | D45: =SUM(D5:D44)

Sheet Models
A1: key | B1: name | C1: source (Hugging Face / file) | D1: witness | E1: role | F1: published accuracy | G1: threshold | H1: fusion weight
A2: df_arena | B2: DF_Arena_500M_V_1 | C2: Speech-Arena-2025/DF_Arena_500M_V_1 | D2: voice | E2: Synthetic-speech detection (primary) | F2: In-the-Wild EER 1.87% · 24-dataset mean EER 5.1% (Speech Anti-Spoofing Arena) | G2: 0.5 | H2: 0.5
A3: nii | B3: Wav2Vec2-Large-AntiDeepfake | C3: NII Wav2Vec2-Large-AntiDeepfake | D3: voice | E3: Synthetic-speech detection (primary) | F3: In-the-Wild EER 2.9% · Deepfake-Eval-2024 EER 30% (arXiv 2506.21090) | G3: 0.5 | H3: 0.2
A4: nii_mms | B4: MMS-300M-AntiDeepfake | C4: NII MMS-300M AntiDeepfake | D4: voice | E4: Synthetic-speech detection (multilingual, primary) | F4: In-the-Wild EER 4.8% · DeepVoice (RVC) EER 4.6% · MMS pretraining on 1,400 languages (arXiv 2506.21090) | G4: 0.3 | H4: 0.65
A5: nii_small | B5: Wav2Vec2-Small-AntiDeepfake | C5: NII Wav2Vec2-Small AntiDeepfake
A6: wavlm | B6: wavlm-base-plus-sv | C6: microsoft/wavlm-base-plus-sv | D6: voice | E6: Speaker verification (voiceprint) | F6: VoxCeleb1 EER 0.84% (model card)
A7: commfor | B7: commfor-model-384 | C7: Community Forensics ViT-S/384 | D7: provenance | E7: AI-generated image detection (primary) | F7: Trained on 4,803 generators (CVPR 2025) | G7: 0.01 | H7: 0.55
A8: swinv2 | B8: ai-image-detector-deploy | C8: haywoodsloan/ai-image-detector-deploy | D8: provenance | E8: AI-generated image detection | F8: SwinV2, modern diffusion generators (model card) | G8: 0.1 | H8: 0.45
A9: gend | B9: GenD_CLIP_L_14 | C9: GenD CLIP ViT-L/14 | D9: face | E9: Face-swap / reenactment detection (primary) | F9: Best mean cross-dataset AUROC over 14 benchmarks (WACV 2026) | G9: 0.75 | H9: 0.5
A10: gend_pe | B10: GenD_PE_L | C10: GenD Perception-Encoder L | D10: face | E10: Face-swap / reenactment detection (primary) | F10: GenD with Meta Perception Encoder backbone (WACV 2026) | G10: 0.75 | H10: 0.5
A11: clip | B11: clip-vit-large-patch14 | C11: openai/clip-vit-large-patch14
A12: phishing | B12: phishing-email-detection-distilbert_v2.4.1 | C12: cybersectony/phishing-email-detection-distilbert | D12: words | E12: Phishing / scam message classifier | F12: English emails and URLs (model card)
A13: nli | B13: mDeBERTa-v3-base-xnli-multilingual-nli-2mil7 | C13: MoritzLaurer/mDeBERTa-v3-base-xnli-multilingual-nli-2mil7 | D13: words | E13: Multilingual zero-shot intent | F13: XNLI 100 languages (model card)
A14: yunet | B14: yunet | C14: OpenCV YuNet | D14: face | E14: Face localisation | F14: WIDER Face (OpenCV Zoo)
A15: syncnet | B15: syncnet | C15: SyncNet v2 (VGG, Chung & Zisserman) | D15: face | E15: Audio-visual lip-sync | F15: LRS2 / VoxCeleb lip-sync (ACCV 2016 workshop)
A16: minilm | B16: paraphrase-multilingual-MiniLM-L12-v2 | C16: sentence-transformers/paraphrase-multilingual-MiniLM-L12-v2 | D16: casebook | E16: Dense retrieval (semantic search) | F16: 50+ languages, paraphrase mining (model card)

Sheet Local model files
A1: file | B1: size (KB)
A2: assistant_eval.json | B2: 2.8
A3: assistant_router.joblib | B3: 12655
A4: benchmark.json | B4: 67.8
A5: fusion.json | B5: 0.1
A6: image_clf.joblib | B6: 1335.8
A7: metrics.json | B7: 1.8
A8: request_anomaly.joblib | B8: 1612
A9: spk_background.npz | B9: 0.7
A10: voice_clf.joblib | B10: 1298
A11: words_clf.joblib | B11: 1618.1

Sheet External datasets
A1: name | B1: dataset | C1: config | D1: split | E1: rows in split | F1: sampled | G1: label
A2: hemg | B2: Hemg/Deepfake-Audio-Dataset | C2: default | D2: train | E2: 100 | F2: 50 | G2: real + fake speech
A3: ljspeech | B3: DynamicSuperb/SpeechDetection_LJSpeech | C3: default | D3: test | E3: 200 | F3: 30 | G3: real + fake speech
A4: indic_hindi | B4: SPRINGLab/IndicTTS-Hindi | C4: default | D4: train | E4: 11825 | F4: 30 | G4: real Hindi speech
A5: google_tamil | B5: ylacombe/google-tamil | C5: female | D5: train | E5: 2335 | F5: 20 | G5: real Tamil speech
A6: google_tamil_m | B6: ylacombe/google-tamil | C6: male | D6: train | E6: 2000 | F6: 20 | G6: real Tamil speech
A7: librispeech | B7: openslr/librispeech_asr | C7: all | D7: test.clean | E7: 2620 | F7: 40 | G7: real English speech
A8: flickr | B8: nlphuji/flickr30k | C8: TEST | D8: test | E8: 31014 | F8: 40 | G8: real photographs

Sheet Field test files
A1: path | B1: folder | C1: size (KB)
A2: audio/edge/chords_music.wav | B2: audio/edge | C2: 187.5
A3: audio/edge/silence_6s.wav | B3: audio/edge | C3: 187.5
A4: audio/edge/street_noise.wav | B4: audio/edge | C4: 187.5
A5: audio/edge/tone_440hz.wav | B5: audio/edge | C5: 187.5
A6: audio/edge/white_noise.wav | B6: audio/edge | C6: 187.5
A7: audio/fake/edge_multilang/bn-IN-TanishaaNeural.wav | B7: audio/fake/edge_multilang | C7: 198
A8: audio/fake/edge_multilang/en-GB-SoniaNeural.wav | B8: audio/fake/edge_multilang | C8: 168.8
A9: audio/fake/edge_multilang/en-IN-NeerjaNeural.wav | B9: audio/fake/edge_multilang | C9: 252
A10: audio/fake/edge_multilang/en-IN-PrabhatNeural.wav | B10: audio/fake/edge_multilang | C10: 237
A11: audio/fake/edge_multilang/en-US-GuyNeural.wav | B11: audio/fake/edge_multilang | C11: 231.8
A12: audio/fake/edge_multilang/gu-IN-NiranjanNeural.wav | B12: audio/fake/edge_multilang | C12: 273
A13: audio/fake/edge_multilang/hi-IN-MadhurNeural.wav | B13: audio/fake/edge_multilang | C13: 225
... A633: image/real_laundered/flickr_023__social.jpg | B633: image/real_laundered | C633: 49.1

Sheet Field test generation
A1: kind | B1: key | C1: value
A2: edge-tts voice | B2: en-IN-NeerjaNeural | C2: ["en-IN", "Hi, this is Neha from the accounts team. Please share the updated invoice before the meeting tomorrow."]
A3: edge-tts voice | B3: en-IN-PrabhatNeural | C3: ["en-IN", "Good afternoon. I'm calling about the quarterly review; the slides are in the shared folder."]
A4: edge-tts voice | B4: hi-IN-SwaraNeural | C4: ["hi-IN", "नमस्ते, मैं बैंक से बोल रही हूँ। आपका खाता सुरक्षित है, कृपया अपना पता अपडेट कर लीजिए।"]
A5: edge-tts voice | B5: hi-IN-MadhurNeural | C5: ["hi-IN", "पापा, मैं ठीक हूँ, बस आज कॉलेज में देर हो जाएगी। रात को फ़ोन करता हूँ।"]
A6: edge-tts voice | B6: ta-IN-PallaviNeural | C6: ["ta-IN", "வணக்கம், நான் உங்கள் வங்கியிலிருந்து பேசுகிறேன். உங்கள் கணக்கு விவரங்களை சரிபார்க்க வேண்டும்."]
A7: edge-tts voice | B7: te-IN-MohanNeural | C7: ["te-IN", "నమస్కారం, నేను ఆఫీసు నుండి మాట్లాడుతున్నాను. రేపటి సమావేశం పది గంటలకు ఉంటుంది."]
A8: edge-tts voice | B8: mr-IN-AarohiNeural | C8: ["mr-IN", "नमस्कार, मी तुमच्या मुलाच्या शाळेतून बोलत आहे. उद्या पालक सभा आहे."]
A9: edge-tts voice | B9: bn-IN-TanishaaNeural | C9: ["bn-IN", "নমস্কার, আমি ব্যাংক থেকে বলছি। আপনার কার্ডের তথ্য যাচাই করতে হবে।"]
A10: edge-tts voice | B10: gu-IN-NiranjanNeural | C10: ["gu-IN", "નમસ્તે, હું તમારી કંપનીના એચઆર વિભાગમાંથી બોલું છું. પગાર સ્લિપ મોકલી દીધી છે."]
A11: edge-tts voice | B11: en-US-GuyNeural | C11: ["en-US", "Hey, it's Mark from IT. We're rolling out a new VPN client this afternoon, nothing for you to do."]
A12: edge-tts voice | B12: en-GB-SoniaNeural | C12: ["en-GB", "Hello, this is the clinic confirming your appointment on Thursday at half past two."]
... A23: spoken script | B23: ta_benign | C23: ["ta-IN-PallaviNeural", "வணக்கம், நாளை காலை பத்து மணிக்கு கூட்டம் நடைபெறும். அனைவரும் வர வேண்டும்.", false]
A24: SAPI voice | B24: 0 | C24: Microsoft David Desktop
A25: SAPI voice | B25: 1 | C25: Microsoft Zira Desktop
A26: SAPI voice | B26: 2 | C26: Microsoft Heera Desktop
A27: SAPI voice | B27: 3 | C27: Microsoft Ravi Desktop
A28: SAPI text | B28: 0 | C28: Hello, this is your manager. Please process the vendor payment today and confirm by email.
A29: SAPI text | B29: 1 | C29: Your parcel is held at customs. Call this number to pay the clearance fee.
A30: SD-Turbo prompt | B30: 0 | C30: passport-style photo of an Indian man in his forties, plain background, realistic
A31: SD-Turbo prompt | B31: 1 | C31: candid photo of an Indian woman in a saree at a railway station, natural light
A32: SD-Turbo prompt | B32: 2 | C32: corporate headshot of a smiling executive in a blue suit, office background
A33: SD-Turbo prompt | B33: 3 | C33: an aadhaar-style identity card lying on a wooden table, photo
A34: SD-Turbo prompt | B34: 4 | C34: a bank cheque on a desk next to a pen, realistic photo
A35: SD-Turbo prompt | B35: 5 | C35: police officer in khaki uniform sitting at a desk, documentary photo
... A52: audio laundering | B52: 5 | C52: noise

Sheet Demo samples
A1: file | B1: size (KB) | C1: sha256
A2: .v5 | B2: 0 | C2: 2689367b205c16ce32ed4200942b8b8b1e262dfc70d9bc9fbc77c49699a4f1df
A3: .v6 | B3: 0 | C3: 2689367b205c16ce32ed4200942b8b8b1e262dfc70d9bc9fbc77c49699a4f1df
A4: cbi_notice.png | B4: 133 | C4: 81c17486b868f3d109e3e4159ad99dc96b03f8f4ee775e81c283ec0caf97c7f5
A5: ceo_meeting.mp4 | B5: 185.5 | C5: dcd6e1b3ce071839949027861d0b90307789c4195fd7679ea6faea24601214e6
A6: cfo_voice_note.wav | B6: 517.9 | C6: 0c6356b156fe3da29f708117352f28de11c438d0cdb8244ab289e7c8728114d2
A7: controller_voice.wav | B7: 218.8 | C7: 6d3028c25ad82112b875e63617be77b57b8b5905dba20e4fea21637999ea2a0e
A8: it_helpdesk.wav | B8: 343.9 | C8: fba1753c8ba9b178f7aa118c0f2625ee3adb89d4d03220b490e41ee78cb61997
A9: papa_voice_note.wav | B9: 350.8 | C9: 8ee650801c14eee68e4b6c098d232806785b31a005cd15483c392f5942151589
A10: short_clip.wav | B10: 46.9 | C10: 235ec47d5168f87a3b610c815c19b49b10e9da6260dfe146e31fcdc0d6519676
A11: townhall_avatar.wav | B11: 235.4 | C11: d6d00889494c5da15299d125fab1c2c2e2dae632a18541cc8ab299cfa623810b
A12: vendor_headshot.png | B12: 233.2 | C12: ccc1c417982603ef80acd77d687e91514a29e8676180703d0490ff6ca035bf5c
A13: vendor_invoice.eml | B13: 0.9 | C13: 3cbeb4efd93349e3f4dc6c1fb106b5232c04986143dba73874e23edfee5e39bc

Sheet Scenarios
A1: key | B1: code | C1: title | D1: story | E1: claimed_sender | F1: channel | G1: sender_contact | H1: message | I1: files | J1: expected | K1: received_hour | L1: tags | M1: hint
A2: cfo_wire | B2: A | C2: CFO voice note: urgent wire | D2: A cloned CFO voice note on WhatsApp asks Accounts Payable to wire ₹48.5 lakh to a new vendor before 4 PM. | E2: Rajesh Mehta (CFO) | F2: whatsapp | G2: +91 70451 88213 | H2: Hi, it's Rajesh. I'm in a board meeting, can't take calls. Please process ₹48,50,000 to the new vendor account 918273645501 IFSC HDFC0001234 before 4 PM — very urgent. Keep this between us, bhai, audit wale ko abhi mat batana. | I2: ["cfo_voice_note.wav"] | J2: HIGH | K2: 15 | L2: ["voice", "BEC", "Hinglish"]
A3: video_meeting | B3: B | C3: Deepfake video meeting | D3: A recorded 'all-hands' clip with the CEO asking finance to move funds for a confidential acquisition. | E3: Ashok Raman (CEO) | F3: video | H3: As discussed on the call, transfer ₹3.2 crore to the escrow account 50100776655441 today. This is confidential until the acquisition is announced. Do not discuss with anyone in finance. | I3: ["ceo_meeting.mp4"] | J3: HIGH | K3: 18 | L3: ["video", "Arup pattern"]
A4: it_otp | B4: C | C4: IT help-desk OTP reset | D4: A short, heavily compressed voice note from 'IT support' asks for the OTP to finish a password reset. | E4: IT helpdesk | F4: phone | G4: +91 88002 31109 | H4: IT team se bol raha hoon, aapka account reset ho raha hai. Jo OTP aaya hai woh bata do jaldi, 10 minute mein lock ho jayega. | I4: ["it_helpdesk.wav"] | J4: HIGH | K4: 21 | L4: ["credential", "Hinglish"]
A5: real_voice_fraud | B5: D | C5: Genuine voice, fraudulent request | D5: The Financial Controller's real voice, but the message asks to pay a never-seen account. The media is fine; the request is not. | E5: Priya Nair | F5: teams | H5: Hi Kavita, please pay ₹14,00,000 to this new account 778899001122 for the Orbit settlement today. Thanks. | I5: ["controller_voice.wav"] | J5: HIGH | K5: 11 | L5: ["context beats detection"]
A6: harmless_avatar | B6: E | C6: Labelled AI avatar, harmless | D6: An AI-generated presenter voice announces the Friday townhall. Synthetic, but it asks for nothing. | F6: email | H6: Join us for the quarterly townhall on Friday at 4 PM in the main auditorium. Snacks will be served! | I6: ["townhall_avatar.wav"] | J6: LOW | K6: 10 | L6: ["no false alarm"]
A7: papa_emergency | B7: F | C7: 'Papa' emergency voice note | D7: A Hinglish voice note in a cloned father's voice from an unknown number asks for money on UPI right now. | E7: Papa | F7: whatsapp | G7: +91 73040 99812 | H7: Beta main hoon, accident ho gaya hai, phone toot gaya. Paise abhi bhejo family.help@ibl pe, ₹75,000, kisi ko mat batana please. | I7: ["papa_voice_note.wav"] | J7: HIGH | K7: 22 | L7: ["family", "Hinglish", "UPI"]
A8: digital_arrest | B8: G | C8: 'CBI officer' digital arrest | D8: A screenshot of a forged 'CBI notice' and a message demanding a verification deposit on a video call. | E8: Inspector Sharma, CBI Cyber Cell | F8: video | G8: +91 90011 22334 | H8: This is Inspector Sharma from CBI Cyber Cell. A parcel in your name contains illegal items. You are under digital arrest. Do not disconnect or inform anyone. Transfer ₹2,40,000 to safeacct.rbi@oksbi for verification. | I8: ["cbi_notice.png"] | J8: HIGH | K8: 13 | L8: ["image", "digital arrest"] | M8: digital_arrest
A9: vendor_headshot | B9: H | C9: Vendor BEC email with AI headshot | D9: A 'new account manager' at a known vendor emails changed bank details with an AI-generated headshot. The original .eml carries the headers. | E9: Orbit Supplies billing | F9: email | I9: ["vendor_invoice.eml", "vendor_headshot.png"] | J9: HIGH | K9: 16 | L9: ["image", "email", "BEC"]
A10: too_little | B10: I | C10: Too little evidence | D10: A 1.5-second clip with no message and no sender. MIRAGE should say it cannot tell. | F10: unknown | I10: ["short_clip.wav"] | J10: INCONCLUSIVE | K10: 12 | L10: ["honest uncertainty"]

Sheet Spoken scripts
A1: key | B1: script | C1: voice
A2: cfo | B2: Hi, it's Rajesh. I'm in a board meeting and can't take calls. Please process forty eight lakh fifty thousand rupees to the new vendor account before 4 PM. Very urgent. Keep this between us, audit wale ko abhi mat batana. | C2: Rishi
A3: it | B3: IT team se bol raha hoon. Aapka account reset ho raha hai. Jo OTP aaya hai woh bata do jaldi, ten minute mein lock ho jayega. | C3: Rishi
A4: townhall | B4: Join us for the quarterly townhall on Friday at 4 PM in the main auditorium. Snacks will be served! | C4: Tara
A5: papa | B5: Beta main hoon, accident ho gaya hai, phone toot gaya. Paise abhi bhejo, seventy five thousand. Kisi ko mat batana please. | C5: Aman
A6: ceo | B6: As discussed on the call, transfer three point two crore to the escrow account today. This is confidential until the acquisition is announced. Do not discuss with anyone in finance. | C6: Aman

Sheet Live Shield demo
A1: call | B1: window | C1: start (s) | D1: synthetic voice | E1: transcript | F1: tactics | G1: request | H1: manipulation | I1: amount (INR)
A2: cfo_voice_note.wav | B2: 1 | C2: 0 | D2: 1 | E2: Hi, it's Rajesh. I'm in a | G2: none | H2: 0.432
A3: cfo_voice_note.wav | B3: 2 | C3: 3 | D3: 1 | E3: board meeting and can't take calls. | F3: authority, channel_switch | G3: none | H3: 0.762
A4: cfo_voice_note.wav | B4: 3 | C4: 6 | D4: 1 | E4: Please process 48,50,000 rupees to the | F4: authority, channel_switch | G4: payment | H4: 0.908 | I4: 4850000
A5: cfo_voice_note.wav | B5: 4 | C5: 9 | D5: 1 | E5: new vendor account before 4 PM. | F5: authority, channel_switch, urgency | G5: payment | H5: 0.948 | I5: 4850000
A6: cfo_voice_note.wav | B6: 5 | C6: 12 | D6: 1 | E6: Very urgent. Keep this between us, | F6: authority, channel_switch, secrecy, urgency | G6: payment | H6: 0.994 | I6: 4850000
A7: cfo_voice_note.wav | B7: 6 | C7: 15 | D7: 1 | E7: audit wale ko abhi mat batana. | F7: authority, bypass, channel_switch, secrecy, urgency | G7: payment | H7: 1 | I7: 4850000
A8: papa_voice_note.wav | B8: 1 | C8: 0 | D8: 1 | E8: Beta main hoon, accident ho | F8: fear | G8: none | H8: 0.805
A9: papa_voice_note.wav | B9: 2 | C9: 3 | D9: 1 | E9: gaya hai, phone toot gaya. | F9: channel_switch, fear | G9: none | H9: 0.866
A10: papa_voice_note.wav | B10: 3 | C10: 6 | D10: 1 | E10: Paise abhi bhejo, ₹75,000. | F10: channel_switch, fear, urgency | G10: payment | H10: 0.947 | I10: 75000
A11: papa_voice_note.wav | B11: 4 | C11: 9 | D11: 1 | E11: Kisi ko mat batana please. | F11: channel_switch, fear, secrecy, urgency | G11: payment | H11: 0.994 | I11: 75000
A12: it_helpdesk.wav | B12: 1 | C12: 0 | D12: 1 | E12: IT team se bol raha hoon. | F12: authority | G12: none | H12: 0.589
A13: it_helpdesk.wav | B13: 2 | C13: 3 | D13: 1 | E13: Aapka account reset ho raha hai. Jo | F13: authority | G13: none | H13: 0.873
A14: it_helpdesk.wav | B14: 3 | C14: 6 | D14: 1 | E14: OTP aaya hai woh bata do jaldi, | F14: authority, urgency | G14: credential | H14: 0.903
A15: it_helpdesk.wav | B15: 4 | C15: 9 | D15: 1 | E15: 10 minute mein lock ho jayega. | F15: authority, urgency | G15: credential | H15: 0.902
A16: townhall_avatar.wav | B16: 1 | C16: 0 | D16: 1 | E16: Join us for the quarterly townhall | G16: none | H16: 0.005
A17: townhall_avatar.wav | B17: 2 | C17: 3 | D17: 1 | E17: on Friday at 4 PM in the | G17: none | H17: 0.003
A18: townhall_avatar.wav | B18: 3 | C18: 6 | D18: 0.997 | E18: main auditorium. Snacks will be served! | G18: none | H18: 0.006

Sheet DB artifacts
A1: id | B1: case_id | C1: kind | D1: filename | E1: mime | F1: sha256 | G1: size_bytes | H1: storage_key | I1: duration_s | J1: meta_json
A2: 1 | B2: MRG-0458 | C2: audio | D2: cfo_voice_note.wav | E2: audio/wav | F2: 0c6356b156fe3da29f708117352f28de11c438d0cdb8244ab289e7c8728114d2 | G2: 530346 | H2: 0c/0c6356b156fe3da29f708117352f28de11c438d0cdb8244ab289e7c8728114d2.wav | I2: 16.57 | J2: {"transcript": "Voice call: confirming the Orbit change, please release the pending \u20b99,80,000 to 600112233445 urgently.", "asr": {"text": "Hi, it's Rajesh. I'm in a board meeting and can't take calls. Please process 48 .50 ,000 rupees to the new vendor account before 4PM very urgent. Keep this between us, AuditWale .co .ubi Matt Batina", "language": "en", "language_p": 1.0, "words": [{"w": "Hi,", "t0": 0.0, "t1": 0.34, "p": 0.77}, {"w": "it's", "t0": 0.68, "t1": 1.02, "p": 0.81}, {"w": "Rajesh.", "t0": 1.02, "t1": 1.34, "p": 0.87}, {"w": "I'm", "t0": 2.26, "t1": 2.64, "p": 0.98}, {"w": "in", "t0": 2.64, "t1": 2.68, "p": 0.98}, {"w": "a", "t0": 2.68, "t1": 2.78, "p": 0.92}, {"w": "board", "t0": 2.78, "t1": 2.98, "p": 0.91}, {"w": "meeting", "t0": 2.98, "t1": 3.3, "p": 1.0}, {"w": "and", "t0": 3.3, "t1": 3.56, "p": 1.0}, {"w": "can't", "t0": 3.56, "t1": 3.92, "p": 0.97}, {"w": "take", "t0": 3.92, "t1": 4.06, "p": 1.0}, {"w": "calls.", "t0": 4.06, "t1": 4.54, "p": 1.0}, {"w": "Please", "t0": 5.58, "t1": 5.8, "p": 0.96}, {"w": "process", "t0": 5.8, "t1": 6.28, "p": 0.96}, {"w": "48", "t0": 6.28, "t1": 6.84, "p": 0.98}, {"w": ".50", "t0": 6.84, "t1": 7.54, "p": 0.54}, {"w": ",000", "t0": 7.54, "t1": 8.08, "p": 0.71}, {"w": "rupees", "t0": 8.08, "t1": 8.42, "p": 0.81}, {"w": "to", "t0": 8.42, "t1": 8.7, "p": 1.0}, {"w": "the", "t0": 8.7, "t1": 8.82, "p": 0.99}, {"w": "new", "t0": 8.82, "t1": 8.98, "p": 0.8}, {"w": "vendor", "t0": 8.98, "t1": 9.24, "p": 0.92}, {"w": "account", "t0": 9.24, "t1": 9.6, "p": 1.0}, {"w": "before", "t0": 9.6, "t1": 9.96, "p": 0.99}, {"w": "4PM", "t0": 9.96, "t1": 10.68, "p": 0.64}, {"w": "very", "t0": 10.68, "t1": 11.1, "p": 0.62}, {"w": "urgent.", "t0": 11.1, "t1": 11.46, "p": 1.0}, {"w": "Keep", "t0": 12.28, "t1": 12.66, "p": 0.98}, {"w": "this", "t0": 12.66, "t1": 12.88, "p": 0.99}, {"w": "between", "t0": 12.88, "t1": 13.24, "p": 0.99}, {"w": "us,", "t0": 13.24, "t1": 13.54, "p": 1.0}, {"w": "AuditWale", "t0": 14.0, "t1": 14.46, "p": 0.5 …(truncated)
A3: 2 | B3: MRG-0459 | C3: video | D3: ceo_meeting.mp4 | E3: video/mp4 | F3: dcd6e1b3ce071839949027861d0b90307789c4195fd7679ea6faea24601214e6 | G3: 190002 | H3: dc/dcd6e1b3ce071839949027861d0b90307789c4195fd7679ea6faea24601214e6.mp4 | I3: 12.61 | J3: {"transcript": "Video meeting: the CEO and CFO ask to move \u20b948,50,000 to 600112233445 today for a confidential settlement. Do not discuss with anyone in finance.", "asr": {"text": "As discussed on the call, transfer 3 .2 crore to the escrow account today. This is confidential until the acquisition is announced. Do not discuss with anyone in finance.", "language": "en", "language_p": 1.0, "words": [{"w": "As", "t0": 0.0, "t1": 0.26, "p": 0.65}, {"w": "discussed", "t0": 0.26, "t1": 0.62, "p": 1.0}, {"w": "on", "t0": 0.62, "t1": 0.92, "p": 1.0}, {"w": "the", "t0": 0.92, "t1": 1.06, "p": 1.0}, {"w": "call,", "t0": 1.06, "t1": 1.32, "p": 0.99}, {"w": "transfer", "t0": 1.84, "t1": 2.3, "p": 0.94}, {"w": "3", "t0": 2.3, "t1": 2.76, "p": 0.93}, {"w": ".2", "t0": 2.76, "t1": 3.2, "p": 0.99}, {"w": "crore", "t0": 3.2, "t1": 3.5, "p": 0.77}, {"w": "to", "t0": 3.5, "t1": 3.68, "p": 1.0}, {"w": "the", "t0": 3.68, "t1": 3.84, "p": 0.99}, {"w": "escrow", "t0": 3.84, "t1": 4.26, "p": 0.85}, {"w": "account", "t0": 4.26, "t1": 4.54, "p": 0.99}, {"w": "today.", "t0": 4.54, "t1": 4.92, "p": 1.0}, {"w": "This", "t0": 5.48, "t1": 6.04, "p": 0.99}, {"w": "is", "t0": 6.04, "t1": 6.2, "p": 1.0}, {"w": "confidential", "t0": 6.2, "t1": 6.7, "p": 1.0}, {"w": "until", "t0": 6.7, "t1": 7.2, "p": 0.99}, {"w": "the", "t0": 7.2, "t1": 7.44, "p": 1.0}, {"w": "acquisition", "t0": 7.44, "t1": 7.9, "p": 1.0}, {"w": "is", "t0": 7.9, "t1": 8.22, "p": 1.0}, {"w": "announced.", "t0": 8.22, "t1": 8.74, "p": 1.0}, {"w": "Do", "t0": 9.52, "t1": 9.82, "p": 0.99}, {"w": "not", "t0": 9.82, "t1": 9.98, "p": 0.99}, {"w": "discuss", "t0": 9.98, "t1": 10.36, "p": 1.0}, {"w": "with", "t0": 10.36, "t1": 10.62, "p": 1.0}, {"w": "anyone", "t0": 10.62, "t1": 11.02, "p": 0.99}, {"w": "in", "t0": 11.02, "t1": 11.24, "p": 1.0}, {"w": "finance.", "t0": 11.24, "t1": 11.6, "p": 0.87}], "engine": "faster-whisper/base"}}
A4: 3 | B4: MRG-0461 | C4: audio | D4: cfo_voice_note.wav | E4: audio/wav | F4: 0c6356b156fe3da29f708117352f28de11c438d0cdb8244ab289e7c8728114d2 | G4: 530346 | H4: 0c/0c6356b156fe3da29f708117352f28de11c438d0cdb8244ab289e7c8728114d2.wav | I4: 16.57 | J4: {"asr": {"text": "Hi, it's Rajesh. I'm in a board meeting and can't take calls. Please process 48 .50 ,000 rupees to the new vendor account before 4PM very urgent. Keep this between us, AuditWale .co .ubi Matt Batina", "language": "en", "language_p": 1.0, "words": [{"w": "Hi,", "t0": 0.0, "t1": 0.34, "p": 0.77}, {"w": "it's", "t0": 0.68, "t1": 1.02, "p": 0.81}, {"w": "Rajesh.", "t0": 1.02, "t1": 1.34, "p": 0.87}, {"w": "I'm", "t0": 2.26, "t1": 2.64, "p": 0.98}, {"w": "in", "t0": 2.64, "t1": 2.68, "p": 0.98}, {"w": "a", "t0": 2.68, "t1": 2.78, "p": 0.92}, {"w": "board", "t0": 2.78, "t1": 2.98, "p": 0.91}, {"w": "meeting", "t0": 2.98, "t1": 3.3, "p": 1.0}, {"w": "and", "t0": 3.3, "t1": 3.56, "p": 1.0}, {"w": "can't", "t0": 3.56, "t1": 3.92, "p": 0.97}, {"w": "take", "t0": 3.92, "t1": 4.06, "p": 1.0}, {"w": "calls.", "t0": 4.06, "t1": 4.54, "p": 1.0}, {"w": "Please", "t0": 5.58, "t1": 5.8, "p": 0.96}, {"w": "process", "t0": 5.8, "t1": 6.28, "p": 0.96}, {"w": "48", "t0": 6.28, "t1": 6.84, "p": 0.98}, {"w": ".50", "t0": 6.84, "t1": 7.54, "p": 0.54}, {"w": ",000", "t0": 7.54, "t1": 8.08, "p": 0.71}, {"w": "rupees", "t0": 8.08, "t1": 8.42, "p": 0.81}, {"w": "to", "t0": 8.42, "t1": 8.7, "p": 1.0}, {"w": "the", "t0": 8.7, "t1": 8.82, "p": 0.99}, {"w": "new", "t0": 8.82, "t1": 8.98, "p": 0.8}, {"w": "vendor", "t0": 8.98, "t1": 9.24, "p": 0.92}, {"w": "account", "t0": 9.24, "t1": 9.6, "p": 1.0}, {"w": "before", "t0": 9.6, "t1": 9.96, "p": 0.99}, {"w": "4PM", "t0": 9.96, "t1": 10.68, "p": 0.64}, {"w": "very", "t0": 10.68, "t1": 11.1, "p": 0.62}, {"w": "urgent.", "t0": 11.1, "t1": 11.46, "p": 1.0}, {"w": "Keep", "t0": 12.28, "t1": 12.66, "p": 0.98}, {"w": "this", "t0": 12.66, "t1": 12.88, "p": 0.99}, {"w": "between", "t0": 12.88, "t1": 13.24, "p": 0.99}, {"w": "us,", "t0": 13.24, "t1": 13.54, "p": 1.0}, {"w": "AuditWale", "t0": 14.0, "t1": 14.46, "p": 0.57}, {"w": ".co", "t0": 14.46, "t1": 14.8, "p": 0.34}, {"w": ".ubi", "t0": 14.8, "t1": 15.1, "p": 0.33}, {"w": "Matt", "t0": 15 …(truncated)
A5: 4 | B5: MRG-0462 | C5: video | D5: ceo_meeting.mp4 | E5: video/mp4 | F5: dcd6e1b3ce071839949027861d0b90307789c4195fd7679ea6faea24601214e6 | G5: 190002 | H5: dc/dcd6e1b3ce071839949027861d0b90307789c4195fd7679ea6faea24601214e6.mp4 | I5: 12.61 | J5: {"asr": {"text": "As discussed on the call, transfer 3 .2 crore to the escrow account today. This is confidential until the acquisition is announced. Do not discuss with anyone in finance.", "language": "en", "language_p": 1.0, "words": [{"w": "As", "t0": 0.0, "t1": 0.26, "p": 0.65}, {"w": "discussed", "t0": 0.26, "t1": 0.62, "p": 1.0}, {"w": "on", "t0": 0.62, "t1": 0.92, "p": 1.0}, {"w": "the", "t0": 0.92, "t1": 1.06, "p": 1.0}, {"w": "call,", "t0": 1.06, "t1": 1.32, "p": 0.99}, {"w": "transfer", "t0": 1.84, "t1": 2.3, "p": 0.94}, {"w": "3", "t0": 2.3, "t1": 2.76, "p": 0.93}, {"w": ".2", "t0": 2.76, "t1": 3.2, "p": 0.99}, {"w": "crore", "t0": 3.2, "t1": 3.5, "p": 0.77}, {"w": "to", "t0": 3.5, "t1": 3.68, "p": 1.0}, {"w": "the", "t0": 3.68, "t1": 3.84, "p": 0.99}, {"w": "escrow", "t0": 3.84, "t1": 4.26, "p": 0.85}, {"w": "account", "t0": 4.26, "t1": 4.54, "p": 0.99}, {"w": "today.", "t0": 4.54, "t1": 4.92, "p": 1.0}, {"w": "This", "t0": 5.48, "t1": 6.04, "p": 0.99}, {"w": "is", "t0": 6.04, "t1": 6.2, "p": 1.0}, {"w": "confidential", "t0": 6.2, "t1": 6.7, "p": 1.0}, {"w": "until", "t0": 6.7, "t1": 7.2, "p": 0.99}, {"w": "the", "t0": 7.2, "t1": 7.44, "p": 1.0}, {"w": "acquisition", "t0": 7.44, "t1": 7.9, "p": 1.0}, {"w": "is", "t0": 7.9, "t1": 8.22, "p": 1.0}, {"w": "announced.", "t0": 8.22, "t1": 8.74, "p": 1.0}, {"w": "Do", "t0": 9.52, "t1": 9.82, "p": 0.99}, {"w": "not", "t0": 9.82, "t1": 9.98, "p": 0.99}, {"w": "discuss", "t0": 9.98, "t1": 10.36, "p": 1.0}, {"w": "with", "t0": 10.36, "t1": 10.62, "p": 1.0}, {"w": "anyone", "t0": 10.62, "t1": 11.02, "p": 0.99}, {"w": "in", "t0": 11.02, "t1": 11.24, "p": 1.0}, {"w": "finance.", "t0": 11.24, "t1": 11.6, "p": 0.87}], "engine": "faster-whisper/base"}}
A6: 5 | B6: MRG-0463 | C6: audio | D6: it_helpdesk.wav | E6: audio/wav | F6: fba1753c8ba9b178f7aa118c0f2625ee3adb89d4d03220b490e41ee78cb61997 | G6: 352134 | H6: fb/fba1753c8ba9b178f7aa118c0f2625ee3adb89d4d03220b490e41ee78cb61997.wav | I6: 11 | J6: {"asr": {"text": "IT Team SE Valra Hoon Opca Account Reset Ho Reha High Jo OTP AIO Highwell Bata Do Jaldi 10 Minute Main Lock Ho Jiega", "language": "en", "language_p": 1.0, "words": [{"w": "IT", "t0": 0.0, "t1": 0.38, "p": 0.62}, {"w": "Team", "t0": 0.38, "t1": 0.76, "p": 0.56}, {"w": "SE", "t0": 0.76, "t1": 1.02, "p": 0.48}, {"w": "Valra", "t0": 1.02, "t1": 1.46, "p": 0.38}, {"w": "Hoon", "t0": 1.46, "t1": 1.92, "p": 0.47}, {"w": "Opca", "t0": 2.64, "t1": 3.12, "p": 0.3}, {"w": "Account", "t0": 3.12, "t1": 3.44, "p": 0.53}, {"w": "Reset", "t0": 3.44, "t1": 3.88, "p": 0.84}, {"w": "Ho", "t0": 3.88, "t1": 4.06, "p": 0.38}, {"w": "Reha", "t0": 4.06, "t1": 4.36, "p": 0.38}, {"w": "High", "t0": 4.36, "t1": 4.76, "p": 0.17}, {"w": "Jo", "t0": 5.28, "t1": 5.66, "p": 0.24}, {"w": "OTP", "t0": 5.66, "t1": 6.08, "p": 0.75}, {"w": "AIO", "t0": 6.08, "t1": 6.58, "p": 0.24}, {"w": "Highwell", "t0": 6.58, "t1": 6.94, "p": 0.07}, {"w": "Bata", "t0": 6.94, "t1": 7.24, "p": 0.34}, {"w": "Do", "t0": 7.24, "t1": 7.44, "p": 0.21}, {"w": "Jaldi", "t0": 7.44, "t1": 7.96, "p": 0.56}, {"w": "10", "t0": 7.96, "t1": 8.6, "p": 0.52}, {"w": "Minute", "t0": 8.6, "t1": 8.8, "p": 0.59}, {"w": "Main", "t0": 8.8, "t1": 9.08, "p": 0.87}, {"w": "Lock", "t0": 9.08, "t1": 9.34, "p": 0.71}, {"w": "Ho", "t0": 9.34, "t1": 9.6, "p": 0.7}, {"w": "Jiega", "t0": 9.6, "t1": 10.1, "p": 0.56}], "engine": "faster-whisper/base"}}
A7: 6 | B7: MRG-0464 | C7: audio | D7: controller_voice.wav | E7: audio/wav | F7: 6d3028c25ad82112b875e63617be77b57b8b5905dba20e4fea21637999ea2a0e | G7: 224044 | H7: 6d/6d3028c25ad82112b875e63617be77b57b8b5905dba20e4fea21637999ea2a0e.wav | I7: 7 | J7: {}
A8: 7 | B8: MRG-0465 | C8: audio | D8: en_cfo_payment.wav | E8: audio/wav | F8: 9c2dc59996e0c43f7bc7eaf65d9d5326eedb9819ddecd62acb29b0cacf9516a4 | G8: 516140 | H8: 9c/9c2dc59996e0c43f7bc7eaf65d9d5326eedb9819ddecd62acb29b0cacf9516a4.wav | I8: 16.13 | J8: {"asr": {"text": "Hi, this is Rajesh, the CFO. I'm in a board meeting. Transfer 12 lakh rupees to the new vendor account today and keep it confidential. Don't call me, just do it before 4.", "language": "en", "language_p": 1.0, "words": [{"w": "Hi,", "t0": 0.0, "t1": 0.38, "p": 0.9}, {"w": "this", "t0": 0.7, "t1": 0.92, "p": 0.79}, {"w": "is", "t0": 0.92, "t1": 1.22, "p": 0.99}, {"w": "Rajesh,", "t0": 1.22, "t1": 1.64, "p": 0.97}, {"w": "the", "t0": 2.02, "t1": 2.12, "p": 0.97}, {"w": "CFO.", "t0": 2.12, "t1": 2.58, "p": 0.91}, {"w": "I'm", "t0": 3.38, "t1": 3.88, "p": 0.79}, {"w": "in", "t0": 3.88, "t1": 4.04, "p": 0.99}, {"w": "a", "t0": 4.04, "t1": 4.16, "p": 0.98}, {"w": "board", "t0": 4.16, "t1": 4.42, "p": 0.86}, {"w": "meeting.", "t0": 4.42, "t1": 4.92, "p": 1.0}, {"w": "Transfer", "t0": 5.82, "t1": 6.36, "p": 0.97}, {"w": "12", "t0": 6.36, "t1": 6.9, "p": 0.83}, {"w": "lakh", "t0": 6.9, "t1": 7.14, "p": 0.44}, {"w": "rupees", "t0": 7.14, "t1": 7.58, "p": 0.88}, {"w": "to", "t0": 7.58, "t1": 7.92, "p": 0.99}, {"w": "the", "t0": 7.92, "t1": 8.06, "p": 0.97}, {"w": "new", "t0": 8.06, "t1": 8.28, "p": 0.88}, {"w": "vendor", "t0": 8.28, "t1": 8.64, "p": 0.72}, {"w": "account", "t0": 8.64, "t1": 9.08, "p": 0.99}, {"w": "today", "t0": 9.08, "t1": 9.58, "p": 0.99}, {"w": "and", "t0": 9.58, "t1": 10.2, "p": 0.66}, {"w": "keep", "t0": 10.2, "t1": 10.46, "p": 1.0}, {"w": "it", "t0": 10.46, "t1": 10.7, "p": 1.0}, {"w": "confidential.", "t0": 10.7, "t1": 11.34, "p": 1.0}, {"w": "Don't", "t0": 12.26, "t1": 12.76, "p": 0.97}, {"w": "call", "t0": 12.76, "t1": 12.98, "p": 0.98}, {"w": "me,", "t0": 12.98, "t1": 13.28, "p": 0.99}, {"w": "just", "t0": 13.68, "t1": 13.86, "p": 0.95}, {"w": "do", "t0": 13.86, "t1": 14.22, "p": 1.0}, {"w": "it", "t0": 14.22, "t1": 14.44, "p": 1.0}, {"w": "before", "t0": 14.44, "t1": 14.78, "p": 0.99}, {"w": "4.", "t0": 14.78, "t1": 15.24, "p": 0.91}], "engine": "faster-whisper/base"}}
A9: 8 | B9: MRG-0466 | C9: audio | D9: hi_digital_arrest.wav | E9: audio/wav | F9: 199e85bffa3c9e5c809b3a12a4e6b87d8549803328e29a7edbfb76177670d5e8 | G9: 473900 | H9: 19/199e85bffa3c9e5c809b3a12a4e6b87d8549803328e29a7edbfb76177670d5e8.wav | I9: 14.81 | J9: {"asr": {"text": "I am speaking with CBI. Your name is Drugs parcel. Don't call anyone. Send two lakh rupees to the judge.", "language": "hi-Latn (Hinglish)", "language_p": 1.0, "words": [{"w": "I", "t0": 0.0, "t1": 0.42, "p": 0.68}, {"w": "am", "t0": 0.42, "t1": 0.42, "p": 0.79}, {"w": "speaking", "t0": 0.42, "t1": 0.42, "p": 0.69}, {"w": "with", "t0": 0.42, "t1": 0.42, "p": 0.29}, {"w": "CBI.", "t0": 0.42, "t1": 1.02, "p": 0.77}, {"w": "Your", "t0": 3.32, "t1": 3.94, "p": 0.23}, {"w": "name", "t0": 3.94, "t1": 4.3, "p": 0.95}, {"w": "is", "t0": 4.3, "t1": 4.64, "p": 0.66}, {"w": "Drugs", "t0": 4.64, "t1": 4.98, "p": 0.55}, {"w": "parcel.", "t0": 4.98, "t1": 5.6, "p": 0.32}, {"w": "Don't", "t0": 6.56, "t1": 7.78, "p": 0.81}, {"w": "call", "t0": 7.78, "t1": 7.78, "p": 0.42}, {"w": "anyone.", "t0": 7.78, "t1": 8.82, "p": 0.69}, {"w": "Send", "t0": 10.46, "t1": 11.7, "p": 0.01}, {"w": "two", "t0": 11.7, "t1": 12.06, "p": 0.58}, {"w": "lakh", "t0": 12.06, "t1": 12.4, "p": 0.52}, {"w": "rupees", "t0": 12.4, "t1": 12.78, "p": 0.33}, {"w": "to", "t0": 12.78, "t1": 13.7, "p": 0.29}, {"w": "the", "t0": 13.7, "t1": 13.7, "p": 0.46}, {"w": "judge.", "t0": 13.7, "t1": 13.7, "p": 0.31}], "engine": "faster-whisper/base"}}
A10: 9 | B10: MRG-0467 | C10: audio | D10: en_benign_townhall.wav | E10: audio/wav | F10: 19e41e05058d84b2666886cfba24e5c95288ff94c9ce177d43005c49efdfeb1f | G10: 303404 | H10: 19/19e41e05058d84b2666886cfba24e5c95288ff94c9ce177d43005c49efdfeb1f.wav | I10: 9.48 | J10: {"asr": {"text": "Reminder, the quarterly town hall moves to Friday at 4pm the agenda is in your calendar invite. See you there.", "language": "en", "language_p": 1.0, "words": [{"w": "Reminder,", "t0": 0.0, "t1": 0.78, "p": 0.9}, {"w": "the", "t0": 1.16, "t1": 1.3, "p": 0.91}, {"w": "quarterly", "t0": 1.3, "t1": 1.74, "p": 0.83}, {"w": "town", "t0": 1.74, "t1": 2.06, "p": 0.87}, {"w": "hall", "t0": 2.06, "t1": 2.34, "p": 0.99}, {"w": "moves", "t0": 2.34, "t1": 2.62, "p": 0.98}, {"w": "to", "t0": 2.62, "t1": 2.9, "p": 0.99}, {"w": "Friday", "t0": 2.9, "t1": 3.24, "p": 0.95}, {"w": "at", "t0": 3.24, "t1": 3.64, "p": 0.96}, {"w": "4pm", "t0": 3.64, "t1": 4.3, "p": 0.67}, {"w": "the", "t0": 4.3, "t1": 4.56, "p": 0.6}, {"w": "agenda", "t0": 4.56, "t1": 5.0, "p": 0.96}, {"w": "is", "t0": 5.0, "t1": 5.34, "p": 0.97}, {"w": "in", "t0": 5.34, "t1": 5.48, "p": 1.0}, {"w": "your", "t0": 5.48, "t1": 5.62, "p": 0.99}, {"w": "calendar", "t0": 5.62, "t1": 6.1, "p": 0.97}, {"w": "invite.", "t0": 6.1, "t1": 6.66, "p": 0.94}, {"w": "See", "t0": 7.36, "t1": 8.04, "p": 0.98}, {"w": "you", "t0": 8.04, "t1": 8.2, "p": 0.97}, {"w": "there.", "t0": 8.2, "t1": 8.42, "p": 0.99}], "engine": "faster-whisper/base"}}
A11: 10 | B11: MRG-0468 | C11: audio | D11: spk6930_000.flac | E11: audio/flac | F11: 3f06a2712cadb8d5bca9618a1560112d7e1e0c229e0dd7f0c4f736f4bcb661b3 | G11: 217708 | H11: 3f/3f06a2712cadb8d5bca9618a1560112d7e1e0c229e0dd7f0c4f736f4bcb661b3.flac | I11: 10.81 | J11: {"asr": {"text": "The night was clear, starlet and splendid. The tempest had passed away, and the sweet influences of the evening had restored life, peace and security everywhere.", "language": "en", "language_p": 1.0, "words": [{"w": "The", "t0": 0.0, "t1": 0.4, "p": 0.86}, {"w": "night", "t0": 0.4, "t1": 0.62, "p": 0.98}, {"w": "was", "t0": 0.62, "t1": 0.86, "p": 1.0}, {"w": "clear,", "t0": 0.86, "t1": 1.18, "p": 1.0}, {"w": "starlet", "t0": 1.52, "t1": 1.86, "p": 0.52}, {"w": "and", "t0": 1.86, "t1": 2.18, "p": 0.76}, {"w": "splendid.", "t0": 2.18, "t1": 2.86, "p": 0.93}, {"w": "The", "t0": 3.26, "t1": 3.3, "p": 0.99}, {"w": "tempest", "t0": 3.3, "t1": 3.76, "p": 0.95}, {"w": "had", "t0": 3.76, "t1": 3.92, "p": 0.99}, {"w": "passed", "t0": 3.92, "t1": 4.28, "p": 0.99}, {"w": "away,", "t0": 4.28, "t1": 4.68, "p": 1.0}, {"w": "and", "t0": 4.92, "t1": 4.96, "p": 0.98}, {"w": "the", "t0": 4.96, "t1": 5.1, "p": 1.0}, {"w": "sweet", "t0": 5.1, "t1": 5.46, "p": 0.99}, {"w": "influences", "t0": 5.46, "t1": 6.14, "p": 0.99}, {"w": "of", "t0": 6.14, "t1": 6.44, "p": 1.0}, {"w": "the", "t0": 6.44, "t1": 6.64, "p": 0.99}, {"w": "evening", "t0": 6.64, "t1": 6.94, "p": 1.0}, {"w": "had", "t0": 6.94, "t1": 7.18, "p": 0.97}, {"w": "restored", "t0": 7.18, "t1": 7.64, "p": 0.99}, {"w": "life,", "t0": 7.64, "t1": 8.26, "p": 0.99}, {"w": "peace", "t0": 8.78, "t1": 8.9, "p": 1.0}, {"w": "and", "t0": 8.9, "t1": 9.18, "p": 0.56}, {"w": "security", "t0": 9.18, "t1": 9.72, "p": 1.0}, {"w": "everywhere.", "t0": 9.72, "t1": 10.36, "p": 0.95}], "engine": "faster-whisper/base"}}
A12: 11 | B12: MRG-0469 | C12: audio | D12: spk6930_000.flac | E12: audio/flac | F12: 3f06a2712cadb8d5bca9618a1560112d7e1e0c229e0dd7f0c4f736f4bcb661b3 | G12: 217708 | H12: 3f/3f06a2712cadb8d5bca9618a1560112d7e1e0c229e0dd7f0c4f736f4bcb661b3.flac | I12: 10.81 | J12: {"asr": {"text": "The night was clear, starlet and splendid. The tempest had passed away, and the sweet influences of the evening had restored life, peace and security everywhere.", "language": "en", "language_p": 1.0, "words": [{"w": "The", "t0": 0.0, "t1": 0.4, "p": 0.86}, {"w": "night", "t0": 0.4, "t1": 0.62, "p": 0.98}, {"w": "was", "t0": 0.62, "t1": 0.86, "p": 1.0}, {"w": "clear,", "t0": 0.86, "t1": 1.18, "p": 1.0}, {"w": "starlet", "t0": 1.52, "t1": 1.86, "p": 0.52}, {"w": "and", "t0": 1.86, "t1": 2.18, "p": 0.76}, {"w": "splendid.", "t0": 2.18, "t1": 2.86, "p": 0.93}, {"w": "The", "t0": 3.26, "t1": 3.3, "p": 0.99}, {"w": "tempest", "t0": 3.3, "t1": 3.76, "p": 0.95}, {"w": "had", "t0": 3.76, "t1": 3.92, "p": 0.99}, {"w": "passed", "t0": 3.92, "t1": 4.28, "p": 0.99}, {"w": "away,", "t0": 4.28, "t1": 4.68, "p": 1.0}, {"w": "and", "t0": 4.92, "t1": 4.96, "p": 0.98}, {"w": "the", "t0": 4.96, "t1": 5.1, "p": 1.0}, {"w": "sweet", "t0": 5.1, "t1": 5.46, "p": 0.99}, {"w": "influences", "t0": 5.46, "t1": 6.14, "p": 0.99}, {"w": "of", "t0": 6.14, "t1": 6.44, "p": 1.0}, {"w": "the", "t0": 6.44, "t1": 6.64, "p": 0.99}, {"w": "evening", "t0": 6.64, "t1": 6.94, "p": 1.0}, {"w": "had", "t0": 6.94, "t1": 7.18, "p": 0.97}, {"w": "restored", "t0": 7.18, "t1": 7.64, "p": 0.99}, {"w": "life,", "t0": 7.64, "t1": 8.26, "p": 0.99}, {"w": "peace", "t0": 8.78, "t1": 8.9, "p": 1.0}, {"w": "and", "t0": 8.9, "t1": 9.18, "p": 0.56}, {"w": "security", "t0": 9.18, "t1": 9.72, "p": 1.0}, {"w": "everywhere.", "t0": 9.72, "t1": 10.36, "p": 0.95}], "engine": "faster-whisper/base"}}
A13: 12 | B13: MRG-0470 | C13: image | D13: 02.png | E13: image/png | F13: ecd406882d7865d068ce1df66d8661c7e8943be2e2205fce1f43bd277e7f8199 | G13: 380588 | H13: ec/ecd406882d7865d068ce1df66d8661c7e8943be2e2205fce1f43bd277e7f8199.png | J13: {"ocr": {"text": "MIRAGE RED TEAM\u00b7SYNTHETIC", "lines": [{"text": "MIRAGE RED TEAM\u00b7SYNTHETIC", "conf": 0.96, "box": [0.6875, 0.9668, 0.3027, 0.0312]}], "engine": "rapidocr"}}
A14: 13 | B14: MRG-0471 | C14: image | D14: 000.jpg | E14: image/jpeg | F14: fe553ba0662dcbb1a66e8aabcbd421831bb3f31536ab89ff8c464a3fd59387c6 | G14: 22901 | H14: fe/fe553ba0662dcbb1a66e8aabcbd421831bb3f31536ab89ff8c464a3fd59387c6.jpg | J14: {}
A15: 14 | B15: MRG-0477 | C15: audio | D15: ta_otp.wav | E15: audio/wav | F15: 0e30f0bdfc206f4787d0a4ec69f695f50db7d3f57c858dbb876fbc1507e1fb45 | G15: 330284 | H15: 0e/0e30f0bdfc206f4787d0a4ec69f695f50db7d3f57c858dbb876fbc1507e1fb45.wav | I15: 10.32 | J15: {"asr": {"text": "\u0bb5\u0ba3\u0b95\u0bcd\u0b95\u0bae\u0bcd \u0ba8\u0bbe\u0ba9\u0bcd \u0bb5\u0ba3\u0bcd\u0b95\u0bbf\u0baf\u0bbf\u0bb2\u0bbf\u0bb0\u0bc1\u0ba8\u0bcd\u0ba4\u0bc1 \u0baa\u0bc7\u0b9a\u0bc1\u0b95\u0bbf\u0bb1\u0bc7\u0ba9\u0bcd \u0b89\u0b99\u0bcd\u0b95\u0bb3\u0bcd \u0b95\u0ba3\u0b95\u0bcd\u0b95\u0bc1 \u0b8e\u0ba9\u0bcd\u0bb1\u0bc1 \u0bae\u0bc1\u0b9f\u0b95\u0bcd\u0b95\u0baa\u0bcd\u0baa\u0b9f\u0bc1\u0bae\u0bcd \u0b89\u0b99\u0bcd\u0b95\u0bb3\u0bcd \u0bae\u0bc1\u0baa\u0bcd\u0baa\u0bc8\u0baf\u0bbf\u0bb2\u0bcd \u0b95\u0bc1 \u0bb5\u0ba8\u0bcd\u0ba4\u0bc1 OTP -NNI \u0b89\u0b9f\u0ba9\u0bc7 \u0b9a\u0bca\u0bb2\u0bcd\u0bb2\u0b99\u0bcd\u0b95\u0bb3\u0bcd", "language": "ta", "language_p": 1.0, "words": [{"w": "\u0bb5\u0ba3\u0b95\u0bcd\u0b95\u0bae\u0bcd", "t0": 0.0, "t1": 0.9, "p": 0.8}, {"w": "\u0ba8\u0bbe\u0ba9\u0bcd", "t0": 0.9, "t1": 1.4, "p": 0.83}, {"w": "\u0bb5\u0ba3\u0bcd\u0b95\u0bbf\u0baf\u0bbf\u0bb2\u0bbf\u0bb0\u0bc1\u0ba8\u0bcd\u0ba4\u0bc1", "t0": 1.4, "t1": 2.18, "p": 0.73}, {"w": "\u0baa\u0bc7\u0b9a\u0bc1\u0b95\u0bbf\u0bb1\u0bc7\u0ba9\u0bcd", "t0": 2.18, "t1": 3.0, "p": 0.81}, {"w": "\u0b89\u0b99\u0bcd\u0b95\u0bb3\u0bcd", "t0": 3.8, "t1": 4.2, "p": 0.92}, {"w": "\u0b95\u0ba3\u0b95\u0bcd\u0b95\u0bc1", "t0": 4.2, "t1": 4.58, "p": 0.89}, {"w": "\u0b8e\u0ba9\u0bcd\u0bb1\u0bc1", "t0": 4.58, "t1": 4.94, "p": 0.76}, {"w": "\u0bae\u0bc1\u0b9f\u0b95\u0bcd\u0b95\u0baa\u0bcd\u0baa\u0b9f\u0bc1\u0bae\u0bcd", "t0": 4.94, "t1": 6.3, "p": 0.78}, {"w": "\u0b89\u0b99\u0bcd\u0b95\u0bb3\u0bcd", "t0": 6.3, "t1": 7.14, "p": 0.99}, {"w": "\u0bae\u0bc1\u0baa\u0bcd\u0baa\u0bc8\u0baf\u0bbf\u0bb2\u0bcd", "t0": 7.14, "t1": 7.56, "p": 0.7}, {"w": "\u0b95\u0bc1", "t0": 7.56, "t1": 7.72, "p": 0.35}, {"w": "\u0bb5\u0ba8\u0bcd\u0ba4\u0bc1", "t0": 7.72, "t1": 8.18, "p": 0.74}, {"w": "OTP", "t0": 8.18, "t1": 8.6, "p": 0.51}, {"w": "-NNI", "t0": 8.6, "t1": 9.12, "p": 0.48}, {"w": "\u0b89\u0b9f\u0ba9\u0bc7", "t0": 9.12, "t1": 9.54, "p": 0.7}, {"w": "\u0b9a\u0bca\u0bb2\u0bcd\u0bb2\u0b99\u0bcd\u0b …(truncated)
A16: 15 | B16: MRG-0478 | C16: audio | D16: google_tamil_m_spk3191_002__noise.wav | E16: audio/wav | F16: 90db5ae7d9061875784f6361967a0f31023fdb9b0c5e15c1e72bd6e964ccae17 | G16: 155692 | H16: 90/90db5ae7d9061875784f6361967a0f31023fdb9b0c5e15c1e72bd6e964ccae17.wav | I16: 4.86 | J16: {"asr": {"text": "\u0ba8\u0bcb\u0b95\u0bcd\u0b95\u0bbf\u0baf\u0bbe \u0bae\u0bc8\u0b95\u0bcd\u0b95\u0bb0\u0b9a\u0bcd \u0b9a\u0bbe\u0baa\u0bcd\u0b9f\u0bc1\u0b9f\u0ba9\u0bcd \u0b8e\u0ba9\u0bcd\u0ba9 \u0b87\u0ba8\u0bcd\u0ba4 \u0b9a\u0bc6\u0baf\u0bcd\u0baf\u0bb2\u0bcd \u0baa\u0b9f \u0bae\u0bc1\u0b9f\u0bbf\u0bb5\u0bc7", "language": "ta", "language_p": 1.0, "words": [{"w": "\u0ba8\u0bcb\u0b95\u0bcd\u0b95\u0bbf\u0baf\u0bbe", "t0": 0.4, "t1": 1.2, "p": 0.61}, {"w": "\u0bae\u0bc8\u0b95\u0bcd\u0b95\u0bb0\u0b9a\u0bcd", "t0": 1.2, "t1": 1.68, "p": 0.51}, {"w": "\u0b9a\u0bbe\u0baa\u0bcd\u0b9f\u0bc1\u0b9f\u0ba9\u0bcd", "t0": 1.68, "t1": 2.32, "p": 0.74}, {"w": "\u0b8e\u0ba9\u0bcd\u0ba9", "t0": 2.32, "t1": 2.48, "p": 0.79}, {"w": "\u0b87\u0ba8\u0bcd\u0ba4", "t0": 2.48, "t1": 2.68, "p": 0.88}, {"w": "\u0b9a\u0bc6\u0baf\u0bcd\u0baf\u0bb2\u0bcd", "t0": 2.68, "t1": 3.24, "p": 0.71}, {"w": "\u0baa\u0b9f", "t0": 3.24, "t1": 3.32, "p": 0.7}, {"w": "\u0bae\u0bc1\u0b9f\u0bbf\u0bb5\u0bc7", "t0": 3.32, "t1": 3.72, "p": 0.79}], "engine": "faster-whisper/base"}}
A17: 16 | B17: MRG-0479 | C17: image | D17: 07_whatsapp_cfo_chat_screenshot.png | E17: image/png | F17: 9352f46f9ef1860dd9fd6bb00b7654c4682122a1663ac24c0671aae1d90d1d41 | G17: 42090 | H17: 93/9352f46f9ef1860dd9fd6bb00b7654c4682122a1663ac24c0671aae1d90d1d41.png | J17: {"ocr": {"text": "Rajesh Mehta (CFO)\nonline\nHi Kavita, Rajesh here. In a board meeting,\ncan't talk.\nPlease process Rs 9,80,000 to Orbit\nSupplies'new account 600112233445 IFSC\nHDFC0001234 today.\nSure, should I loop in audit?\nNo,keep this between us until the audit\ncloses.Very urgent,before 4 PM.", "lines": [{"text": "Rajesh Mehta (CFO)", "conf": 0.99, "box": [0.0944, 0.0294, 0.2875, 0.0496]}, {"text": "online", "conf": 0.99, "box": [0.0944, 0.0882, 0.0708, 0.0349]}, {"text": "Hi Kavita, Rajesh here. In a board meeting,", "conf": 0.96, "box": [0.0431, 0.204, 0.5875, 0.0496]}, {"text": "can't talk.", "conf": 0.95, "box": [0.0444, 0.2629, 0.1278, 0.0404]}, {"text": "Please process Rs 9,80,000 to Orbit", "conf": 0.97, "box": [0.0458, 0.3824, 0.4931, 0.0423]}, {"text": "Supplies'new account 600112233445 IFSC", "conf": 0.97, "box": [0.0444, 0.4357, 0.5944, 0.046]}, {"text": "HDFC0001234 today.", "conf": 0.99, "box": [0.0431, 0.4871, 0.2972, 0.0533]}, {"text": "Sure, should I loop in audit?", "conf": 0.97, "box": [0.5764, 0.6158, 0.3778, 0.0404]}, {"text": "No,keep this between us until the audit", "conf": 0.96, "box": [0.0431, 0.7353, 0.5403, 0.0423]}, {"text": "closes.Very urgent,before 4 PM.", "conf": 0.99, "box": [0.0458, 0.7941, 0.4514, 0.0386]}], "engine": "rapidocr"}}
A18: 17 | B18: MRG-0480 | C18: text | D18: 01_vendor_bank_change_bec.eml | E18: text/plain | F18: f8a7017d25072502f6e6cf4390b82f690ceaf4c6fac0c321f87dbf16a6856e79 | G18: 960 | H18: f8/f8a7017d25072502f6e6cf4390b82f690ceaf4c6fac0c321f87dbf16a6856e79.eml | J18: {}
A19: 18 | B19: MRG-0481 | C19: text | D19: 02_ceo_gift_cards_urgent.eml | E19: text/plain | F19: 51354c917e32e3aa256912f89bf4f26f08760b04a60e3b776318ec14c07b6b94 | G19: 575 | H19: 51/51354c917e32e3aa256912f89bf4f26f08760b04a60e3b776318ec14c07b6b94.eml | J19: {}
A20: 19 | B20: MRG-0482 | C20: text | D20: 03_password_expiry_phishing.eml | E20: text/plain | F20: 02c67d1cd12ff0680714a89d74039101e5632a15e1e8418e3a639c49761225b1 | G20: 551 | H20: 02/02c67d1cd12ff0680714a89d74039101e5632a15e1e8418e3a639c49761225b1.eml | J20: {}
A21: 20 | B21: MRG-0483 | C21: text | D21: 04_benign_hr_newsletter.eml | E21: text/plain | F21: 4bf350238f37abd18e43521f591d257eea2ddb62e0c6a970acfce20f6ee7d262 | G21: 452 | H21: 4b/4bf350238f37abd18e43521f591d257eea2ddb62e0c6a970acfce20f6ee7d262.eml | J21: {}
A22: 21 | B22: MRG-0484 | C22: audio | D22: cfo_voice_note.ogg | E22: audio/ogg | F22: 76804f5c9ce590d9736b14708da395f59772b54da34102673c29f621cbcedcbd | G22: 45575 | H22: 76/76804f5c9ce590d9736b14708da395f59772b54da34102673c29f621cbcedcbd.ogg | I22: 17.62 | J22: {"asr": {"text": "Hi, it's Rajesh from the CFO office. I'm in a board meeting and can't take calls. Please wire 48 lakh rupees to the new vendor account before 4 pm it's urgent and confidential. Don't loop in audit.", "language": "en", "language_p": 1.0, "words": [{"w": "Hi,", "t0": 0.0, "t1": 0.38, "p": 0.9}, {"w": "it's", "t0": 0.72, "t1": 1.16, "p": 0.69}, {"w": "Rajesh", "t0": 1.16, "t1": 1.5, "p": 0.98}, {"w": "from", "t0": 1.5, "t1": 1.78, "p": 0.99}, {"w": "the", "t0": 1.78, "t1": 1.98, "p": 0.97}, {"w": "CFO", "t0": 1.98, "t1": 2.4, "p": 0.85}, {"w": "office.", "t0": 2.4, "t1": 3.0, "p": 0.75}, {"w": "I'm", "t0": 3.7, "t1": 4.24, "p": 0.9}, {"w": "in", "t0": 4.24, "t1": 4.38, "p": 0.99}, {"w": "a", "t0": 4.38, "t1": 4.5, "p": 0.97}, {"w": "board", "t0": 4.5, "t1": 4.76, "p": 0.92}, {"w": "meeting", "t0": 4.76, "t1": 5.22, "p": 1.0}, {"w": "and", "t0": 5.22, "t1": 5.78, "p": 0.87}, {"w": "can't", "t0": 5.78, "t1": 6.18, "p": 0.96}, {"w": "take", "t0": 6.18, "t1": 6.44, "p": 1.0}, {"w": "calls.", "t0": 6.44, "t1": 6.84, "p": 0.97}, {"w": "Please", "t0": 7.86, "t1": 8.12, "p": 0.98}, {"w": "wire", "t0": 8.12, "t1": 8.52, "p": 0.87}, {"w": "48", "t0": 8.52, "t1": 9.34, "p": 0.94}, {"w": "lakh", "t0": 9.34, "t1": 9.7, "p": 0.31}, {"w": "rupees", "t0": 9.7, "t1": 10.14, "p": 0.89}, {"w": "to", "t0": 10.14, "t1": 10.48, "p": 0.99}, {"w": "the", "t0": 10.48, "t1": 10.62, "p": 0.99}, {"w": "new", "t0": 10.62, "t1": 10.84, "p": 0.85}, {"w": "vendor", "t0": 10.84, "t1": 11.18, "p": 0.81}, {"w": "account", "t0": 11.18, "t1": 11.66, "p": 0.99}, {"w": "before", "t0": 11.66, "t1": 12.16, "p": 0.92}, {"w": "4", "t0": 12.16, "t1": 12.7, "p": 0.98}, {"w": "pm", "t0": 12.7, "t1": 13.02, "p": 0.33}, {"w": "it's", "t0": 13.02, "t1": 13.54, "p": 0.68}, {"w": "urgent", "t0": 13.54, "t1": 13.86, "p": 0.98}, {"w": "and", "t0": 13.86, "t1": 14.26, "p": 0.98}, {"w": "confidential.", "t0": 14.26, "t1": 14.94, "p": 1.0}, {"w": "Don't", "t0": 15.42, "t1": 15.72, "p": 0.93}, {"w": "loop", …(truncated)
A23: 22 | B23: MRG-0485 | C23: video | D23: video_call.mp4 | E23: video/mp4 | F23: c82097dc6a47d2309350a516a095c5a8eb99a548c9001f7dcf3bc26eff30d2d0 | G23: 378965 | H23: c8/c82097dc6a47d2309350a516a095c5a8eb99a548c9001f7dcf3bc26eff30d2d0.mp4 | I23: 23.1 | J23: {"asr": {"text": "This is Inspector Sharma from the CBI CyberSair. A parcel in your name has illegal items and an arrest warrant is issued. Stay on this video call and do not disconnect. Transfer your savings to the RBI verification account to avoid arrest. Do not tell anyone.", "language": "en", "language_p": 1.0, "words": [{"w": "This", "t0": 0.0, "t1": 0.4, "p": 0.93}, {"w": "is", "t0": 0.4, "t1": 0.7, "p": 0.99}, {"w": "Inspector", "t0": 0.7, "t1": 1.34, "p": 0.87}, {"w": "Sharma", "t0": 1.34, "t1": 1.84, "p": 0.97}, {"w": "from", "t0": 1.84, "t1": 2.14, "p": 0.98}, {"w": "the", "t0": 2.14, "t1": 2.3, "p": 0.93}, {"w": "CBI", "t0": 2.3, "t1": 2.84, "p": 0.75}, {"w": "CyberSair.", "t0": 2.84, "t1": 3.7, "p": 0.23}, {"w": "A", "t0": 4.36, "t1": 4.92, "p": 0.82}, {"w": "parcel", "t0": 4.92, "t1": 5.2, "p": 0.98}, {"w": "in", "t0": 5.2, "t1": 5.56, "p": 0.98}, {"w": "your", "t0": 5.56, "t1": 5.8, "p": 0.99}, {"w": "name", "t0": 5.8, "t1": 6.14, "p": 0.97}, {"w": "has", "t0": 6.14, "t1": 6.62, "p": 0.99}, {"w": "illegal", "t0": 6.62, "t1": 7.02, "p": 0.98}, {"w": "items", "t0": 7.02, "t1": 7.54, "p": 0.98}, {"w": "and", "t0": 7.54, "t1": 8.1, "p": 0.79}, {"w": "an", "t0": 8.1, "t1": 8.36, "p": 0.85}, {"w": "arrest", "t0": 8.36, "t1": 8.56, "p": 0.99}, {"w": "warrant", "t0": 8.56, "t1": 9.04, "p": 1.0}, {"w": "is", "t0": 9.04, "t1": 9.38, "p": 0.96}, {"w": "issued.", "t0": 9.38, "t1": 9.72, "p": 0.99}, {"w": "Stay", "t0": 10.34, "t1": 11.06, "p": 0.97}, {"w": "on", "t0": 11.06, "t1": 11.36, "p": 1.0}, {"w": "this", "t0": 11.36, "t1": 11.68, "p": 0.99}, {"w": "video", "t0": 11.68, "t1": 12.06, "p": 0.98}, {"w": "call", "t0": 12.06, "t1": 12.38, "p": 0.93}, {"w": "and", "t0": 12.38, "t1": 12.9, "p": 0.93}, {"w": "do", "t0": 12.9, "t1": 13.08, "p": 0.97}, {"w": "not", "t0": 13.08, "t1": 13.32, "p": 0.99}, {"w": "disconnect.", "t0": 13.32, "t1": 13.92, "p": 1.0}, {"w": "Transfer", "t0": 14.86, "t1": 15.48, "p": 0.98}, {"w": "your", "t0": 15.48, "t1": 15.82, "p": 0.99}, {" …(truncated)
A24: 23 | B24: MRG-0486 | C24: audio | D24: papa_voice.ogg | E24: audio/ogg | F24: 5bc20c8a106e85862e3a8d71c9ba55d57d863e6ab5d75e170636c2243ddd4e23 | G24: 38664 | H24: 5b/5bc20c8a106e85862e3a8d71c9ba55d57d863e6ab5d75e170636c2243ddd4e23.ogg | I24: 16.99 | J24: {"asr": {"text": "Papa, I am. Accident is over and phone is broken. This is the number of friends.", "language": "hi-Latn (Hinglish)", "language_p": 1.0, "words": [{"w": "Papa,", "t0": 0.0, "t1": 0.58, "p": 0.37}, {"w": "I", "t0": 0.9, "t1": 1.3, "p": 0.89}, {"w": "am.", "t0": 1.3, "t1": 1.6, "p": 0.79}, {"w": "Accident", "t0": 2.62, "t1": 3.26, "p": 0.58}, {"w": "is", "t0": 3.26, "t1": 3.52, "p": 0.65}, {"w": "over", "t0": 3.52, "t1": 3.72, "p": 0.08}, {"w": "and", "t0": 3.72, "t1": 4.22, "p": 0.69}, {"w": "phone", "t0": 4.22, "t1": 4.54, "p": 0.23}, {"w": "is", "t0": 4.54, "t1": 4.8, "p": 0.7}, {"w": "broken.", "t0": 4.8, "t1": 4.96, "p": 0.62}, {"w": "This", "t0": 5.44, "t1": 5.72, "p": 0.69}, {"w": "is", "t0": 5.72, "t1": 6.14, "p": 0.93}, {"w": "the", "t0": 6.14, "t1": 6.3, "p": 0.66}, {"w": "number", "t0": 6.3, "t1": 6.62, "p": 0.67}, {"w": "of", "t0": 6.62, "t1": 6.78, "p": 0.95}, {"w": "friends.", "t0": 6.78, "t1": 6.78, "p": 0.75}], "engine": "faster-whisper/base"}}
A25: 24 | B25: MRG-0487 | C25: image | D25: accounts_manager.jpg | E25: image/jpeg | F25: 044c58a1e2a77eb23602a272ef458789c1e9fe7ff494c7a7adb14ec045624187 | G25: 71244 | H25: 04/044c58a1e2a77eb23602a272ef458789c1e9fe7ff494c7a7adb14ec045624187.jpg | J25: {"ocr": {"text": "MIRAGE RED TEAM\u00b7SYNTHETIC", "lines": [{"text": "MIRAGE RED TEAM\u00b7SYNTHETIC", "conf": 0.98, "box": [0.6914, 0.9688, 0.2969, 0.0273]}], "engine": "rapidocr"}}
A26: 25 | B26: MRG-0487 | C26: text | D26: invoice.eml | E26: text/plain | F26: f8a7017d25072502f6e6cf4390b82f690ceaf4c6fac0c321f87dbf16a6856e79 | G26: 960 | H26: f8/f8a7017d25072502f6e6cf4390b82f690ceaf4c6fac0c321f87dbf16a6856e79.eml | J26: {}
A27: 26 | B27: MRG-0488 | C27: audio | D27: townhall.mp3 | E27: audio/mpeg | F27: e6d8bbfd37a6f671ac1887cebe8cbbb9a77ceb30a0ba791a8c625227c1610534 | G27: 97100 | H27: e6/e6d8bbfd37a6f671ac1887cebe8cbbb9a77ceb30a0ba791a8c625227c1610534.mp3 | I27: 12 | J27: {"asr": {"text": "Good morning team. The quarterly town hall moves to Friday at 4pm in the main auditorium. Snacks will be served. See you there.", "language": "en", "language_p": 1.0, "words": [{"w": "Good", "t0": 0.0, "t1": 0.4, "p": 0.84}, {"w": "morning", "t0": 0.4, "t1": 0.78, "p": 0.81}, {"w": "team.", "t0": 0.78, "t1": 1.26, "p": 0.75}, {"w": "The", "t0": 2.28, "t1": 2.4, "p": 0.98}, {"w": "quarterly", "t0": 2.4, "t1": 2.86, "p": 0.68}, {"w": "town", "t0": 2.86, "t1": 3.18, "p": 0.89}, {"w": "hall", "t0": 3.18, "t1": 3.48, "p": 0.98}, {"w": "moves", "t0": 3.48, "t1": 3.78, "p": 0.99}, {"w": "to", "t0": 3.78, "t1": 4.04, "p": 0.99}, {"w": "Friday", "t0": 4.04, "t1": 4.36, "p": 0.93}, {"w": "at", "t0": 4.36, "t1": 4.74, "p": 0.98}, {"w": "4pm", "t0": 4.74, "t1": 5.38, "p": 0.66}, {"w": "in", "t0": 5.38, "t1": 5.7, "p": 0.97}, {"w": "the", "t0": 5.7, "t1": 5.8, "p": 0.97}, {"w": "main", "t0": 5.8, "t1": 6.12, "p": 0.95}, {"w": "auditorium.", "t0": 6.12, "t1": 6.92, "p": 1.0}, {"w": "Snacks", "t0": 7.92, "t1": 8.4, "p": 0.95}, {"w": "will", "t0": 8.4, "t1": 8.62, "p": 1.0}, {"w": "be", "t0": 8.62, "t1": 8.8, "p": 1.0}, {"w": "served.", "t0": 8.8, "t1": 9.18, "p": 0.99}, {"w": "See", "t0": 10.02, "t1": 10.54, "p": 0.99}, {"w": "you", "t0": 10.54, "t1": 10.7, "p": 0.99}, {"w": "there.", "t0": 10.7, "t1": 10.96, "p": 0.99}], "engine": "faster-whisper/base"}}
A28: 27 | B28: MRG-0489 | C28: audio | D28: papa_voice_note.wav | E28: audio/wav | F28: 8ee650801c14eee68e4b6c098d232806785b31a005cd15483c392f5942151589 | G28: 359182 | H28: 8e/8ee650801c14eee68e4b6c098d232806785b31a005cd15483c392f5942151589.wav | I28: 11.22 | J28: {"asr": {"text": "Beta main hoon, accident ho gaya high, phone toot gaya, pays abi burjo, 75 ,000, G -she -ke -oh mat Pat No Please.", "language": "en", "language_p": 1.0, "words": [{"w": "Beta", "t0": 0.0, "t1": 0.36, "p": 0.56}, {"w": "main", "t0": 0.36, "t1": 0.6, "p": 0.39}, {"w": "hoon,", "t0": 0.6, "t1": 0.96, "p": 0.57}, {"w": "accident", "t0": 1.36, "t1": 1.76, "p": 0.77}, {"w": "ho", "t0": 1.76, "t1": 2.02, "p": 0.53}, {"w": "gaya", "t0": 2.02, "t1": 2.34, "p": 0.52}, {"w": "high,", "t0": 2.34, "t1": 2.74, "p": 0.32}, {"w": "phone", "t0": 3.1, "t1": 3.26, "p": 0.79}, {"w": "toot", "t0": 3.26, "t1": 3.6, "p": 0.69}, {"w": "gaya,", "t0": 3.6, "t1": 3.9, "p": 0.98}, {"w": "pays", "t0": 4.54, "t1": 5.14, "p": 0.43}, {"w": "abi", "t0": 5.14, "t1": 5.42, "p": 0.2}, {"w": "burjo,", "t0": 5.42, "t1": 5.74, "p": 0.73}, {"w": "75", "t0": 6.26, "t1": 6.94, "p": 0.77}, {"w": ",000,", "t0": 6.94, "t1": 8.32, "p": 0.67}, {"w": "G", "t0": 8.54, "t1": 8.74, "p": 0.46}, {"w": "-she", "t0": 8.74, "t1": 8.96, "p": 0.24}, {"w": "-ke", "t0": 8.96, "t1": 9.18, "p": 0.2}, {"w": "-oh", "t0": 9.18, "t1": 9.3, "p": 0.3}, {"w": "mat", "t0": 9.3, "t1": 9.52, "p": 0.32}, {"w": "Pat", "t0": 9.52, "t1": 9.74, "p": 0.14}, {"w": "No", "t0": 9.74, "t1": 9.9, "p": 0.28}, {"w": "Please.", "t0": 9.9, "t1": 10.2, "p": 0.36}], "engine": "faster-whisper/base"}}
A29: 28 | B29: MRG-0490 | C29: audio | D29: papa_voice_note.wav | E29: audio/wav | F29: 8ee650801c14eee68e4b6c098d232806785b31a005cd15483c392f5942151589 | G29: 359182 | H29: 8e/8ee650801c14eee68e4b6c098d232806785b31a005cd15483c392f5942151589.wav | I29: 11.22 | J29: {"asr": {"text": "Beta main hoon, accident ho gaya high, phone toot gaya, pays abi burjo, 75 ,000, G -she -ke -oh mat Pat No Please.", "language": "en", "language_p": 1.0, "words": [{"w": "Beta", "t0": 0.0, "t1": 0.36, "p": 0.56}, {"w": "main", "t0": 0.36, "t1": 0.6, "p": 0.39}, {"w": "hoon,", "t0": 0.6, "t1": 0.96, "p": 0.57}, {"w": "accident", "t0": 1.36, "t1": 1.76, "p": 0.77}, {"w": "ho", "t0": 1.76, "t1": 2.02, "p": 0.53}, {"w": "gaya", "t0": 2.02, "t1": 2.34, "p": 0.52}, {"w": "high,", "t0": 2.34, "t1": 2.74, "p": 0.32}, {"w": "phone", "t0": 3.1, "t1": 3.26, "p": 0.79}, {"w": "toot", "t0": 3.26, "t1": 3.6, "p": 0.69}, {"w": "gaya,", "t0": 3.6, "t1": 3.9, "p": 0.98}, {"w": "pays", "t0": 4.54, "t1": 5.14, "p": 0.43}, {"w": "abi", "t0": 5.14, "t1": 5.42, "p": 0.2}, {"w": "burjo,", "t0": 5.42, "t1": 5.74, "p": 0.73}, {"w": "75", "t0": 6.26, "t1": 6.94, "p": 0.77}, {"w": ",000,", "t0": 6.94, "t1": 8.32, "p": 0.67}, {"w": "G", "t0": 8.54, "t1": 8.74, "p": 0.46}, {"w": "-she", "t0": 8.74, "t1": 8.96, "p": 0.24}, {"w": "-ke", "t0": 8.96, "t1": 9.18, "p": 0.2}, {"w": "-oh", "t0": 9.18, "t1": 9.3, "p": 0.3}, {"w": "mat", "t0": 9.3, "t1": 9.52, "p": 0.32}, {"w": "Pat", "t0": 9.52, "t1": 9.74, "p": 0.14}, {"w": "No", "t0": 9.74, "t1": 9.9, "p": 0.28}, {"w": "Please.", "t0": 9.9, "t1": 10.2, "p": 0.36}], "engine": "faster-whisper/base"}}
A30: 29 | B30: MRG-0491 | C30: audio | D30: 02_ai_family_emergency_hinglish.ogg | E30: audio/ogg | F30: 5bc20c8a106e85862e3a8d71c9ba55d57d863e6ab5d75e170636c2243ddd4e23 | G30: 38664 | H30: 5b/5bc20c8a106e85862e3a8d71c9ba55d57d863e6ab5d75e170636c2243ddd4e23.ogg | I30: 16.99 | J30: {"asr": {"text": "Papa, I am. Accident is over and phone is broken. This is the number of friends.", "language": "hi-Latn (Hinglish)", "language_p": 1.0, "words": [{"w": "Papa,", "t0": 0.0, "t1": 0.58, "p": 0.37}, {"w": "I", "t0": 0.9, "t1": 1.3, "p": 0.89}, {"w": "am.", "t0": 1.3, "t1": 1.6, "p": 0.79}, {"w": "Accident", "t0": 2.62, "t1": 3.26, "p": 0.58}, {"w": "is", "t0": 3.26, "t1": 3.52, "p": 0.65}, {"w": "over", "t0": 3.52, "t1": 3.72, "p": 0.08}, {"w": "and", "t0": 3.72, "t1": 4.22, "p": 0.69}, {"w": "phone", "t0": 4.22, "t1": 4.54, "p": 0.23}, {"w": "is", "t0": 4.54, "t1": 4.8, "p": 0.7}, {"w": "broken.", "t0": 4.8, "t1": 4.96, "p": 0.62}, {"w": "This", "t0": 5.44, "t1": 5.72, "p": 0.69}, {"w": "is", "t0": 5.72, "t1": 6.14, "p": 0.93}, {"w": "the", "t0": 6.14, "t1": 6.3, "p": 0.66}, {"w": "number", "t0": 6.3, "t1": 6.62, "p": 0.67}, {"w": "of", "t0": 6.62, "t1": 6.78, "p": 0.95}, {"w": "friends.", "t0": 6.78, "t1": 6.78, "p": 0.75}], "engine": "faster-whisper/base"}}
A31: 30 | B31: MRG-0492 | C31: audio | D31: 02_ai_family_emergency_hinglish.ogg | E31: audio/ogg | F31: 5bc20c8a106e85862e3a8d71c9ba55d57d863e6ab5d75e170636c2243ddd4e23 | G31: 38664 | H31: 5b/5bc20c8a106e85862e3a8d71c9ba55d57d863e6ab5d75e170636c2243ddd4e23.ogg | I31: 16.99 | J31: {"asr": {"text": "Papa, I am. Accident is over and phone is broken. This is the number of friends.", "language": "hi-Latn (Hinglish)", "language_p": 1.0, "words": [{"w": "Papa,", "t0": 0.0, "t1": 0.58, "p": 0.37}, {"w": "I", "t0": 0.9, "t1": 1.3, "p": 0.89}, {"w": "am.", "t0": 1.3, "t1": 1.6, "p": 0.79}, {"w": "Accident", "t0": 2.62, "t1": 3.26, "p": 0.58}, {"w": "is", "t0": 3.26, "t1": 3.52, "p": 0.65}, {"w": "over", "t0": 3.52, "t1": 3.72, "p": 0.08}, {"w": "and", "t0": 3.72, "t1": 4.22, "p": 0.69}, {"w": "phone", "t0": 4.22, "t1": 4.54, "p": 0.23}, {"w": "is", "t0": 4.54, "t1": 4.8, "p": 0.7}, {"w": "broken.", "t0": 4.8, "t1": 4.96, "p": 0.62}, {"w": "This", "t0": 5.44, "t1": 5.72, "p": 0.69}, {"w": "is", "t0": 5.72, "t1": 6.14, "p": 0.93}, {"w": "the", "t0": 6.14, "t1": 6.3, "p": 0.66}, {"w": "number", "t0": 6.3, "t1": 6.62, "p": 0.67}, {"w": "of", "t0": 6.62, "t1": 6.78, "p": 0.95}, {"w": "friends.", "t0": 6.78, "t1": 6.78, "p": 0.75}], "engine": "faster-whisper/base"}}
A32: 31 | B32: MRG-0493 | C32: video | D32: 02_ai_avatar_investment_endorsement.mp4 | E32: video/mp4 | F32: 1a456cad8d21c7302376cd537c1a918357601ee7218dae499462eaef63939c8c | G32: 243404 | H32: 1a/1a456cad8d21c7302376cd537c1a918357601ee7218dae499462eaef63939c8c.mp4 | I32: 14.14 | J32: {"asr": {"text": "I personally use this trading platform. Invest just 20 ,000 today and earn 4 % daily guaranteed. registration closes tonight, join the WhatsApp group now.", "language": "en", "language_p": 1.0, "words": [{"w": "I", "t0": 0.0, "t1": 0.28, "p": 0.95}, {"w": "personally", "t0": 0.28, "t1": 0.74, "p": 0.99}, {"w": "use", "t0": 0.74, "t1": 1.2, "p": 0.76}, {"w": "this", "t0": 1.2, "t1": 1.44, "p": 0.98}, {"w": "trading", "t0": 1.44, "t1": 1.86, "p": 0.98}, {"w": "platform.", "t0": 1.86, "t1": 2.46, "p": 0.99}, {"w": "Invest", "t0": 3.38, "t1": 3.84, "p": 0.93}, {"w": "just", "t0": 3.84, "t1": 4.3, "p": 0.96}, {"w": "20", "t0": 4.3, "t1": 4.84, "p": 0.75}, {"w": ",000", "t0": 4.84, "t1": 5.22, "p": 0.89}, {"w": "today", "t0": 5.22, "t1": 5.58, "p": 0.93}, {"w": "and", "t0": 5.58, "t1": 6.2, "p": 0.67}, {"w": "earn", "t0": 6.2, "t1": 6.44, "p": 1.0}, {"w": "4", "t0": 6.44, "t1": 6.94, "p": 0.99}, {"w": "%", "t0": 6.94, "t1": 7.3, "p": 0.9}, {"w": "daily", "t0": 7.3, "t1": 7.78, "p": 0.98}, {"w": "guaranteed.", "t0": 7.78, "t1": 8.5, "p": 0.89}, {"w": "registration", "t0": 8.5, "t1": 10.08, "p": 0.18}, {"w": "closes", "t0": 10.08, "t1": 10.68, "p": 0.82}, {"w": "tonight,", "t0": 10.68, "t1": 11.18, "p": 0.98}, {"w": "join", "t0": 11.68, "t1": 11.86, "p": 0.84}, {"w": "the", "t0": 11.86, "t1": 12.08, "p": 0.95}, {"w": "WhatsApp", "t0": 12.08, "t1": 12.48, "p": 0.77}, {"w": "group", "t0": 12.48, "t1": 12.9, "p": 0.81}, {"w": "now.", "t0": 12.9, "t1": 13.26, "p": 0.98}], "engine": "faster-whisper/base"}}
A33: 32 | B33: MRG-0494 | C33: image | D33: 07_whatsapp_cfo_chat_screenshot.png | E33: image/png | F33: 9352f46f9ef1860dd9fd6bb00b7654c4682122a1663ac24c0671aae1d90d1d41 | G33: 42090 | H33: 93/9352f46f9ef1860dd9fd6bb00b7654c4682122a1663ac24c0671aae1d90d1d41.png | J33: {"ocr": {"text": "Rajesh Mehta (CFO)\nonline\nHi Kavita, Rajesh here. In a board meeting,\ncan't talk.\nPlease process Rs 9,80,000 to Orbit\nSupplies'new account 600112233445 IFSC\nHDFC0001234 today.\nSure, should I loop in audit?\nNo,keep this between us until the audit\ncloses.Very urgent,before 4 PM.", "lines": [{"text": "Rajesh Mehta (CFO)", "conf": 0.99, "box": [0.0944, 0.0294, 0.2875, 0.0496]}, {"text": "online", "conf": 0.99, "box": [0.0944, 0.0882, 0.0708, 0.0349]}, {"text": "Hi Kavita, Rajesh here. In a board meeting,", "conf": 0.96, "box": [0.0431, 0.204, 0.5875, 0.0496]}, {"text": "can't talk.", "conf": 0.95, "box": [0.0444, 0.2629, 0.1278, 0.0404]}, {"text": "Please process Rs 9,80,000 to Orbit", "conf": 0.97, "box": [0.0458, 0.3824, 0.4931, 0.0423]}, {"text": "Supplies'new account 600112233445 IFSC", "conf": 0.97, "box": [0.0444, 0.4357, 0.5944, 0.046]}, {"text": "HDFC0001234 today.", "conf": 0.99, "box": [0.0431, 0.4871, 0.2972, 0.0533]}, {"text": "Sure, should I loop in audit?", "conf": 0.97, "box": [0.5764, 0.6158, 0.3778, 0.0404]}, {"text": "No,keep this between us until the audit", "conf": 0.96, "box": [0.0431, 0.7353, 0.5403, 0.0423]}, {"text": "closes.Very urgent,before 4 PM.", "conf": 0.99, "box": [0.0458, 0.7941, 0.4514, 0.0386]}], "engine": "rapidocr"}}
A34: 33 | B34: MRG-0495 | C34: text | D34: 01_vendor_bank_change_bec.eml | E34: text/plain | F34: f8a7017d25072502f6e6cf4390b82f690ceaf4c6fac0c321f87dbf16a6856e79 | G34: 960 | H34: f8/f8a7017d25072502f6e6cf4390b82f690ceaf4c6fac0c321f87dbf16a6856e79.eml | J34: {}
A35: 34 | B35: MRG-0496 | C35: text | D35: 02_ceo_gift_cards_urgent.eml | E35: text/plain | F35: 51354c917e32e3aa256912f89bf4f26f08760b04a60e3b776318ec14c07b6b94 | G35: 575 | H35: 51/51354c917e32e3aa256912f89bf4f26f08760b04a60e3b776318ec14c07b6b94.eml | J35: {}
A36: 35 | B36: MRG-0497 | C36: text | D36: 03_password_expiry_phishing.eml | E36: text/plain | F36: 02c67d1cd12ff0680714a89d74039101e5632a15e1e8418e3a639c49761225b1 | G36: 551 | H36: 02/02c67d1cd12ff0680714a89d74039101e5632a15e1e8418e3a639c49761225b1.eml | J36: {}
A37: 36 | B37: MRG-0498 | C37: text | D37: 04_benign_hr_newsletter.eml | E37: text/plain | F37: 4bf350238f37abd18e43521f591d257eea2ddb62e0c6a970acfce20f6ee7d262 | G37: 452 | H37: 4b/4bf350238f37abd18e43521f591d257eea2ddb62e0c6a970acfce20f6ee7d262.eml | J37: {}
A38: 37 | B38: MRG-0499 | C38: audio | D38: cfo_voice_note.ogg | E38: audio/ogg | F38: 76804f5c9ce590d9736b14708da395f59772b54da34102673c29f621cbcedcbd | G38: 45575 | H38: 76/76804f5c9ce590d9736b14708da395f59772b54da34102673c29f621cbcedcbd.ogg | I38: 17.62 | J38: {"asr": {"text": "Hi, it's Rajesh from the CFO office. I'm in a board meeting and can't take calls. Please wire 48 lakh rupees to the new vendor account before 4 pm it's urgent and confidential. Don't loop in audit.", "language": "en", "language_p": 1.0, "words": [{"w": "Hi,", "t0": 0.0, "t1": 0.38, "p": 0.9}, {"w": "it's", "t0": 0.72, "t1": 1.16, "p": 0.69}, {"w": "Rajesh", "t0": 1.16, "t1": 1.5, "p": 0.98}, {"w": "from", "t0": 1.5, "t1": 1.78, "p": 0.99}, {"w": "the", "t0": 1.78, "t1": 1.98, "p": 0.97}, {"w": "CFO", "t0": 1.98, "t1": 2.4, "p": 0.85}, {"w": "office.", "t0": 2.4, "t1": 3.0, "p": 0.75}, {"w": "I'm", "t0": 3.7, "t1": 4.24, "p": 0.9}, {"w": "in", "t0": 4.24, "t1": 4.38, "p": 0.99}, {"w": "a", "t0": 4.38, "t1": 4.5, "p": 0.97}, {"w": "board", "t0": 4.5, "t1": 4.76, "p": 0.92}, {"w": "meeting", "t0": 4.76, "t1": 5.22, "p": 1.0}, {"w": "and", "t0": 5.22, "t1": 5.78, "p": 0.87}, {"w": "can't", "t0": 5.78, "t1": 6.18, "p": 0.96}, {"w": "take", "t0": 6.18, "t1": 6.44, "p": 1.0}, {"w": "calls.", "t0": 6.44, "t1": 6.84, "p": 0.97}, {"w": "Please", "t0": 7.86, "t1": 8.12, "p": 0.98}, {"w": "wire", "t0": 8.12, "t1": 8.52, "p": 0.87}, {"w": "48", "t0": 8.52, "t1": 9.34, "p": 0.94}, {"w": "lakh", "t0": 9.34, "t1": 9.7, "p": 0.31}, {"w": "rupees", "t0": 9.7, "t1": 10.14, "p": 0.89}, {"w": "to", "t0": 10.14, "t1": 10.48, "p": 0.99}, {"w": "the", "t0": 10.48, "t1": 10.62, "p": 0.99}, {"w": "new", "t0": 10.62, "t1": 10.84, "p": 0.85}, {"w": "vendor", "t0": 10.84, "t1": 11.18, "p": 0.81}, {"w": "account", "t0": 11.18, "t1": 11.66, "p": 0.99}, {"w": "before", "t0": 11.66, "t1": 12.16, "p": 0.92}, {"w": "4", "t0": 12.16, "t1": 12.7, "p": 0.98}, {"w": "pm", "t0": 12.7, "t1": 13.02, "p": 0.33}, {"w": "it's", "t0": 13.02, "t1": 13.54, "p": 0.68}, {"w": "urgent", "t0": 13.54, "t1": 13.86, "p": 0.98}, {"w": "and", "t0": 13.86, "t1": 14.26, "p": 0.98}, {"w": "confidential.", "t0": 14.26, "t1": 14.94, "p": 1.0}, {"w": "Don't", "t0": 15.42, "t1": 15.72, "p": 0.93}, {"w": "loop", …(truncated)
A39: 38 | B39: MRG-0500 | C39: video | D39: video_call.mp4 | E39: video/mp4 | F39: c82097dc6a47d2309350a516a095c5a8eb99a548c9001f7dcf3bc26eff30d2d0 | G39: 378965 | H39: c8/c82097dc6a47d2309350a516a095c5a8eb99a548c9001f7dcf3bc26eff30d2d0.mp4 | I39: 23.1 | J39: {"asr": {"text": "This is Inspector Sharma from the CBI CyberSair. A parcel in your name has illegal items and an arrest warrant is issued. Stay on this video call and do not disconnect. Transfer your savings to the RBI verification account to avoid arrest. Do not tell anyone.", "language": "en", "language_p": 1.0, "words": [{"w": "This", "t0": 0.0, "t1": 0.4, "p": 0.93}, {"w": "is", "t0": 0.4, "t1": 0.7, "p": 0.99}, {"w": "Inspector", "t0": 0.7, "t1": 1.34, "p": 0.87}, {"w": "Sharma", "t0": 1.34, "t1": 1.84, "p": 0.97}, {"w": "from", "t0": 1.84, "t1": 2.14, "p": 0.98}, {"w": "the", "t0": 2.14, "t1": 2.3, "p": 0.93}, {"w": "CBI", "t0": 2.3, "t1": 2.84, "p": 0.75}, {"w": "CyberSair.", "t0": 2.84, "t1": 3.7, "p": 0.23}, {"w": "A", "t0": 4.36, "t1": 4.92, "p": 0.82}, {"w": "parcel", "t0": 4.92, "t1": 5.2, "p": 0.98}, {"w": "in", "t0": 5.2, "t1": 5.56, "p": 0.98}, {"w": "your", "t0": 5.56, "t1": 5.8, "p": 0.99}, {"w": "name", "t0": 5.8, "t1": 6.14, "p": 0.97}, {"w": "has", "t0": 6.14, "t1": 6.62, "p": 0.99}, {"w": "illegal", "t0": 6.62, "t1": 7.02, "p": 0.98}, {"w": "items", "t0": 7.02, "t1": 7.54, "p": 0.98}, {"w": "and", "t0": 7.54, "t1": 8.1, "p": 0.79}, {"w": "an", "t0": 8.1, "t1": 8.36, "p": 0.85}, {"w": "arrest", "t0": 8.36, "t1": 8.56, "p": 0.99}, {"w": "warrant", "t0": 8.56, "t1": 9.04, "p": 1.0}, {"w": "is", "t0": 9.04, "t1": 9.38, "p": 0.96}, {"w": "issued.", "t0": 9.38, "t1": 9.72, "p": 0.99}, {"w": "Stay", "t0": 10.34, "t1": 11.06, "p": 0.97}, {"w": "on", "t0": 11.06, "t1": 11.36, "p": 1.0}, {"w": "this", "t0": 11.36, "t1": 11.68, "p": 0.99}, {"w": "video", "t0": 11.68, "t1": 12.06, "p": 0.98}, {"w": "call", "t0": 12.06, "t1": 12.38, "p": 0.93}, {"w": "and", "t0": 12.38, "t1": 12.9, "p": 0.93}, {"w": "do", "t0": 12.9, "t1": 13.08, "p": 0.97}, {"w": "not", "t0": 13.08, "t1": 13.32, "p": 0.99}, {"w": "disconnect.", "t0": 13.32, "t1": 13.92, "p": 1.0}, {"w": "Transfer", "t0": 14.86, "t1": 15.48, "p": 0.98}, {"w": "your", "t0": 15.48, "t1": 15.82, "p": 0.99}, {" …(truncated)
A40: 39 | B40: MRG-0501 | C40: audio | D40: papa_voice.ogg | E40: audio/ogg | F40: 5bc20c8a106e85862e3a8d71c9ba55d57d863e6ab5d75e170636c2243ddd4e23 | G40: 38664 | H40: 5b/5bc20c8a106e85862e3a8d71c9ba55d57d863e6ab5d75e170636c2243ddd4e23.ogg | I40: 16.99 | J40: {"asr": {"text": "Papa, I am. Accident is over and phone is broken. This is the number of friends.", "language": "hi-Latn (Hinglish)", "language_p": 1.0, "words": [{"w": "Papa,", "t0": 0.0, "t1": 0.58, "p": 0.37}, {"w": "I", "t0": 0.9, "t1": 1.3, "p": 0.89}, {"w": "am.", "t0": 1.3, "t1": 1.6, "p": 0.79}, {"w": "Accident", "t0": 2.62, "t1": 3.26, "p": 0.58}, {"w": "is", "t0": 3.26, "t1": 3.52, "p": 0.65}, {"w": "over", "t0": 3.52, "t1": 3.72, "p": 0.08}, {"w": "and", "t0": 3.72, "t1": 4.22, "p": 0.69}, {"w": "phone", "t0": 4.22, "t1": 4.54, "p": 0.23}, {"w": "is", "t0": 4.54, "t1": 4.8, "p": 0.7}, {"w": "broken.", "t0": 4.8, "t1": 4.96, "p": 0.62}, {"w": "This", "t0": 5.44, "t1": 5.72, "p": 0.69}, {"w": "is", "t0": 5.72, "t1": 6.14, "p": 0.93}, {"w": "the", "t0": 6.14, "t1": 6.3, "p": 0.66}, {"w": "number", "t0": 6.3, "t1": 6.62, "p": 0.67}, {"w": "of", "t0": 6.62, "t1": 6.78, "p": 0.95}, {"w": "friends.", "t0": 6.78, "t1": 6.78, "p": 0.75}], "engine": "faster-whisper/base"}}
A41: 40 | B41: MRG-0502 | C41: image | D41: accounts_manager.jpg | E41: image/jpeg | F41: 044c58a1e2a77eb23602a272ef458789c1e9fe7ff494c7a7adb14ec045624187 | G41: 71244 | H41: 04/044c58a1e2a77eb23602a272ef458789c1e9fe7ff494c7a7adb14ec045624187.jpg | J41: {"ocr": {"text": "MIRAGE RED TEAM\u00b7SYNTHETIC", "lines": [{"text": "MIRAGE RED TEAM\u00b7SYNTHETIC", "conf": 0.98, "box": [0.6914, 0.9688, 0.2969, 0.0273]}], "engine": "rapidocr"}}
A42: 41 | B42: MRG-0502 | C42: text | D42: invoice.eml | E42: text/plain | F42: f8a7017d25072502f6e6cf4390b82f690ceaf4c6fac0c321f87dbf16a6856e79 | G42: 960 | H42: f8/f8a7017d25072502f6e6cf4390b82f690ceaf4c6fac0c321f87dbf16a6856e79.eml | J42: {}
A43: 42 | B43: MRG-0503 | C43: audio | D43: townhall.mp3 | E43: audio/mpeg | F43: e6d8bbfd37a6f671ac1887cebe8cbbb9a77ceb30a0ba791a8c625227c1610534 | G43: 97100 | H43: e6/e6d8bbfd37a6f671ac1887cebe8cbbb9a77ceb30a0ba791a8c625227c1610534.mp3 | I43: 12 | J43: {"asr": {"text": "Good morning team. The quarterly town hall moves to Friday at 4pm in the main auditorium. Snacks will be served. See you there.", "language": "en", "language_p": 1.0, "words": [{"w": "Good", "t0": 0.0, "t1": 0.4, "p": 0.84}, {"w": "morning", "t0": 0.4, "t1": 0.78, "p": 0.81}, {"w": "team.", "t0": 0.78, "t1": 1.26, "p": 0.75}, {"w": "The", "t0": 2.28, "t1": 2.4, "p": 0.98}, {"w": "quarterly", "t0": 2.4, "t1": 2.86, "p": 0.68}, {"w": "town", "t0": 2.86, "t1": 3.18, "p": 0.89}, {"w": "hall", "t0": 3.18, "t1": 3.48, "p": 0.98}, {"w": "moves", "t0": 3.48, "t1": 3.78, "p": 0.99}, {"w": "to", "t0": 3.78, "t1": 4.04, "p": 0.99}, {"w": "Friday", "t0": 4.04, "t1": 4.36, "p": 0.93}, {"w": "at", "t0": 4.36, "t1": 4.74, "p": 0.98}, {"w": "4pm", "t0": 4.74, "t1": 5.38, "p": 0.66}, {"w": "in", "t0": 5.38, "t1": 5.7, "p": 0.97}, {"w": "the", "t0": 5.7, "t1": 5.8, "p": 0.97}, {"w": "main", "t0": 5.8, "t1": 6.12, "p": 0.95}, {"w": "auditorium.", "t0": 6.12, "t1": 6.92, "p": 1.0}, {"w": "Snacks", "t0": 7.92, "t1": 8.4, "p": 0.95}, {"w": "will", "t0": 8.4, "t1": 8.62, "p": 1.0}, {"w": "be", "t0": 8.62, "t1": 8.8, "p": 1.0}, {"w": "served.", "t0": 8.8, "t1": 9.18, "p": 0.99}, {"w": "See", "t0": 10.02, "t1": 10.54, "p": 0.99}, {"w": "you", "t0": 10.54, "t1": 10.7, "p": 0.99}, {"w": "there.", "t0": 10.7, "t1": 10.96, "p": 0.99}], "engine": "faster-whisper/base"}}
A44: 43 | B44: MRG-0504 | C44: audio | D44: papa_voice_note.wav | E44: audio/wav | F44: 8ee650801c14eee68e4b6c098d232806785b31a005cd15483c392f5942151589 | G44: 359182 | H44: 8e/8ee650801c14eee68e4b6c098d232806785b31a005cd15483c392f5942151589.wav | I44: 11.22 | J44: {"asr": {"text": "Beta main hoon, accident ho gaya high, phone toot gaya, pays abi burjo, 75 ,000, G -she -ke -oh mat Pat No Please.", "language": "en", "language_p": 1.0, "words": [{"w": "Beta", "t0": 0.0, "t1": 0.36, "p": 0.56}, {"w": "main", "t0": 0.36, "t1": 0.6, "p": 0.39}, {"w": "hoon,", "t0": 0.6, "t1": 0.96, "p": 0.57}, {"w": "accident", "t0": 1.36, "t1": 1.76, "p": 0.77}, {"w": "ho", "t0": 1.76, "t1": 2.02, "p": 0.53}, {"w": "gaya", "t0": 2.02, "t1": 2.34, "p": 0.52}, {"w": "high,", "t0": 2.34, "t1": 2.74, "p": 0.32}, {"w": "phone", "t0": 3.1, "t1": 3.26, "p": 0.79}, {"w": "toot", "t0": 3.26, "t1": 3.6, "p": 0.69}, {"w": "gaya,", "t0": 3.6, "t1": 3.9, "p": 0.98}, {"w": "pays", "t0": 4.54, "t1": 5.14, "p": 0.43}, {"w": "abi", "t0": 5.14, "t1": 5.42, "p": 0.2}, {"w": "burjo,", "t0": 5.42, "t1": 5.74, "p": 0.73}, {"w": "75", "t0": 6.26, "t1": 6.94, "p": 0.77}, {"w": ",000,", "t0": 6.94, "t1": 8.32, "p": 0.67}, {"w": "G", "t0": 8.54, "t1": 8.74, "p": 0.46}, {"w": "-she", "t0": 8.74, "t1": 8.96, "p": 0.24}, {"w": "-ke", "t0": 8.96, "t1": 9.18, "p": 0.2}, {"w": "-oh", "t0": 9.18, "t1": 9.3, "p": 0.3}, {"w": "mat", "t0": 9.3, "t1": 9.52, "p": 0.32}, {"w": "Pat", "t0": 9.52, "t1": 9.74, "p": 0.14}, {"w": "No", "t0": 9.74, "t1": 9.9, "p": 0.28}, {"w": "Please.", "t0": 9.9, "t1": 10.2, "p": 0.36}], "engine": "faster-whisper/base"}}
A45: 44 | B45: MRG-0505 | C45: video | D45: 01_ai_avatar_digital_arrest_officer.mp4 | E45: video/mp4 | F45: c82097dc6a47d2309350a516a095c5a8eb99a548c9001f7dcf3bc26eff30d2d0 | G45: 378965 | H45: c8/c82097dc6a47d2309350a516a095c5a8eb99a548c9001f7dcf3bc26eff30d2d0.mp4 | I45: 23.1 | J45: {"asr": {"text": "This is Inspector Sharma from the CBI CyberSair. A parcel in your name has illegal items and an arrest warrant is issued. Stay on this video call and do not disconnect. Transfer your savings to the RBI verification account to avoid arrest. Do not tell anyone.", "language": "en", "language_p": 1.0, "words": [{"w": "This", "t0": 0.0, "t1": 0.4, "p": 0.93}, {"w": "is", "t0": 0.4, "t1": 0.7, "p": 0.99}, {"w": "Inspector", "t0": 0.7, "t1": 1.34, "p": 0.87}, {"w": "Sharma", "t0": 1.34, "t1": 1.84, "p": 0.97}, {"w": "from", "t0": 1.84, "t1": 2.14, "p": 0.98}, {"w": "the", "t0": 2.14, "t1": 2.3, "p": 0.93}, {"w": "CBI", "t0": 2.3, "t1": 2.84, "p": 0.75}, {"w": "CyberSair.", "t0": 2.84, "t1": 3.7, "p": 0.23}, {"w": "A", "t0": 4.36, "t1": 4.92, "p": 0.82}, {"w": "parcel", "t0": 4.92, "t1": 5.2, "p": 0.98}, {"w": "in", "t0": 5.2, "t1": 5.56, "p": 0.98}, {"w": "your", "t0": 5.56, "t1": 5.8, "p": 0.99}, {"w": "name", "t0": 5.8, "t1": 6.14, "p": 0.97}, {"w": "has", "t0": 6.14, "t1": 6.62, "p": 0.99}, {"w": "illegal", "t0": 6.62, "t1": 7.02, "p": 0.98}, {"w": "items", "t0": 7.02, "t1": 7.54, "p": 0.98}, {"w": "and", "t0": 7.54, "t1": 8.1, "p": 0.79}, {"w": "an", "t0": 8.1, "t1": 8.36, "p": 0.85}, {"w": "arrest", "t0": 8.36, "t1": 8.56, "p": 0.99}, {"w": "warrant", "t0": 8.56, "t1": 9.04, "p": 1.0}, {"w": "is", "t0": 9.04, "t1": 9.38, "p": 0.96}, {"w": "issued.", "t0": 9.38, "t1": 9.72, "p": 0.99}, {"w": "Stay", "t0": 10.34, "t1": 11.06, "p": 0.97}, {"w": "on", "t0": 11.06, "t1": 11.36, "p": 1.0}, {"w": "this", "t0": 11.36, "t1": 11.68, "p": 0.99}, {"w": "video", "t0": 11.68, "t1": 12.06, "p": 0.98}, {"w": "call", "t0": 12.06, "t1": 12.38, "p": 0.93}, {"w": "and", "t0": 12.38, "t1": 12.9, "p": 0.93}, {"w": "do", "t0": 12.9, "t1": 13.08, "p": 0.97}, {"w": "not", "t0": 13.08, "t1": 13.32, "p": 0.99}, {"w": "disconnect.", "t0": 13.32, "t1": 13.92, "p": 1.0}, {"w": "Transfer", "t0": 14.86, "t1": 15.48, "p": 0.98}, {"w": "your", "t0": 15.48, "t1": 15.82, "p": 0.99}, {" …(truncated)
A46: 45 | B46: MRG-0506 | C46: video | D46: 02_ai_avatar_investment_endorsement.mp4 | E46: video/mp4 | F46: 1a456cad8d21c7302376cd537c1a918357601ee7218dae499462eaef63939c8c | G46: 243404 | H46: 1a/1a456cad8d21c7302376cd537c1a918357601ee7218dae499462eaef63939c8c.mp4 | I46: 14.14 | J46: {"asr": {"text": "I personally use this trading platform. Invest just 20 ,000 today and earn 4 % daily guaranteed. registration closes tonight, join the WhatsApp group now.", "language": "en", "language_p": 1.0, "words": [{"w": "I", "t0": 0.0, "t1": 0.28, "p": 0.95}, {"w": "personally", "t0": 0.28, "t1": 0.74, "p": 0.99}, {"w": "use", "t0": 0.74, "t1": 1.2, "p": 0.76}, {"w": "this", "t0": 1.2, "t1": 1.44, "p": 0.98}, {"w": "trading", "t0": 1.44, "t1": 1.86, "p": 0.98}, {"w": "platform.", "t0": 1.86, "t1": 2.46, "p": 0.99}, {"w": "Invest", "t0": 3.38, "t1": 3.84, "p": 0.93}, {"w": "just", "t0": 3.84, "t1": 4.3, "p": 0.96}, {"w": "20", "t0": 4.3, "t1": 4.84, "p": 0.75}, {"w": ",000", "t0": 4.84, "t1": 5.22, "p": 0.89}, {"w": "today", "t0": 5.22, "t1": 5.58, "p": 0.93}, {"w": "and", "t0": 5.58, "t1": 6.2, "p": 0.67}, {"w": "earn", "t0": 6.2, "t1": 6.44, "p": 1.0}, {"w": "4", "t0": 6.44, "t1": 6.94, "p": 0.99}, {"w": "%", "t0": 6.94, "t1": 7.3, "p": 0.9}, {"w": "daily", "t0": 7.3, "t1": 7.78, "p": 0.98}, {"w": "guaranteed.", "t0": 7.78, "t1": 8.5, "p": 0.89}, {"w": "registration", "t0": 8.5, "t1": 10.08, "p": 0.18}, {"w": "closes", "t0": 10.08, "t1": 10.68, "p": 0.82}, {"w": "tonight,", "t0": 10.68, "t1": 11.18, "p": 0.98}, {"w": "join", "t0": 11.68, "t1": 11.86, "p": 0.84}, {"w": "the", "t0": 11.86, "t1": 12.08, "p": 0.95}, {"w": "WhatsApp", "t0": 12.08, "t1": 12.48, "p": 0.77}, {"w": "group", "t0": 12.48, "t1": 12.9, "p": 0.81}, {"w": "now.", "t0": 12.9, "t1": 13.26, "p": 0.98}], "engine": "faster-whisper/base"}}
A47: 46 | B47: MRG-0507 | C47: video | D47: 03_ai_meeting_lipsync_drift.mp4 | E47: video/mp4 | F47: dcd6e1b3ce071839949027861d0b90307789c4195fd7679ea6faea24601214e6 | G47: 190002 | H47: dc/dcd6e1b3ce071839949027861d0b90307789c4195fd7679ea6faea24601214e6.mp4 | I47: 12.61 | J47: {"asr": {"text": "As discussed on the call, transfer 3 .2 crore to the escrow account today. This is confidential until the acquisition is announced. Do not discuss with anyone in finance.", "language": "en", "language_p": 1.0, "words": [{"w": "As", "t0": 0.0, "t1": 0.26, "p": 0.65}, {"w": "discussed", "t0": 0.26, "t1": 0.62, "p": 1.0}, {"w": "on", "t0": 0.62, "t1": 0.92, "p": 1.0}, {"w": "the", "t0": 0.92, "t1": 1.06, "p": 1.0}, {"w": "call,", "t0": 1.06, "t1": 1.32, "p": 0.99}, {"w": "transfer", "t0": 1.84, "t1": 2.3, "p": 0.94}, {"w": "3", "t0": 2.3, "t1": 2.76, "p": 0.93}, {"w": ".2", "t0": 2.76, "t1": 3.2, "p": 0.99}, {"w": "crore", "t0": 3.2, "t1": 3.5, "p": 0.77}, {"w": "to", "t0": 3.5, "t1": 3.68, "p": 1.0}, {"w": "the", "t0": 3.68, "t1": 3.84, "p": 0.99}, {"w": "escrow", "t0": 3.84, "t1": 4.26, "p": 0.85}, {"w": "account", "t0": 4.26, "t1": 4.54, "p": 0.99}, {"w": "today.", "t0": 4.54, "t1": 4.92, "p": 1.0}, {"w": "This", "t0": 5.48, "t1": 6.04, "p": 0.99}, {"w": "is", "t0": 6.04, "t1": 6.2, "p": 1.0}, {"w": "confidential", "t0": 6.2, "t1": 6.7, "p": 1.0}, {"w": "until", "t0": 6.7, "t1": 7.2, "p": 0.99}, {"w": "the", "t0": 7.2, "t1": 7.44, "p": 1.0}, {"w": "acquisition", "t0": 7.44, "t1": 7.9, "p": 1.0}, {"w": "is", "t0": 7.9, "t1": 8.22, "p": 1.0}, {"w": "announced.", "t0": 8.22, "t1": 8.74, "p": 1.0}, {"w": "Do", "t0": 9.52, "t1": 9.82, "p": 0.99}, {"w": "not", "t0": 9.82, "t1": 9.98, "p": 0.99}, {"w": "discuss", "t0": 9.98, "t1": 10.36, "p": 1.0}, {"w": "with", "t0": 10.36, "t1": 10.62, "p": 1.0}, {"w": "anyone", "t0": 10.62, "t1": 11.02, "p": 0.99}, {"w": "in", "t0": 11.02, "t1": 11.24, "p": 1.0}, {"w": "finance.", "t0": 11.24, "t1": 11.6, "p": 0.87}], "engine": "faster-whisper/base"}}
A48: 47 | B48: MRG-0508 | C48: video | D48: 04_real_face_human_voice_benign.mp4 | E48: video/mp4 | F48: 0ec2f08797793f3b3e2734ca43a27a1707e424ab366ea638da889e9b6ec8addc | G48: 418676 | H48: 0e/0ec2f08797793f3b3e2734ca43a27a1707e424ab366ea638da889e9b6ec8addc.mp4 | I48: 24.38 | J48: {"asr": {"text": "Mr. Quilter is the apostle of the middle classes, and we are glad to welcome his gospel. Nor is Mr. Quilter's manner less interesting than his matter. He tells us that at this festive season of the year, with Christmas and roast beef looming before us, Similarly, it is drawn from eating and its results occur most readily to the mind.", "language": "en", "language_p": 1.0, "words": [{"w": "Mr.", "t0": 0.18, "t1": 0.74, "p": 0.86}, {"w": "Quilter", "t0": 0.86, "t1": 1.16, "p": 0.85}, {"w": "is", "t0": 1.16, "t1": 1.38, "p": 0.99}, {"w": "the", "t0": 1.38, "t1": 1.54, "p": 0.99}, {"w": "apostle", "t0": 1.54, "t1": 1.92, "p": 0.83}, {"w": "of", "t0": 1.92, "t1": 2.24, "p": 0.99}, {"w": "the", "t0": 2.24, "t1": 2.36, "p": 0.99}, {"w": "middle", "t0": 2.36, "t1": 2.56, "p": 0.79}, {"w": "classes,", "t0": 2.56, "t1": 3.0, "p": 0.9}, {"w": "and", "t0": 3.36, "t1": 3.44, "p": 0.99}, {"w": "we", "t0": 3.44, "t1": 3.6, "p": 1.0}, {"w": "are", "t0": 3.6, "t1": 3.66, "p": 0.91}, {"w": "glad", "t0": 3.66, "t1": 3.94, "p": 1.0}, {"w": "to", "t0": 3.94, "t1": 4.22, "p": 1.0}, {"w": "welcome", "t0": 4.22, "t1": 4.48, "p": 1.0}, {"w": "his", "t0": 4.48, "t1": 4.78, "p": 0.97}, {"w": "gospel.", "t0": 4.78, "t1": 5.28, "p": 0.86}, {"w": "Nor", "t0": 6.7, "t1": 7.02, "p": 0.85}, {"w": "is", "t0": 7.02, "t1": 7.18, "p": 0.47}, {"w": "Mr.", "t0": 7.18, "t1": 7.56, "p": 0.99}, {"w": "Quilter's", "t0": 7.72, "t1": 8.1, "p": 0.99}, {"w": "manner", "t0": 8.1, "t1": 8.38, "p": 0.98}, {"w": "less", "t0": 8.38, "t1": 8.7, "p": 0.99}, {"w": "interesting", "t0": 8.7, "t1": 9.4, "p": 0.99}, {"w": "than", "t0": 9.4, "t1": 9.68, "p": 0.99}, {"w": "his", "t0": 9.68, "t1": 10.0, "p": 0.99}, {"w": "matter.", "t0": 10.0, "t1": 10.46, "p": 0.64}, {"w": "He", "t0": 11.7, "t1": 12.12, "p": 0.98}, {"w": "tells", "t0": 12.12, "t1": 12.38, "p": 1.0}, {"w": "us", "t0": 12.38, "t1": 12.64, "p": 1.0}, {"w": "that", "t0": 12.64, "t1": 12.96, "p": 0.97}, {"w": "at", "t0": 12.96, "t1": 13.2, "p": 0 …(truncated)
A49: 48 | B49: MRG-0509 | C49: video | D49: 01_ai_avatar_digital_arrest_officer.mp4 | E49: video/mp4 | F49: c82097dc6a47d2309350a516a095c5a8eb99a548c9001f7dcf3bc26eff30d2d0 | G49: 378965 | H49: c8/c82097dc6a47d2309350a516a095c5a8eb99a548c9001f7dcf3bc26eff30d2d0.mp4 | I49: 23.1 | J49: {"asr": {"text": "This is Inspector Sharma from the CBI CyberSair. A parcel in your name has illegal items and an arrest warrant is issued. Stay on this video call and do not disconnect. Transfer your savings to the RBI verification account to avoid arrest. Do not tell anyone.", "language": "en", "language_p": 1.0, "words": [{"w": "This", "t0": 0.0, "t1": 0.4, "p": 0.93}, {"w": "is", "t0": 0.4, "t1": 0.7, "p": 0.99}, {"w": "Inspector", "t0": 0.7, "t1": 1.34, "p": 0.87}, {"w": "Sharma", "t0": 1.34, "t1": 1.84, "p": 0.97}, {"w": "from", "t0": 1.84, "t1": 2.14, "p": 0.98}, {"w": "the", "t0": 2.14, "t1": 2.3, "p": 0.93}, {"w": "CBI", "t0": 2.3, "t1": 2.84, "p": 0.75}, {"w": "CyberSair.", "t0": 2.84, "t1": 3.7, "p": 0.23}, {"w": "A", "t0": 4.36, "t1": 4.92, "p": 0.82}, {"w": "parcel", "t0": 4.92, "t1": 5.2, "p": 0.98}, {"w": "in", "t0": 5.2, "t1": 5.56, "p": 0.98}, {"w": "your", "t0": 5.56, "t1": 5.8, "p": 0.99}, {"w": "name", "t0": 5.8, "t1": 6.14, "p": 0.97}, {"w": "has", "t0": 6.14, "t1": 6.62, "p": 0.99}, {"w": "illegal", "t0": 6.62, "t1": 7.02, "p": 0.98}, {"w": "items", "t0": 7.02, "t1": 7.54, "p": 0.98}, {"w": "and", "t0": 7.54, "t1": 8.1, "p": 0.79}, {"w": "an", "t0": 8.1, "t1": 8.36, "p": 0.85}, {"w": "arrest", "t0": 8.36, "t1": 8.56, "p": 0.99}, {"w": "warrant", "t0": 8.56, "t1": 9.04, "p": 1.0}, {"w": "is", "t0": 9.04, "t1": 9.38, "p": 0.96}, {"w": "issued.", "t0": 9.38, "t1": 9.72, "p": 0.99}, {"w": "Stay", "t0": 10.34, "t1": 11.06, "p": 0.97}, {"w": "on", "t0": 11.06, "t1": 11.36, "p": 1.0}, {"w": "this", "t0": 11.36, "t1": 11.68, "p": 0.99}, {"w": "video", "t0": 11.68, "t1": 12.06, "p": 0.98}, {"w": "call", "t0": 12.06, "t1": 12.38, "p": 0.93}, {"w": "and", "t0": 12.38, "t1": 12.9, "p": 0.93}, {"w": "do", "t0": 12.9, "t1": 13.08, "p": 0.97}, {"w": "not", "t0": 13.08, "t1": 13.32, "p": 0.99}, {"w": "disconnect.", "t0": 13.32, "t1": 13.92, "p": 1.0}, {"w": "Transfer", "t0": 14.86, "t1": 15.48, "p": 0.98}, {"w": "your", "t0": 15.48, "t1": 15.82, "p": 0.99}, {" …(truncated)
A50: 49 | B50: MRG-0510 | C50: video | D50: 02_ai_avatar_investment_endorsement.mp4 | E50: video/mp4 | F50: 1a456cad8d21c7302376cd537c1a918357601ee7218dae499462eaef63939c8c | G50: 243404 | H50: 1a/1a456cad8d21c7302376cd537c1a918357601ee7218dae499462eaef63939c8c.mp4 | I50: 14.14 | J50: {"asr": {"text": "I personally use this trading platform. Invest just 20 ,000 today and earn 4 % daily guaranteed. registration closes tonight, join the WhatsApp group now.", "language": "en", "language_p": 1.0, "words": [{"w": "I", "t0": 0.0, "t1": 0.28, "p": 0.95}, {"w": "personally", "t0": 0.28, "t1": 0.74, "p": 0.99}, {"w": "use", "t0": 0.74, "t1": 1.2, "p": 0.76}, {"w": "this", "t0": 1.2, "t1": 1.44, "p": 0.98}, {"w": "trading", "t0": 1.44, "t1": 1.86, "p": 0.98}, {"w": "platform.", "t0": 1.86, "t1": 2.46, "p": 0.99}, {"w": "Invest", "t0": 3.38, "t1": 3.84, "p": 0.93}, {"w": "just", "t0": 3.84, "t1": 4.3, "p": 0.96}, {"w": "20", "t0": 4.3, "t1": 4.84, "p": 0.75}, {"w": ",000", "t0": 4.84, "t1": 5.22, "p": 0.89}, {"w": "today", "t0": 5.22, "t1": 5.58, "p": 0.93}, {"w": "and", "t0": 5.58, "t1": 6.2, "p": 0.67}, {"w": "earn", "t0": 6.2, "t1": 6.44, "p": 1.0}, {"w": "4", "t0": 6.44, "t1": 6.94, "p": 0.99}, {"w": "%", "t0": 6.94, "t1": 7.3, "p": 0.9}, {"w": "daily", "t0": 7.3, "t1": 7.78, "p": 0.98}, {"w": "guaranteed.", "t0": 7.78, "t1": 8.5, "p": 0.89}, {"w": "registration", "t0": 8.5, "t1": 10.08, "p": 0.18}, {"w": "closes", "t0": 10.08, "t1": 10.68, "p": 0.82}, {"w": "tonight,", "t0": 10.68, "t1": 11.18, "p": 0.98}, {"w": "join", "t0": 11.68, "t1": 11.86, "p": 0.84}, {"w": "the", "t0": 11.86, "t1": 12.08, "p": 0.95}, {"w": "WhatsApp", "t0": 12.08, "t1": 12.48, "p": 0.77}, {"w": "group", "t0": 12.48, "t1": 12.9, "p": 0.81}, {"w": "now.", "t0": 12.9, "t1": 13.26, "p": 0.98}], "engine": "faster-whisper/base"}}
A51: 50 | B51: MRG-0511 | C51: video | D51: 03_ai_meeting_lipsync_drift.mp4 | E51: video/mp4 | F51: dcd6e1b3ce071839949027861d0b90307789c4195fd7679ea6faea24601214e6 | G51: 190002 | H51: dc/dcd6e1b3ce071839949027861d0b90307789c4195fd7679ea6faea24601214e6.mp4 | I51: 12.61 | J51: {"asr": {"text": "As discussed on the call, transfer 3 .2 crore to the escrow account today. This is confidential until the acquisition is announced. Do not discuss with anyone in finance.", "language": "en", "language_p": 1.0, "words": [{"w": "As", "t0": 0.0, "t1": 0.26, "p": 0.65}, {"w": "discussed", "t0": 0.26, "t1": 0.62, "p": 1.0}, {"w": "on", "t0": 0.62, "t1": 0.92, "p": 1.0}, {"w": "the", "t0": 0.92, "t1": 1.06, "p": 1.0}, {"w": "call,", "t0": 1.06, "t1": 1.32, "p": 0.99}, {"w": "transfer", "t0": 1.84, "t1": 2.3, "p": 0.94}, {"w": "3", "t0": 2.3, "t1": 2.76, "p": 0.93}, {"w": ".2", "t0": 2.76, "t1": 3.2, "p": 0.99}, {"w": "crore", "t0": 3.2, "t1": 3.5, "p": 0.77}, {"w": "to", "t0": 3.5, "t1": 3.68, "p": 1.0}, {"w": "the", "t0": 3.68, "t1": 3.84, "p": 0.99}, {"w": "escrow", "t0": 3.84, "t1": 4.26, "p": 0.85}, {"w": "account", "t0": 4.26, "t1": 4.54, "p": 0.99}, {"w": "today.", "t0": 4.54, "t1": 4.92, "p": 1.0}, {"w": "This", "t0": 5.48, "t1": 6.04, "p": 0.99}, {"w": "is", "t0": 6.04, "t1": 6.2, "p": 1.0}, {"w": "confidential", "t0": 6.2, "t1": 6.7, "p": 1.0}, {"w": "until", "t0": 6.7, "t1": 7.2, "p": 0.99}, {"w": "the", "t0": 7.2, "t1": 7.44, "p": 1.0}, {"w": "acquisition", "t0": 7.44, "t1": 7.9, "p": 1.0}, {"w": "is", "t0": 7.9, "t1": 8.22, "p": 1.0}, {"w": "announced.", "t0": 8.22, "t1": 8.74, "p": 1.0}, {"w": "Do", "t0": 9.52, "t1": 9.82, "p": 0.99}, {"w": "not", "t0": 9.82, "t1": 9.98, "p": 0.99}, {"w": "discuss", "t0": 9.98, "t1": 10.36, "p": 1.0}, {"w": "with", "t0": 10.36, "t1": 10.62, "p": 1.0}, {"w": "anyone", "t0": 10.62, "t1": 11.02, "p": 0.99}, {"w": "in", "t0": 11.02, "t1": 11.24, "p": 1.0}, {"w": "finance.", "t0": 11.24, "t1": 11.6, "p": 0.87}], "engine": "faster-whisper/base"}}
A52: 51 | B52: MRG-0512 | C52: video | D52: 04_real_face_human_voice_benign.mp4 | E52: video/mp4 | F52: 0ec2f08797793f3b3e2734ca43a27a1707e424ab366ea638da889e9b6ec8addc | G52: 418676 | H52: 0e/0ec2f08797793f3b3e2734ca43a27a1707e424ab366ea638da889e9b6ec8addc.mp4 | I52: 24.38 | J52: {"asr": {"text": "Mr. Quilter is the apostle of the middle classes, and we are glad to welcome his gospel. Nor is Mr. Quilter's manner less interesting than his matter. He tells us that at this festive season of the year, with Christmas and roast beef looming before us, Similarly, it is drawn from eating and its results occur most readily to the mind.", "language": "en", "language_p": 1.0, "words": [{"w": "Mr.", "t0": 0.18, "t1": 0.74, "p": 0.86}, {"w": "Quilter", "t0": 0.86, "t1": 1.16, "p": 0.85}, {"w": "is", "t0": 1.16, "t1": 1.38, "p": 0.99}, {"w": "the", "t0": 1.38, "t1": 1.54, "p": 0.99}, {"w": "apostle", "t0": 1.54, "t1": 1.92, "p": 0.83}, {"w": "of", "t0": 1.92, "t1": 2.24, "p": 0.99}, {"w": "the", "t0": 2.24, "t1": 2.36, "p": 0.99}, {"w": "middle", "t0": 2.36, "t1": 2.56, "p": 0.79}, {"w": "classes,", "t0": 2.56, "t1": 3.0, "p": 0.9}, {"w": "and", "t0": 3.36, "t1": 3.44, "p": 0.99}, {"w": "we", "t0": 3.44, "t1": 3.6, "p": 1.0}, {"w": "are", "t0": 3.6, "t1": 3.66, "p": 0.91}, {"w": "glad", "t0": 3.66, "t1": 3.94, "p": 1.0}, {"w": "to", "t0": 3.94, "t1": 4.22, "p": 1.0}, {"w": "welcome", "t0": 4.22, "t1": 4.48, "p": 1.0}, {"w": "his", "t0": 4.48, "t1": 4.78, "p": 0.97}, {"w": "gospel.", "t0": 4.78, "t1": 5.28, "p": 0.86}, {"w": "Nor", "t0": 6.7, "t1": 7.02, "p": 0.85}, {"w": "is", "t0": 7.02, "t1": 7.18, "p": 0.47}, {"w": "Mr.", "t0": 7.18, "t1": 7.56, "p": 0.99}, {"w": "Quilter's", "t0": 7.72, "t1": 8.1, "p": 0.99}, {"w": "manner", "t0": 8.1, "t1": 8.38, "p": 0.98}, {"w": "less", "t0": 8.38, "t1": 8.7, "p": 0.99}, {"w": "interesting", "t0": 8.7, "t1": 9.4, "p": 0.99}, {"w": "than", "t0": 9.4, "t1": 9.68, "p": 0.99}, {"w": "his", "t0": 9.68, "t1": 10.0, "p": 0.99}, {"w": "matter.", "t0": 10.0, "t1": 10.46, "p": 0.64}, {"w": "He", "t0": 11.7, "t1": 12.12, "p": 0.98}, {"w": "tells", "t0": 12.12, "t1": 12.38, "p": 1.0}, {"w": "us", "t0": 12.38, "t1": 12.64, "p": 1.0}, {"w": "that", "t0": 12.64, "t1": 12.96, "p": 0.97}, {"w": "at", "t0": 12.96, "t1": 13.2, "p": 0 …(truncated)
A53: 52 | B53: MRG-0513 | C53: image | D53: 07_whatsapp_cfo_chat_screenshot.png | E53: image/png | F53: 9352f46f9ef1860dd9fd6bb00b7654c4682122a1663ac24c0671aae1d90d1d41 | G53: 42090 | H53: 93/9352f46f9ef1860dd9fd6bb00b7654c4682122a1663ac24c0671aae1d90d1d41.png | J53: {"ocr": {"text": "Rajesh Mehta (CFO)\nonline\nHi Kavita, Rajesh here. In a board meeting,\ncan't talk.\nPlease process Rs 9,80,000 to Orbit\nSupplies'new account 600112233445 IFSC\nHDFC0001234 today.\nSure, should I loop in audit?\nNo,keep this between us until the audit\ncloses.Very urgent,before 4 PM.", "lines": [{"text": "Rajesh Mehta (CFO)", "conf": 0.99, "box": [0.0944, 0.0294, 0.2875, 0.0496]}, {"text": "online", "conf": 0.99, "box": [0.0944, 0.0882, 0.0708, 0.0349]}, {"text": "Hi Kavita, Rajesh here. In a board meeting,", "conf": 0.96, "box": [0.0431, 0.204, 0.5875, 0.0496]}, {"text": "can't talk.", "conf": 0.95, "box": [0.0444, 0.2629, 0.1278, 0.0404]}, {"text": "Please process Rs 9,80,000 to Orbit", "conf": 0.97, "box": [0.0458, 0.3824, 0.4931, 0.0423]}, {"text": "Supplies'new account 600112233445 IFSC", "conf": 0.97, "box": [0.0444, 0.4357, 0.5944, 0.046]}, {"text": "HDFC0001234 today.", "conf": 0.99, "box": [0.0431, 0.4871, 0.2972, 0.0533]}, {"text": "Sure, should I loop in audit?", "conf": 0.97, "box": [0.5764, 0.6158, 0.3778, 0.0404]}, {"text": "No,keep this between us until the audit", "conf": 0.96, "box": [0.0431, 0.7353, 0.5403, 0.0423]}, {"text": "closes.Very urgent,before 4 PM.", "conf": 0.99, "box": [0.0458, 0.7941, 0.4514, 0.0386]}], "engine": "rapidocr"}}
A54: 53 | B54: MRG-0514 | C54: text | D54: 01_vendor_bank_change_bec.eml | E54: text/plain | F54: f8a7017d25072502f6e6cf4390b82f690ceaf4c6fac0c321f87dbf16a6856e79 | G54: 960 | H54: f8/f8a7017d25072502f6e6cf4390b82f690ceaf4c6fac0c321f87dbf16a6856e79.eml | J54: {}
A55: 54 | B55: MRG-0515 | C55: text | D55: 02_ceo_gift_cards_urgent.eml | E55: text/plain | F55: 51354c917e32e3aa256912f89bf4f26f08760b04a60e3b776318ec14c07b6b94 | G55: 575 | H55: 51/51354c917e32e3aa256912f89bf4f26f08760b04a60e3b776318ec14c07b6b94.eml | J55: {}
A56: 55 | B56: MRG-0516 | C56: text | D56: 03_password_expiry_phishing.eml | E56: text/plain | F56: 02c67d1cd12ff0680714a89d74039101e5632a15e1e8418e3a639c49761225b1 | G56: 551 | H56: 02/02c67d1cd12ff0680714a89d74039101e5632a15e1e8418e3a639c49761225b1.eml | J56: {}
A57: 56 | B57: MRG-0517 | C57: text | D57: 04_benign_hr_newsletter.eml | E57: text/plain | F57: 4bf350238f37abd18e43521f591d257eea2ddb62e0c6a970acfce20f6ee7d262 | G57: 452 | H57: 4b/4bf350238f37abd18e43521f591d257eea2ddb62e0c6a970acfce20f6ee7d262.eml | J57: {}
A58: 57 | B58: MRG-0518 | C58: audio | D58: cfo_voice_note.ogg | E58: audio/ogg | F58: 76804f5c9ce590d9736b14708da395f59772b54da34102673c29f621cbcedcbd | G58: 45575 | H58: 76/76804f5c9ce590d9736b14708da395f59772b54da34102673c29f621cbcedcbd.ogg | I58: 17.62 | J58: {"asr": {"text": "Hi, it's Rajesh from the CFO office. I'm in a board meeting and can't take calls. Please wire 48 lakh rupees to the new vendor account before 4 pm it's urgent and confidential. Don't loop in audit.", "language": "en", "language_p": 1.0, "words": [{"w": "Hi,", "t0": 0.0, "t1": 0.38, "p": 0.9}, {"w": "it's", "t0": 0.72, "t1": 1.16, "p": 0.69}, {"w": "Rajesh", "t0": 1.16, "t1": 1.5, "p": 0.98}, {"w": "from", "t0": 1.5, "t1": 1.78, "p": 0.99}, {"w": "the", "t0": 1.78, "t1": 1.98, "p": 0.97}, {"w": "CFO", "t0": 1.98, "t1": 2.4, "p": 0.85}, {"w": "office.", "t0": 2.4, "t1": 3.0, "p": 0.75}, {"w": "I'm", "t0": 3.7, "t1": 4.24, "p": 0.9}, {"w": "in", "t0": 4.24, "t1": 4.38, "p": 0.99}, {"w": "a", "t0": 4.38, "t1": 4.5, "p": 0.97}, {"w": "board", "t0": 4.5, "t1": 4.76, "p": 0.92}, {"w": "meeting", "t0": 4.76, "t1": 5.22, "p": 1.0}, {"w": "and", "t0": 5.22, "t1": 5.78, "p": 0.87}, {"w": "can't", "t0": 5.78, "t1": 6.18, "p": 0.96}, {"w": "take", "t0": 6.18, "t1": 6.44, "p": 1.0}, {"w": "calls.", "t0": 6.44, "t1": 6.84, "p": 0.97}, {"w": "Please", "t0": 7.86, "t1": 8.12, "p": 0.98}, {"w": "wire", "t0": 8.12, "t1": 8.52, "p": 0.87}, {"w": "48", "t0": 8.52, "t1": 9.34, "p": 0.94}, {"w": "lakh", "t0": 9.34, "t1": 9.7, "p": 0.31}, {"w": "rupees", "t0": 9.7, "t1": 10.14, "p": 0.89}, {"w": "to", "t0": 10.14, "t1": 10.48, "p": 0.99}, {"w": "the", "t0": 10.48, "t1": 10.62, "p": 0.99}, {"w": "new", "t0": 10.62, "t1": 10.84, "p": 0.85}, {"w": "vendor", "t0": 10.84, "t1": 11.18, "p": 0.81}, {"w": "account", "t0": 11.18, "t1": 11.66, "p": 0.99}, {"w": "before", "t0": 11.66, "t1": 12.16, "p": 0.92}, {"w": "4", "t0": 12.16, "t1": 12.7, "p": 0.98}, {"w": "pm", "t0": 12.7, "t1": 13.02, "p": 0.33}, {"w": "it's", "t0": 13.02, "t1": 13.54, "p": 0.68}, {"w": "urgent", "t0": 13.54, "t1": 13.86, "p": 0.98}, {"w": "and", "t0": 13.86, "t1": 14.26, "p": 0.98}, {"w": "confidential.", "t0": 14.26, "t1": 14.94, "p": 1.0}, {"w": "Don't", "t0": 15.42, "t1": 15.72, "p": 0.93}, {"w": "loop", …(truncated)
A59: 58 | B59: MRG-0519 | C59: video | D59: video_call.mp4 | E59: video/mp4 | F59: c82097dc6a47d2309350a516a095c5a8eb99a548c9001f7dcf3bc26eff30d2d0 | G59: 378965 | H59: c8/c82097dc6a47d2309350a516a095c5a8eb99a548c9001f7dcf3bc26eff30d2d0.mp4 | I59: 23.1 | J59: {"asr": {"text": "This is Inspector Sharma from the CBI CyberSair. A parcel in your name has illegal items and an arrest warrant is issued. Stay on this video call and do not disconnect. Transfer your savings to the RBI verification account to avoid arrest. Do not tell anyone.", "language": "en", "language_p": 1.0, "words": [{"w": "This", "t0": 0.0, "t1": 0.4, "p": 0.93}, {"w": "is", "t0": 0.4, "t1": 0.7, "p": 0.99}, {"w": "Inspector", "t0": 0.7, "t1": 1.34, "p": 0.87}, {"w": "Sharma", "t0": 1.34, "t1": 1.84, "p": 0.97}, {"w": "from", "t0": 1.84, "t1": 2.14, "p": 0.98}, {"w": "the", "t0": 2.14, "t1": 2.3, "p": 0.93}, {"w": "CBI", "t0": 2.3, "t1": 2.84, "p": 0.75}, {"w": "CyberSair.", "t0": 2.84, "t1": 3.7, "p": 0.23}, {"w": "A", "t0": 4.36, "t1": 4.92, "p": 0.82}, {"w": "parcel", "t0": 4.92, "t1": 5.2, "p": 0.98}, {"w": "in", "t0": 5.2, "t1": 5.56, "p": 0.98}, {"w": "your", "t0": 5.56, "t1": 5.8, "p": 0.99}, {"w": "name", "t0": 5.8, "t1": 6.14, "p": 0.97}, {"w": "has", "t0": 6.14, "t1": 6.62, "p": 0.99}, {"w": "illegal", "t0": 6.62, "t1": 7.02, "p": 0.98}, {"w": "items", "t0": 7.02, "t1": 7.54, "p": 0.98}, {"w": "and", "t0": 7.54, "t1": 8.1, "p": 0.79}, {"w": "an", "t0": 8.1, "t1": 8.36, "p": 0.85}, {"w": "arrest", "t0": 8.36, "t1": 8.56, "p": 0.99}, {"w": "warrant", "t0": 8.56, "t1": 9.04, "p": 1.0}, {"w": "is", "t0": 9.04, "t1": 9.38, "p": 0.96}, {"w": "issued.", "t0": 9.38, "t1": 9.72, "p": 0.99}, {"w": "Stay", "t0": 10.34, "t1": 11.06, "p": 0.97}, {"w": "on", "t0": 11.06, "t1": 11.36, "p": 1.0}, {"w": "this", "t0": 11.36, "t1": 11.68, "p": 0.99}, {"w": "video", "t0": 11.68, "t1": 12.06, "p": 0.98}, {"w": "call", "t0": 12.06, "t1": 12.38, "p": 0.93}, {"w": "and", "t0": 12.38, "t1": 12.9, "p": 0.93}, {"w": "do", "t0": 12.9, "t1": 13.08, "p": 0.97}, {"w": "not", "t0": 13.08, "t1": 13.32, "p": 0.99}, {"w": "disconnect.", "t0": 13.32, "t1": 13.92, "p": 1.0}, {"w": "Transfer", "t0": 14.86, "t1": 15.48, "p": 0.98}, {"w": "your", "t0": 15.48, "t1": 15.82, "p": 0.99}, {" …(truncated)
A60: 59 | B60: MRG-0520 | C60: audio | D60: papa_voice.ogg | E60: audio/ogg | F60: 5bc20c8a106e85862e3a8d71c9ba55d57d863e6ab5d75e170636c2243ddd4e23 | G60: 38664 | H60: 5b/5bc20c8a106e85862e3a8d71c9ba55d57d863e6ab5d75e170636c2243ddd4e23.ogg | I60: 16.99 | J60: {"asr": {"text": "Papa, I am. Accident is over and phone is broken. This is the number of friends.", "language": "hi-Latn (Hinglish)", "language_p": 1.0, "words": [{"w": "Papa,", "t0": 0.0, "t1": 0.58, "p": 0.37}, {"w": "I", "t0": 0.9, "t1": 1.3, "p": 0.89}, {"w": "am.", "t0": 1.3, "t1": 1.6, "p": 0.79}, {"w": "Accident", "t0": 2.62, "t1": 3.26, "p": 0.58}, {"w": "is", "t0": 3.26, "t1": 3.52, "p": 0.65}, {"w": "over", "t0": 3.52, "t1": 3.72, "p": 0.08}, {"w": "and", "t0": 3.72, "t1": 4.22, "p": 0.69}, {"w": "phone", "t0": 4.22, "t1": 4.54, "p": 0.23}, {"w": "is", "t0": 4.54, "t1": 4.8, "p": 0.7}, {"w": "broken.", "t0": 4.8, "t1": 4.96, "p": 0.62}, {"w": "This", "t0": 5.44, "t1": 5.72, "p": 0.69}, {"w": "is", "t0": 5.72, "t1": 6.14, "p": 0.93}, {"w": "the", "t0": 6.14, "t1": 6.3, "p": 0.66}, {"w": "number", "t0": 6.3, "t1": 6.62, "p": 0.67}, {"w": "of", "t0": 6.62, "t1": 6.78, "p": 0.95}, {"w": "friends.", "t0": 6.78, "t1": 6.78, "p": 0.75}], "engine": "faster-whisper/base"}}
A61: 60 | B61: MRG-0521 | C61: image | D61: accounts_manager.jpg | E61: image/jpeg | F61: 044c58a1e2a77eb23602a272ef458789c1e9fe7ff494c7a7adb14ec045624187 | G61: 71244 | H61: 04/044c58a1e2a77eb23602a272ef458789c1e9fe7ff494c7a7adb14ec045624187.jpg | J61: {"ocr": {"text": "MIRAGE RED TEAM\u00b7SYNTHETIC", "lines": [{"text": "MIRAGE RED TEAM\u00b7SYNTHETIC", "conf": 0.98, "box": [0.6914, 0.9688, 0.2969, 0.0273]}], "engine": "rapidocr"}}
A62: 61 | B62: MRG-0521 | C62: text | D62: invoice.eml | E62: text/plain | F62: f8a7017d25072502f6e6cf4390b82f690ceaf4c6fac0c321f87dbf16a6856e79 | G62: 960 | H62: f8/f8a7017d25072502f6e6cf4390b82f690ceaf4c6fac0c321f87dbf16a6856e79.eml | J62: {}
A63: 62 | B63: MRG-0522 | C63: audio | D63: townhall.mp3 | E63: audio/mpeg | F63: e6d8bbfd37a6f671ac1887cebe8cbbb9a77ceb30a0ba791a8c625227c1610534 | G63: 97100 | H63: e6/e6d8bbfd37a6f671ac1887cebe8cbbb9a77ceb30a0ba791a8c625227c1610534.mp3 | I63: 12 | J63: {"asr": {"text": "Good morning team. The quarterly town hall moves to Friday at 4pm in the main auditorium. Snacks will be served. See you there.", "language": "en", "language_p": 1.0, "words": [{"w": "Good", "t0": 0.0, "t1": 0.4, "p": 0.84}, {"w": "morning", "t0": 0.4, "t1": 0.78, "p": 0.81}, {"w": "team.", "t0": 0.78, "t1": 1.26, "p": 0.75}, {"w": "The", "t0": 2.28, "t1": 2.4, "p": 0.98}, {"w": "quarterly", "t0": 2.4, "t1": 2.86, "p": 0.68}, {"w": "town", "t0": 2.86, "t1": 3.18, "p": 0.89}, {"w": "hall", "t0": 3.18, "t1": 3.48, "p": 0.98}, {"w": "moves", "t0": 3.48, "t1": 3.78, "p": 0.99}, {"w": "to", "t0": 3.78, "t1": 4.04, "p": 0.99}, {"w": "Friday", "t0": 4.04, "t1": 4.36, "p": 0.93}, {"w": "at", "t0": 4.36, "t1": 4.74, "p": 0.98}, {"w": "4pm", "t0": 4.74, "t1": 5.38, "p": 0.66}, {"w": "in", "t0": 5.38, "t1": 5.7, "p": 0.97}, {"w": "the", "t0": 5.7, "t1": 5.8, "p": 0.97}, {"w": "main", "t0": 5.8, "t1": 6.12, "p": 0.95}, {"w": "auditorium.", "t0": 6.12, "t1": 6.92, "p": 1.0}, {"w": "Snacks", "t0": 7.92, "t1": 8.4, "p": 0.95}, {"w": "will", "t0": 8.4, "t1": 8.62, "p": 1.0}, {"w": "be", "t0": 8.62, "t1": 8.8, "p": 1.0}, {"w": "served.", "t0": 8.8, "t1": 9.18, "p": 0.99}, {"w": "See", "t0": 10.02, "t1": 10.54, "p": 0.99}, {"w": "you", "t0": 10.54, "t1": 10.7, "p": 0.99}, {"w": "there.", "t0": 10.7, "t1": 10.96, "p": 0.99}], "engine": "faster-whisper/base"}}
A64: 63 | B64: MRG-0523 | C64: audio | D64: papa_voice_note.wav | E64: audio/wav | F64: 8ee650801c14eee68e4b6c098d232806785b31a005cd15483c392f5942151589 | G64: 359182 | H64: 8e/8ee650801c14eee68e4b6c098d232806785b31a005cd15483c392f5942151589.wav | I64: 11.22 | J64: {"asr": {"text": "Beta main hoon, accident ho gaya high, phone toot gaya, pays abi burjo, 75 ,000, G -she -ke -oh mat Pat No Please.", "language": "en", "language_p": 1.0, "words": [{"w": "Beta", "t0": 0.0, "t1": 0.36, "p": 0.56}, {"w": "main", "t0": 0.36, "t1": 0.6, "p": 0.39}, {"w": "hoon,", "t0": 0.6, "t1": 0.96, "p": 0.57}, {"w": "accident", "t0": 1.36, "t1": 1.76, "p": 0.77}, {"w": "ho", "t0": 1.76, "t1": 2.02, "p": 0.53}, {"w": "gaya", "t0": 2.02, "t1": 2.34, "p": 0.52}, {"w": "high,", "t0": 2.34, "t1": 2.74, "p": 0.32}, {"w": "phone", "t0": 3.1, "t1": 3.26, "p": 0.79}, {"w": "toot", "t0": 3.26, "t1": 3.6, "p": 0.69}, {"w": "gaya,", "t0": 3.6, "t1": 3.9, "p": 0.98}, {"w": "pays", "t0": 4.54, "t1": 5.14, "p": 0.43}, {"w": "abi", "t0": 5.14, "t1": 5.42, "p": 0.2}, {"w": "burjo,", "t0": 5.42, "t1": 5.74, "p": 0.73}, {"w": "75", "t0": 6.26, "t1": 6.94, "p": 0.77}, {"w": ",000,", "t0": 6.94, "t1": 8.32, "p": 0.67}, {"w": "G", "t0": 8.54, "t1": 8.74, "p": 0.46}, {"w": "-she", "t0": 8.74, "t1": 8.96, "p": 0.24}, {"w": "-ke", "t0": 8.96, "t1": 9.18, "p": 0.2}, {"w": "-oh", "t0": 9.18, "t1": 9.3, "p": 0.3}, {"w": "mat", "t0": 9.3, "t1": 9.52, "p": 0.32}, {"w": "Pat", "t0": 9.52, "t1": 9.74, "p": 0.14}, {"w": "No", "t0": 9.74, "t1": 9.9, "p": 0.28}, {"w": "Please.", "t0": 9.9, "t1": 10.2, "p": 0.36}], "engine": "faster-whisper/base"}}
A65: 64 | B65: MRG-0524 | C65: audio | D65: en_cfo_payment.wav | E65: audio/wav | F65: 9c2dc59996e0c43f7bc7eaf65d9d5326eedb9819ddecd62acb29b0cacf9516a4 | G65: 516140 | H65: 9c/9c2dc59996e0c43f7bc7eaf65d9d5326eedb9819ddecd62acb29b0cacf9516a4.wav | I65: 16.13 | J65: {"asr": {"text": "Hi, this is Rajesh, the CFO. I'm in a board meeting. Transfer 12 lakh rupees to the new vendor account today and keep it confidential. Don't call me, just do it before 4.", "language": "en", "language_p": 1.0, "words": [{"w": "Hi,", "t0": 0.0, "t1": 0.38, "p": 0.9}, {"w": "this", "t0": 0.7, "t1": 0.92, "p": 0.79}, {"w": "is", "t0": 0.92, "t1": 1.22, "p": 0.99}, {"w": "Rajesh,", "t0": 1.22, "t1": 1.64, "p": 0.97}, {"w": "the", "t0": 2.02, "t1": 2.12, "p": 0.97}, {"w": "CFO.", "t0": 2.12, "t1": 2.58, "p": 0.91}, {"w": "I'm", "t0": 3.38, "t1": 3.88, "p": 0.79}, {"w": "in", "t0": 3.88, "t1": 4.04, "p": 0.99}, {"w": "a", "t0": 4.04, "t1": 4.16, "p": 0.98}, {"w": "board", "t0": 4.16, "t1": 4.42, "p": 0.86}, {"w": "meeting.", "t0": 4.42, "t1": 4.92, "p": 1.0}, {"w": "Transfer", "t0": 5.82, "t1": 6.36, "p": 0.97}, {"w": "12", "t0": 6.36, "t1": 6.9, "p": 0.83}, {"w": "lakh", "t0": 6.9, "t1": 7.14, "p": 0.44}, {"w": "rupees", "t0": 7.14, "t1": 7.58, "p": 0.88}, {"w": "to", "t0": 7.58, "t1": 7.92, "p": 0.99}, {"w": "the", "t0": 7.92, "t1": 8.06, "p": 0.97}, {"w": "new", "t0": 8.06, "t1": 8.28, "p": 0.88}, {"w": "vendor", "t0": 8.28, "t1": 8.64, "p": 0.72}, {"w": "account", "t0": 8.64, "t1": 9.08, "p": 0.99}, {"w": "today", "t0": 9.08, "t1": 9.58, "p": 0.99}, {"w": "and", "t0": 9.58, "t1": 10.2, "p": 0.66}, {"w": "keep", "t0": 10.2, "t1": 10.46, "p": 1.0}, {"w": "it", "t0": 10.46, "t1": 10.7, "p": 1.0}, {"w": "confidential.", "t0": 10.7, "t1": 11.34, "p": 1.0}, {"w": "Don't", "t0": 12.26, "t1": 12.76, "p": 0.97}, {"w": "call", "t0": 12.76, "t1": 12.98, "p": 0.98}, {"w": "me,", "t0": 12.98, "t1": 13.28, "p": 0.99}, {"w": "just", "t0": 13.68, "t1": 13.86, "p": 0.95}, {"w": "do", "t0": 13.86, "t1": 14.22, "p": 1.0}, {"w": "it", "t0": 14.22, "t1": 14.44, "p": 1.0}, {"w": "before", "t0": 14.44, "t1": 14.78, "p": 0.99}, {"w": "4.", "t0": 14.78, "t1": 15.24, "p": 0.91}], "engine": "faster-whisper/base"}}
A66: 65 | B66: MRG-0525 | C66: audio | D66: hi_digital_arrest.wav | E66: audio/wav | F66: 199e85bffa3c9e5c809b3a12a4e6b87d8549803328e29a7edbfb76177670d5e8 | G66: 473900 | H66: 19/199e85bffa3c9e5c809b3a12a4e6b87d8549803328e29a7edbfb76177670d5e8.wav | I66: 14.81 | J66: {"asr": {"text": "I am speaking with CBI. Your name is Drugs parcel. Don't call anyone. Send two lakh rupees to the judge.", "language": "hi-Latn (Hinglish)", "language_p": 1.0, "words": [{"w": "I", "t0": 0.0, "t1": 0.42, "p": 0.68}, {"w": "am", "t0": 0.42, "t1": 0.42, "p": 0.79}, {"w": "speaking", "t0": 0.42, "t1": 0.42, "p": 0.69}, {"w": "with", "t0": 0.42, "t1": 0.42, "p": 0.29}, {"w": "CBI.", "t0": 0.42, "t1": 1.02, "p": 0.77}, {"w": "Your", "t0": 3.32, "t1": 3.94, "p": 0.23}, {"w": "name", "t0": 3.94, "t1": 4.3, "p": 0.95}, {"w": "is", "t0": 4.3, "t1": 4.64, "p": 0.66}, {"w": "Drugs", "t0": 4.64, "t1": 4.98, "p": 0.55}, {"w": "parcel.", "t0": 4.98, "t1": 5.6, "p": 0.32}, {"w": "Don't", "t0": 6.56, "t1": 7.78, "p": 0.81}, {"w": "call", "t0": 7.78, "t1": 7.78, "p": 0.42}, {"w": "anyone.", "t0": 7.78, "t1": 8.82, "p": 0.69}, {"w": "Send", "t0": 10.46, "t1": 11.7, "p": 0.01}, {"w": "two", "t0": 11.7, "t1": 12.06, "p": 0.58}, {"w": "lakh", "t0": 12.06, "t1": 12.4, "p": 0.52}, {"w": "rupees", "t0": 12.4, "t1": 12.78, "p": 0.33}, {"w": "to", "t0": 12.78, "t1": 13.7, "p": 0.29}, {"w": "the", "t0": 13.7, "t1": 13.7, "p": 0.46}, {"w": "judge.", "t0": 13.7, "t1": 13.7, "p": 0.31}], "engine": "faster-whisper/base"}}
A67: 66 | B67: MRG-0526 | C67: audio | D67: en_benign_townhall.wav | E67: audio/wav | F67: 19e41e05058d84b2666886cfba24e5c95288ff94c9ce177d43005c49efdfeb1f | G67: 303404 | H67: 19/19e41e05058d84b2666886cfba24e5c95288ff94c9ce177d43005c49efdfeb1f.wav | I67: 9.48 | J67: {"asr": {"text": "Reminder, the quarterly town hall moves to Friday at 4pm the agenda is in your calendar invite. See you there.", "language": "en", "language_p": 1.0, "words": [{"w": "Reminder,", "t0": 0.0, "t1": 0.78, "p": 0.9}, {"w": "the", "t0": 1.16, "t1": 1.3, "p": 0.91}, {"w": "quarterly", "t0": 1.3, "t1": 1.74, "p": 0.83}, {"w": "town", "t0": 1.74, "t1": 2.06, "p": 0.87}, {"w": "hall", "t0": 2.06, "t1": 2.34, "p": 0.99}, {"w": "moves", "t0": 2.34, "t1": 2.62, "p": 0.98}, {"w": "to", "t0": 2.62, "t1": 2.9, "p": 0.99}, {"w": "Friday", "t0": 2.9, "t1": 3.24, "p": 0.95}, {"w": "at", "t0": 3.24, "t1": 3.64, "p": 0.96}, {"w": "4pm", "t0": 3.64, "t1": 4.3, "p": 0.67}, {"w": "the", "t0": 4.3, "t1": 4.56, "p": 0.6}, {"w": "agenda", "t0": 4.56, "t1": 5.0, "p": 0.96}, {"w": "is", "t0": 5.0, "t1": 5.34, "p": 0.97}, {"w": "in", "t0": 5.34, "t1": 5.48, "p": 1.0}, {"w": "your", "t0": 5.48, "t1": 5.62, "p": 0.99}, {"w": "calendar", "t0": 5.62, "t1": 6.1, "p": 0.97}, {"w": "invite.", "t0": 6.1, "t1": 6.66, "p": 0.94}, {"w": "See", "t0": 7.36, "t1": 8.04, "p": 0.98}, {"w": "you", "t0": 8.04, "t1": 8.2, "p": 0.97}, {"w": "there.", "t0": 8.2, "t1": 8.42, "p": 0.99}], "engine": "faster-whisper/base"}}
A68: 67 | B68: MRG-0527 | C68: audio | D68: spk6930_000.flac | E68: audio/flac | F68: 3f06a2712cadb8d5bca9618a1560112d7e1e0c229e0dd7f0c4f736f4bcb661b3 | G68: 217708 | H68: 3f/3f06a2712cadb8d5bca9618a1560112d7e1e0c229e0dd7f0c4f736f4bcb661b3.flac | I68: 10.81 | J68: {"asr": {"text": "The night was clear, starlet and splendid. The tempest had passed away, and the sweet influences of the evening had restored life, peace and security everywhere.", "language": "en", "language_p": 1.0, "words": [{"w": "The", "t0": 0.0, "t1": 0.4, "p": 0.86}, {"w": "night", "t0": 0.4, "t1": 0.62, "p": 0.98}, {"w": "was", "t0": 0.62, "t1": 0.86, "p": 1.0}, {"w": "clear,", "t0": 0.86, "t1": 1.18, "p": 1.0}, {"w": "starlet", "t0": 1.52, "t1": 1.86, "p": 0.52}, {"w": "and", "t0": 1.86, "t1": 2.18, "p": 0.76}, {"w": "splendid.", "t0": 2.18, "t1": 2.86, "p": 0.93}, {"w": "The", "t0": 3.26, "t1": 3.3, "p": 0.99}, {"w": "tempest", "t0": 3.3, "t1": 3.76, "p": 0.95}, {"w": "had", "t0": 3.76, "t1": 3.92, "p": 0.99}, {"w": "passed", "t0": 3.92, "t1": 4.28, "p": 0.99}, {"w": "away,", "t0": 4.28, "t1": 4.68, "p": 1.0}, {"w": "and", "t0": 4.92, "t1": 4.96, "p": 0.98}, {"w": "the", "t0": 4.96, "t1": 5.1, "p": 1.0}, {"w": "sweet", "t0": 5.1, "t1": 5.46, "p": 0.99}, {"w": "influences", "t0": 5.46, "t1": 6.14, "p": 0.99}, {"w": "of", "t0": 6.14, "t1": 6.44, "p": 1.0}, {"w": "the", "t0": 6.44, "t1": 6.64, "p": 0.99}, {"w": "evening", "t0": 6.64, "t1": 6.94, "p": 1.0}, {"w": "had", "t0": 6.94, "t1": 7.18, "p": 0.97}, {"w": "restored", "t0": 7.18, "t1": 7.64, "p": 0.99}, {"w": "life,", "t0": 7.64, "t1": 8.26, "p": 0.99}, {"w": "peace", "t0": 8.78, "t1": 8.9, "p": 1.0}, {"w": "and", "t0": 8.9, "t1": 9.18, "p": 0.56}, {"w": "security", "t0": 9.18, "t1": 9.72, "p": 1.0}, {"w": "everywhere.", "t0": 9.72, "t1": 10.36, "p": 0.95}], "engine": "faster-whisper/base"}}
A69: 68 | B69: MRG-0528 | C69: audio | D69: spk6930_000.flac | E69: audio/flac | F69: 3f06a2712cadb8d5bca9618a1560112d7e1e0c229e0dd7f0c4f736f4bcb661b3 | G69: 217708 | H69: 3f/3f06a2712cadb8d5bca9618a1560112d7e1e0c229e0dd7f0c4f736f4bcb661b3.flac | I69: 10.81 | J69: {"asr": {"text": "The night was clear, starlet and splendid. The tempest had passed away, and the sweet influences of the evening had restored life, peace and security everywhere.", "language": "en", "language_p": 1.0, "words": [{"w": "The", "t0": 0.0, "t1": 0.4, "p": 0.86}, {"w": "night", "t0": 0.4, "t1": 0.62, "p": 0.98}, {"w": "was", "t0": 0.62, "t1": 0.86, "p": 1.0}, {"w": "clear,", "t0": 0.86, "t1": 1.18, "p": 1.0}, {"w": "starlet", "t0": 1.52, "t1": 1.86, "p": 0.52}, {"w": "and", "t0": 1.86, "t1": 2.18, "p": 0.76}, {"w": "splendid.", "t0": 2.18, "t1": 2.86, "p": 0.93}, {"w": "The", "t0": 3.26, "t1": 3.3, "p": 0.99}, {"w": "tempest", "t0": 3.3, "t1": 3.76, "p": 0.95}, {"w": "had", "t0": 3.76, "t1": 3.92, "p": 0.99}, {"w": "passed", "t0": 3.92, "t1": 4.28, "p": 0.99}, {"w": "away,", "t0": 4.28, "t1": 4.68, "p": 1.0}, {"w": "and", "t0": 4.92, "t1": 4.96, "p": 0.98}, {"w": "the", "t0": 4.96, "t1": 5.1, "p": 1.0}, {"w": "sweet", "t0": 5.1, "t1": 5.46, "p": 0.99}, {"w": "influences", "t0": 5.46, "t1": 6.14, "p": 0.99}, {"w": "of", "t0": 6.14, "t1": 6.44, "p": 1.0}, {"w": "the", "t0": 6.44, "t1": 6.64, "p": 0.99}, {"w": "evening", "t0": 6.64, "t1": 6.94, "p": 1.0}, {"w": "had", "t0": 6.94, "t1": 7.18, "p": 0.97}, {"w": "restored", "t0": 7.18, "t1": 7.64, "p": 0.99}, {"w": "life,", "t0": 7.64, "t1": 8.26, "p": 0.99}, {"w": "peace", "t0": 8.78, "t1": 8.9, "p": 1.0}, {"w": "and", "t0": 8.9, "t1": 9.18, "p": 0.56}, {"w": "security", "t0": 9.18, "t1": 9.72, "p": 1.0}, {"w": "everywhere.", "t0": 9.72, "t1": 10.36, "p": 0.95}], "engine": "faster-whisper/base"}}
A70: 69 | B70: MRG-0529 | C70: image | D70: 02.png | E70: image/png | F70: ecd406882d7865d068ce1df66d8661c7e8943be2e2205fce1f43bd277e7f8199 | G70: 380588 | H70: ec/ecd406882d7865d068ce1df66d8661c7e8943be2e2205fce1f43bd277e7f8199.png | J70: {"ocr": {"text": "MIRAGE RED TEAM\u00b7SYNTHETIC", "lines": [{"text": "MIRAGE RED TEAM\u00b7SYNTHETIC", "conf": 0.96, "box": [0.6875, 0.9668, 0.3027, 0.0312]}], "engine": "rapidocr"}}
A71: 70 | B71: MRG-0530 | C71: image | D71: 000.jpg | E71: image/jpeg | F71: fe553ba0662dcbb1a66e8aabcbd421831bb3f31536ab89ff8c464a3fd59387c6 | G71: 22901 | H71: fe/fe553ba0662dcbb1a66e8aabcbd421831bb3f31536ab89ff8c464a3fd59387c6.jpg | J71: {}
A72: 71 | B72: MRG-0536 | C72: audio | D72: ta_otp.wav | E72: audio/wav | F72: 0e30f0bdfc206f4787d0a4ec69f695f50db7d3f57c858dbb876fbc1507e1fb45 | G72: 330284 | H72: 0e/0e30f0bdfc206f4787d0a4ec69f695f50db7d3f57c858dbb876fbc1507e1fb45.wav | I72: 10.32 | J72: {"asr": {"text": "\u0bb5\u0ba3\u0b95\u0bcd\u0b95\u0bae\u0bcd \u0ba8\u0bbe\u0ba9\u0bcd \u0bb5\u0ba3\u0bcd\u0b95\u0bbf\u0baf\u0bbf\u0bb2\u0bbf\u0bb0\u0bc1\u0ba8\u0bcd\u0ba4\u0bc1 \u0baa\u0bc7\u0b9a\u0bc1\u0b95\u0bbf\u0bb1\u0bc7\u0ba9\u0bcd \u0b89\u0b99\u0bcd\u0b95\u0bb3\u0bcd \u0b95\u0ba3\u0b95\u0bcd\u0b95\u0bc1 \u0b8e\u0ba9\u0bcd\u0bb1\u0bc1 \u0bae\u0bc1\u0b9f\u0b95\u0bcd\u0b95\u0baa\u0bcd\u0baa\u0b9f\u0bc1\u0bae\u0bcd \u0b89\u0b99\u0bcd\u0b95\u0bb3\u0bcd \u0bae\u0bc1\u0baa\u0bcd\u0baa\u0bc8\u0baf\u0bbf\u0bb2\u0bcd \u0b95\u0bc1 \u0bb5\u0ba8\u0bcd\u0ba4\u0bc1 OTP -NNI \u0b89\u0b9f\u0ba9\u0bc7 \u0b9a\u0bca\u0bb2\u0bcd\u0bb2\u0b99\u0bcd\u0b95\u0bb3\u0bcd", "language": "ta", "language_p": 1.0, "words": [{"w": "\u0bb5\u0ba3\u0b95\u0bcd\u0b95\u0bae\u0bcd", "t0": 0.0, "t1": 0.9, "p": 0.8}, {"w": "\u0ba8\u0bbe\u0ba9\u0bcd", "t0": 0.9, "t1": 1.4, "p": 0.83}, {"w": "\u0bb5\u0ba3\u0bcd\u0b95\u0bbf\u0baf\u0bbf\u0bb2\u0bbf\u0bb0\u0bc1\u0ba8\u0bcd\u0ba4\u0bc1", "t0": 1.4, "t1": 2.18, "p": 0.73}, {"w": "\u0baa\u0bc7\u0b9a\u0bc1\u0b95\u0bbf\u0bb1\u0bc7\u0ba9\u0bcd", "t0": 2.18, "t1": 3.0, "p": 0.81}, {"w": "\u0b89\u0b99\u0bcd\u0b95\u0bb3\u0bcd", "t0": 3.8, "t1": 4.2, "p": 0.92}, {"w": "\u0b95\u0ba3\u0b95\u0bcd\u0b95\u0bc1", "t0": 4.2, "t1": 4.58, "p": 0.89}, {"w": "\u0b8e\u0ba9\u0bcd\u0bb1\u0bc1", "t0": 4.58, "t1": 4.94, "p": 0.76}, {"w": "\u0bae\u0bc1\u0b9f\u0b95\u0bcd\u0b95\u0baa\u0bcd\u0baa\u0b9f\u0bc1\u0bae\u0bcd", "t0": 4.94, "t1": 6.3, "p": 0.78}, {"w": "\u0b89\u0b99\u0bcd\u0b95\u0bb3\u0bcd", "t0": 6.3, "t1": 7.14, "p": 0.99}, {"w": "\u0bae\u0bc1\u0baa\u0bcd\u0baa\u0bc8\u0baf\u0bbf\u0bb2\u0bcd", "t0": 7.14, "t1": 7.56, "p": 0.7}, {"w": "\u0b95\u0bc1", "t0": 7.56, "t1": 7.72, "p": 0.35}, {"w": "\u0bb5\u0ba8\u0bcd\u0ba4\u0bc1", "t0": 7.72, "t1": 8.18, "p": 0.74}, {"w": "OTP", "t0": 8.18, "t1": 8.6, "p": 0.51}, {"w": "-NNI", "t0": 8.6, "t1": 9.12, "p": 0.48}, {"w": "\u0b89\u0b9f\u0ba9\u0bc7", "t0": 9.12, "t1": 9.54, "p": 0.7}, {"w": "\u0b9a\u0bca\u0bb2\u0bcd\u0bb2\u0b99\u0bcd\u0b …(truncated)
A73: 72 | B73: MRG-0537 | C73: audio | D73: google_tamil_m_spk3191_002__noise.wav | E73: audio/wav | F73: 90db5ae7d9061875784f6361967a0f31023fdb9b0c5e15c1e72bd6e964ccae17 | G73: 155692 | H73: 90/90db5ae7d9061875784f6361967a0f31023fdb9b0c5e15c1e72bd6e964ccae17.wav | I73: 4.86 | J73: {"asr": {"text": "\u0ba8\u0bcb\u0b95\u0bcd\u0b95\u0bbf\u0baf\u0bbe \u0bae\u0bc8\u0b95\u0bcd\u0b95\u0bb0\u0b9a\u0bcd \u0b9a\u0bbe\u0baa\u0bcd\u0b9f\u0bc1\u0b9f\u0ba9\u0bcd \u0b8e\u0ba9\u0bcd\u0ba9 \u0b87\u0ba8\u0bcd\u0ba4 \u0b9a\u0bc6\u0baf\u0bcd\u0baf\u0bb2\u0bcd \u0baa\u0b9f \u0bae\u0bc1\u0b9f\u0bbf\u0bb5\u0bc7", "language": "ta", "language_p": 1.0, "words": [{"w": "\u0ba8\u0bcb\u0b95\u0bcd\u0b95\u0bbf\u0baf\u0bbe", "t0": 0.4, "t1": 1.2, "p": 0.61}, {"w": "\u0bae\u0bc8\u0b95\u0bcd\u0b95\u0bb0\u0b9a\u0bcd", "t0": 1.2, "t1": 1.68, "p": 0.51}, {"w": "\u0b9a\u0bbe\u0baa\u0bcd\u0b9f\u0bc1\u0b9f\u0ba9\u0bcd", "t0": 1.68, "t1": 2.32, "p": 0.74}, {"w": "\u0b8e\u0ba9\u0bcd\u0ba9", "t0": 2.32, "t1": 2.48, "p": 0.79}, {"w": "\u0b87\u0ba8\u0bcd\u0ba4", "t0": 2.48, "t1": 2.68, "p": 0.88}, {"w": "\u0b9a\u0bc6\u0baf\u0bcd\u0baf\u0bb2\u0bcd", "t0": 2.68, "t1": 3.24, "p": 0.71}, {"w": "\u0baa\u0b9f", "t0": 3.24, "t1": 3.32, "p": 0.7}, {"w": "\u0bae\u0bc1\u0b9f\u0bbf\u0bb5\u0bc7", "t0": 3.32, "t1": 3.72, "p": 0.79}], "engine": "faster-whisper/base"}}
A74: 73 | B74: MRG-0538 | C74: video | D74: 02_ai_avatar_investment_endorsement.mp4 | E74: video/mp4 | F74: 1a456cad8d21c7302376cd537c1a918357601ee7218dae499462eaef63939c8c | G74: 243404 | H74: 1a/1a456cad8d21c7302376cd537c1a918357601ee7218dae499462eaef63939c8c.mp4 | I74: 14.14 | J74: {"asr": {"text": "I personally use this trading platform. Invest just 20 ,000 today and earn 4 % daily guaranteed. registration closes tonight, join the WhatsApp group now.", "language": "en", "language_p": 1.0, "words": [{"w": "I", "t0": 0.0, "t1": 0.28, "p": 0.95}, {"w": "personally", "t0": 0.28, "t1": 0.74, "p": 0.99}, {"w": "use", "t0": 0.74, "t1": 1.2, "p": 0.76}, {"w": "this", "t0": 1.2, "t1": 1.44, "p": 0.98}, {"w": "trading", "t0": 1.44, "t1": 1.86, "p": 0.98}, {"w": "platform.", "t0": 1.86, "t1": 2.46, "p": 0.99}, {"w": "Invest", "t0": 3.38, "t1": 3.84, "p": 0.93}, {"w": "just", "t0": 3.84, "t1": 4.3, "p": 0.96}, {"w": "20", "t0": 4.3, "t1": 4.84, "p": 0.75}, {"w": ",000", "t0": 4.84, "t1": 5.22, "p": 0.89}, {"w": "today", "t0": 5.22, "t1": 5.58, "p": 0.93}, {"w": "and", "t0": 5.58, "t1": 6.2, "p": 0.67}, {"w": "earn", "t0": 6.2, "t1": 6.44, "p": 1.0}, {"w": "4", "t0": 6.44, "t1": 6.94, "p": 0.99}, {"w": "%", "t0": 6.94, "t1": 7.3, "p": 0.9}, {"w": "daily", "t0": 7.3, "t1": 7.78, "p": 0.98}, {"w": "guaranteed.", "t0": 7.78, "t1": 8.5, "p": 0.89}, {"w": "registration", "t0": 8.5, "t1": 10.08, "p": 0.18}, {"w": "closes", "t0": 10.08, "t1": 10.68, "p": 0.82}, {"w": "tonight,", "t0": 10.68, "t1": 11.18, "p": 0.98}, {"w": "join", "t0": 11.68, "t1": 11.86, "p": 0.84}, {"w": "the", "t0": 11.86, "t1": 12.08, "p": 0.95}, {"w": "WhatsApp", "t0": 12.08, "t1": 12.48, "p": 0.77}, {"w": "group", "t0": 12.48, "t1": 12.9, "p": 0.81}, {"w": "now.", "t0": 12.9, "t1": 13.26, "p": 0.98}], "engine": "faster-whisper/base"}}
A75: 74 | B75: MRG-0539 | C75: audio | D75: call_recording.wav | E75: audio/wav | F75: e57baef93c3d286b592c58cc231c8beb30d4dfa75f0c66d1a36fbd00095fc407 | G75: 917036 | H75: e5/e57baef93c3d286b592c58cc231c8beb30d4dfa75f0c66d1a36fbd00095fc407.wav | I75: 28.66 | J75: {"asr": {"text": "Hello, this is Inspector Rajeev Rathard from the Cybercrime Cell. Your father has been arrested in a hit and run case and is in our custody. To avoid an FIR and Jail tonight, you must deposit 50 ,000 rupees as bail immediately to the verification account I send you. Do not tell anyone about this and do not disconnect the call or the case will become serious.", "language": "en", "language_p": 1.0, "words": [{"w": "Hello,", "t0": 0.0, "t1": 0.44, "p": 0.92}, {"w": "this", "t0": 0.84, "t1": 1.04, "p": 0.79}, {"w": "is", "t0": 1.04, "t1": 1.3, "p": 0.99}, {"w": "Inspector", "t0": 1.3, "t1": 1.86, "p": 0.85}, {"w": "Rajeev", "t0": 1.86, "t1": 2.54, "p": 0.84}, {"w": "Rathard", "t0": 2.54, "t1": 2.96, "p": 0.56}, {"w": "from", "t0": 2.96, "t1": 3.28, "p": 0.94}, {"w": "the", "t0": 3.28, "t1": 3.44, "p": 0.76}, {"w": "Cybercrime", "t0": 3.44, "t1": 4.18, "p": 0.67}, {"w": "Cell.", "t0": 4.18, "t1": 4.46, "p": 0.92}, {"w": "Your", "t0": 5.26, "t1": 5.62, "p": 0.95}, {"w": "father", "t0": 5.62, "t1": 6.1, "p": 0.95}, {"w": "has", "t0": 6.1, "t1": 6.42, "p": 0.99}, {"w": "been", "t0": 6.42, "t1": 6.68, "p": 0.99}, {"w": "arrested", "t0": 6.68, "t1": 7.22, "p": 1.0}, {"w": "in", "t0": 7.22, "t1": 7.6, "p": 0.99}, {"w": "a", "t0": 7.6, "t1": 7.74, "p": 1.0}, {"w": "hit", "t0": 7.74, "t1": 7.98, "p": 0.96}, {"w": "and", "t0": 7.98, "t1": 8.36, "p": 0.82}, {"w": "run", "t0": 8.36, "t1": 8.56, "p": 0.96}, {"w": "case", "t0": 8.56, "t1": 8.92, "p": 0.98}, {"w": "and", "t0": 8.92, "t1": 9.58, "p": 0.87}, {"w": "is", "t0": 9.58, "t1": 9.76, "p": 0.96}, {"w": "in", "t0": 9.76, "t1": 9.94, "p": 1.0}, {"w": "our", "t0": 9.94, "t1": 10.1, "p": 0.9}, {"w": "custody.", "t0": 10.1, "t1": 10.54, "p": 1.0}, {"w": "To", "t0": 11.46, "t1": 11.68, "p": 1.0}, {"w": "avoid", "t0": 11.68, "t1": 12.04, "p": 1.0}, {"w": "an", "t0": 12.04, "t1": 12.32, "p": 0.97}, {"w": "FIR", "t0": 12.32, "t1": 12.68, "p": 0.95}, {"w": "and", "t0": 12.68, "t1": 13.22, "p": 0.96}, {"w": "Jail", "t0": …(truncated)
A76: 75 | B76: MRG-0540 | C76: video | D76: video_call.mp4 | E76: video/mp4 | F76: 1ce94473bc8a090da83b4e069c691cc73bc61cb5585747280ba7a959733d2391 | G76: 404969 | H76: 1c/1ce94473bc8a090da83b4e069c691cc73bc61cb5585747280ba7a959733d2391.mp4 | I76: 19.46 | J76: {"asr": {"text": "Hi, it's Rajesh from the CFO office. I'm in a board meeting and can't take calls. Please wire 12 .5 lakh rupees to the new vendor account before 4 pm today. It's urgent and confidential. Don't look in audit yet.", "language": "en", "language_p": 1.0, "words": [{"w": "Hi,", "t0": 0.0, "t1": 0.4, "p": 0.92}, {"w": "it's", "t0": 0.7, "t1": 1.16, "p": 0.73}, {"w": "Rajesh", "t0": 1.16, "t1": 1.54, "p": 0.94}, {"w": "from", "t0": 1.54, "t1": 1.8, "p": 0.99}, {"w": "the", "t0": 1.8, "t1": 1.98, "p": 0.97}, {"w": "CFO", "t0": 1.98, "t1": 2.4, "p": 0.89}, {"w": "office.", "t0": 2.4, "t1": 2.98, "p": 0.81}, {"w": "I'm", "t0": 3.7, "t1": 4.22, "p": 0.9}, {"w": "in", "t0": 4.22, "t1": 4.38, "p": 0.99}, {"w": "a", "t0": 4.38, "t1": 4.5, "p": 0.98}, {"w": "board", "t0": 4.5, "t1": 4.76, "p": 0.91}, {"w": "meeting", "t0": 4.76, "t1": 5.22, "p": 1.0}, {"w": "and", "t0": 5.22, "t1": 5.78, "p": 0.91}, {"w": "can't", "t0": 5.78, "t1": 6.16, "p": 0.96}, {"w": "take", "t0": 6.16, "t1": 6.42, "p": 1.0}, {"w": "calls.", "t0": 6.42, "t1": 6.9, "p": 1.0}, {"w": "Please", "t0": 7.74, "t1": 8.14, "p": 0.98}, {"w": "wire", "t0": 8.14, "t1": 8.5, "p": 0.96}, {"w": "12", "t0": 8.5, "t1": 9.04, "p": 0.95}, {"w": ".5", "t0": 9.04, "t1": 9.64, "p": 1.0}, {"w": "lakh", "t0": 9.64, "t1": 9.94, "p": 0.78}, {"w": "rupees", "t0": 9.94, "t1": 10.4, "p": 0.86}, {"w": "to", "t0": 10.4, "t1": 10.88, "p": 0.99}, {"w": "the", "t0": 10.88, "t1": 11.02, "p": 0.98}, {"w": "new", "t0": 11.02, "t1": 11.22, "p": 0.9}, {"w": "vendor", "t0": 11.22, "t1": 11.58, "p": 0.78}, {"w": "account", "t0": 11.58, "t1": 12.04, "p": 0.99}, {"w": "before", "t0": 12.04, "t1": 12.54, "p": 0.97}, {"w": "4", "t0": 12.54, "t1": 13.1, "p": 0.99}, {"w": "pm", "t0": 13.1, "t1": 13.36, "p": 0.36}, {"w": "today.", "t0": 13.36, "t1": 13.78, "p": 0.97}, {"w": "It's", "t0": 14.66, "t1": 15.0, "p": 0.85}, {"w": "urgent", "t0": 15.0, "t1": 15.34, "p": 0.99}, {"w": "and", "t0": 15.34, "t1": 15.76, "p": 0.99}, {"w": "confidentia …(truncated)
A77: 76 | B77: MRG-0541 | C77: audio | D77: real_human_voice.wav | E77: audio/wav | F77: 373ab8f0af93f82cfe405409e7781fa0bd0f224391e02b7f715b71d85e629762 | G77: 779404 | H77: 37/373ab8f0af93f82cfe405409e7781fa0bd0f224391e02b7f715b71d85e629762.wav | I77: 24.36 | J77: {"asr": {"text": "Mr. Quilter is the apostle of the middle classes, and we are glad to welcome his gospel. Nor is Mr. Quilter's manner less interesting than his matter. He tells us that at this festive season of the year, with Christmas and roast beef looming before us, similarly drawn from eating and its results occur most readily to the mind.", "language": "en", "language_p": 1.0, "words": [{"w": "Mr.", "t0": 0.18, "t1": 0.76, "p": 0.84}, {"w": "Quilter", "t0": 0.84, "t1": 1.16, "p": 0.85}, {"w": "is", "t0": 1.16, "t1": 1.38, "p": 0.99}, {"w": "the", "t0": 1.38, "t1": 1.54, "p": 0.99}, {"w": "apostle", "t0": 1.54, "t1": 1.92, "p": 0.82}, {"w": "of", "t0": 1.92, "t1": 2.22, "p": 0.99}, {"w": "the", "t0": 2.22, "t1": 2.36, "p": 0.99}, {"w": "middle", "t0": 2.36, "t1": 2.56, "p": 0.84}, {"w": "classes,", "t0": 2.56, "t1": 3.0, "p": 0.9}, {"w": "and", "t0": 3.36, "t1": 3.44, "p": 0.99}, {"w": "we", "t0": 3.44, "t1": 3.6, "p": 1.0}, {"w": "are", "t0": 3.6, "t1": 3.66, "p": 0.89}, {"w": "glad", "t0": 3.66, "t1": 3.94, "p": 1.0}, {"w": "to", "t0": 3.94, "t1": 4.22, "p": 0.99}, {"w": "welcome", "t0": 4.22, "t1": 4.48, "p": 1.0}, {"w": "his", "t0": 4.48, "t1": 4.8, "p": 0.97}, {"w": "gospel.", "t0": 4.8, "t1": 5.28, "p": 0.86}, {"w": "Nor", "t0": 6.68, "t1": 7.02, "p": 0.83}, {"w": "is", "t0": 7.02, "t1": 7.18, "p": 0.37}, {"w": "Mr.", "t0": 7.18, "t1": 7.56, "p": 0.99}, {"w": "Quilter's", "t0": 7.72, "t1": 8.12, "p": 0.99}, {"w": "manner", "t0": 8.12, "t1": 8.38, "p": 0.98}, {"w": "less", "t0": 8.38, "t1": 8.7, "p": 0.99}, {"w": "interesting", "t0": 8.7, "t1": 9.4, "p": 0.99}, {"w": "than", "t0": 9.4, "t1": 9.7, "p": 0.99}, {"w": "his", "t0": 9.7, "t1": 10.0, "p": 0.99}, {"w": "matter.", "t0": 10.0, "t1": 10.46, "p": 0.64}, {"w": "He", "t0": 11.7, "t1": 12.12, "p": 0.99}, {"w": "tells", "t0": 12.12, "t1": 12.38, "p": 1.0}, {"w": "us", "t0": 12.38, "t1": 12.64, "p": 1.0}, {"w": "that", "t0": 12.64, "t1": 12.96, "p": 0.98}, {"w": "at", "t0": 12.96, "t1": 13.2, "p": 0.81}, { …(truncated)
A78: 77 | B78: MRG-0542 | C78: audio | D78: call_recording.wav | E78: audio/wav | F78: bd01d50aec6f4ab723c83c783e4160e2b3f5af1360601aa489d4a3cb0c2aa126 | G78: 917036 | H78: bd/bd01d50aec6f4ab723c83c783e4160e2b3f5af1360601aa489d4a3cb0c2aa126.wav | I78: 28.66 | J78: {"asr": {"text": "Hello, this is Inspector Rajeev Rathard from the Cybercrime Cell. Your father has been arrested in a hit and run case and is in our custody. To avoid an FIR and Jail tonight, you must deposit 50 ,000 rupees as bail immediately to the verification account I send you. Do not tell anyone about this and do not disconnect the call or the case will become serious.", "language": "en", "language_p": 1.0, "words": [{"w": "Hello,", "t0": 0.0, "t1": 0.44, "p": 0.92}, {"w": "this", "t0": 0.84, "t1": 1.04, "p": 0.82}, {"w": "is", "t0": 1.04, "t1": 1.28, "p": 0.98}, {"w": "Inspector", "t0": 1.28, "t1": 1.86, "p": 0.86}, {"w": "Rajeev", "t0": 1.86, "t1": 2.54, "p": 0.85}, {"w": "Rathard", "t0": 2.54, "t1": 2.96, "p": 0.59}, {"w": "from", "t0": 2.96, "t1": 3.28, "p": 0.95}, {"w": "the", "t0": 3.28, "t1": 3.44, "p": 0.81}, {"w": "Cybercrime", "t0": 3.44, "t1": 4.18, "p": 0.69}, {"w": "Cell.", "t0": 4.18, "t1": 4.46, "p": 0.92}, {"w": "Your", "t0": 5.28, "t1": 5.64, "p": 0.96}, {"w": "father", "t0": 5.64, "t1": 6.1, "p": 0.95}, {"w": "has", "t0": 6.1, "t1": 6.42, "p": 1.0}, {"w": "been", "t0": 6.42, "t1": 6.68, "p": 0.99}, {"w": "arrested", "t0": 6.68, "t1": 7.22, "p": 1.0}, {"w": "in", "t0": 7.22, "t1": 7.6, "p": 0.99}, {"w": "a", "t0": 7.6, "t1": 7.74, "p": 1.0}, {"w": "hit", "t0": 7.74, "t1": 7.98, "p": 0.96}, {"w": "and", "t0": 7.98, "t1": 8.38, "p": 0.84}, {"w": "run", "t0": 8.38, "t1": 8.56, "p": 0.96}, {"w": "case", "t0": 8.56, "t1": 8.92, "p": 0.99}, {"w": "and", "t0": 8.92, "t1": 9.58, "p": 0.92}, {"w": "is", "t0": 9.58, "t1": 9.76, "p": 0.96}, {"w": "in", "t0": 9.76, "t1": 9.94, "p": 1.0}, {"w": "our", "t0": 9.94, "t1": 10.1, "p": 0.87}, {"w": "custody.", "t0": 10.1, "t1": 10.54, "p": 1.0}, {"w": "To", "t0": 11.46, "t1": 11.68, "p": 1.0}, {"w": "avoid", "t0": 11.68, "t1": 12.04, "p": 1.0}, {"w": "an", "t0": 12.04, "t1": 12.32, "p": 0.97}, {"w": "FIR", "t0": 12.32, "t1": 12.68, "p": 0.95}, {"w": "and", "t0": 12.68, "t1": 13.22, "p": 0.96}, {"w": "Jail", "t0 …(truncated)
A79: 78 | B79: MRG-0543 | C79: audio | D79: call_recording.wav | E79: audio/wav | F79: 230e53bb7ce9523ac0824131f11c5817666fd622719787a1b972e09ebdf8b881 | G79: 692012 | H79: 23/230e53bb7ce9523ac0824131f11c5817666fd622719787a1b972e09ebdf8b881.wav | I79: 21.62 | J79: {"asr": {"text": "Papa Rohan here. I had an accident and I am at the hospital. My phone broke so this is a friend's number. I need 75 ,000 rupees right now for the treatment. Please send it to this UPI quickly and don't tell anyone at home. I'll explain later.", "language": "en", "language_p": 1.0, "words": [{"w": "Papa", "t0": 0.0, "t1": 0.48, "p": 0.76}, {"w": "Rohan", "t0": 0.48, "t1": 1.14, "p": 0.94}, {"w": "here.", "t0": 1.14, "t1": 1.38, "p": 0.92}, {"w": "I", "t0": 2.26, "t1": 2.56, "p": 0.94}, {"w": "had", "t0": 2.56, "t1": 2.84, "p": 0.99}, {"w": "an", "t0": 2.84, "t1": 3.04, "p": 0.99}, {"w": "accident", "t0": 3.04, "t1": 3.5, "p": 1.0}, {"w": "and", "t0": 3.5, "t1": 3.94, "p": 0.92}, {"w": "I", "t0": 3.94, "t1": 4.14, "p": 0.96}, {"w": "am", "t0": 4.14, "t1": 4.28, "p": 0.68}, {"w": "at", "t0": 4.28, "t1": 4.52, "p": 0.99}, {"w": "the", "t0": 4.52, "t1": 4.72, "p": 0.95}, {"w": "hospital.", "t0": 4.72, "t1": 5.2, "p": 0.98}, {"w": "My", "t0": 5.84, "t1": 5.96, "p": 0.99}, {"w": "phone", "t0": 5.96, "t1": 6.3, "p": 1.0}, {"w": "broke", "t0": 6.3, "t1": 6.6, "p": 1.0}, {"w": "so", "t0": 6.6, "t1": 6.9, "p": 0.69}, {"w": "this", "t0": 6.9, "t1": 7.18, "p": 0.98}, {"w": "is", "t0": 7.18, "t1": 7.5, "p": 0.98}, {"w": "a", "t0": 7.5, "t1": 7.6, "p": 0.97}, {"w": "friend's", "t0": 7.6, "t1": 8.06, "p": 0.77}, {"w": "number.", "t0": 8.06, "t1": 8.34, "p": 0.98}, {"w": "I", "t0": 9.2, "t1": 9.54, "p": 0.99}, {"w": "need", "t0": 9.54, "t1": 9.8, "p": 1.0}, {"w": "75", "t0": 9.8, "t1": 10.56, "p": 0.91}, {"w": ",000", "t0": 10.56, "t1": 11.1, "p": 0.82}, {"w": "rupees", "t0": 11.1, "t1": 11.42, "p": 0.62}, {"w": "right", "t0": 11.42, "t1": 11.98, "p": 0.95}, {"w": "now", "t0": 11.98, "t1": 12.42, "p": 1.0}, {"w": "for", "t0": 12.42, "t1": 12.68, "p": 0.98}, {"w": "the", "t0": 12.68, "t1": 12.88, "p": 0.99}, {"w": "treatment.", "t0": 12.88, "t1": 13.28, "p": 1.0}, {"w": "Please", "t0": 14.24, "t1": 14.56, "p": 0.99}, {"w": "send", "t0": 14.56, "t1": 15.02, "p": 1.0} …(truncated)
A80: 79 | B80: MRG-0545 | C80: video | D80: video_call.mp4 | E80: video/mp4 | F80: 090feb5d9cc7eaf81f10a1726ad6875bd4339f3af4934b3538f5578db28ec900 | G80: 369568 | H80: 09/090feb5d9cc7eaf81f10a1726ad6875bd4339f3af4934b3538f5578db28ec900.mp4 | I80: 18.62 | J80: {"asr": {"text": "Hi, it's Rajesh from the CFO office. I'm in a board meeting and can't take calls. Please wire 20 lakh rupees to the new vendor account before 4pm today. It's urgent and confidential. Don't look in audit yet.", "language": "en", "language_p": 1.0, "words": [{"w": "Hi,", "t0": 0.0, "t1": 0.4, "p": 0.92}, {"w": "it's", "t0": 0.72, "t1": 1.16, "p": 0.81}, {"w": "Rajesh", "t0": 1.16, "t1": 1.54, "p": 0.96}, {"w": "from", "t0": 1.54, "t1": 1.8, "p": 0.99}, {"w": "the", "t0": 1.8, "t1": 1.98, "p": 0.98}, {"w": "CFO", "t0": 1.98, "t1": 2.4, "p": 0.89}, {"w": "office.", "t0": 2.4, "t1": 2.98, "p": 0.81}, {"w": "I'm", "t0": 3.7, "t1": 4.22, "p": 0.9}, {"w": "in", "t0": 4.22, "t1": 4.38, "p": 0.99}, {"w": "a", "t0": 4.38, "t1": 4.5, "p": 0.98}, {"w": "board", "t0": 4.5, "t1": 4.76, "p": 0.92}, {"w": "meeting", "t0": 4.76, "t1": 5.22, "p": 1.0}, {"w": "and", "t0": 5.22, "t1": 5.78, "p": 0.87}, {"w": "can't", "t0": 5.78, "t1": 6.16, "p": 0.96}, {"w": "take", "t0": 6.16, "t1": 6.42, "p": 1.0}, {"w": "calls.", "t0": 6.42, "t1": 6.88, "p": 1.0}, {"w": "Please", "t0": 7.74, "t1": 8.14, "p": 0.99}, {"w": "wire", "t0": 8.14, "t1": 8.5, "p": 0.93}, {"w": "20", "t0": 8.5, "t1": 8.96, "p": 0.83}, {"w": "lakh", "t0": 8.96, "t1": 9.2, "p": 0.64}, {"w": "rupees", "t0": 9.2, "t1": 9.64, "p": 0.91}, {"w": "to", "t0": 9.64, "t1": 9.98, "p": 0.99}, {"w": "the", "t0": 9.98, "t1": 10.12, "p": 0.98}, {"w": "new", "t0": 10.12, "t1": 10.34, "p": 0.88}, {"w": "vendor", "t0": 10.34, "t1": 10.68, "p": 0.76}, {"w": "account", "t0": 10.68, "t1": 11.16, "p": 0.98}, {"w": "before", "t0": 11.16, "t1": 11.68, "p": 0.98}, {"w": "4pm", "t0": 11.68, "t1": 12.48, "p": 0.64}, {"w": "today.", "t0": 12.48, "t1": 12.9, "p": 0.97}, {"w": "It's", "t0": 13.84, "t1": 14.16, "p": 0.85}, {"w": "urgent", "t0": 14.16, "t1": 14.48, "p": 0.99}, {"w": "and", "t0": 14.48, "t1": 14.9, "p": 1.0}, {"w": "confidential.", "t0": 14.9, "t1": 15.58, "p": 1.0}, {"w": "Don't", "t0": 16.1, "t1": 16.38, "p": 0.95}, {"w": …(truncated)
A81: 80 | B81: MRG-0546 | C81: audio | D81: call_recording.wav | E81: audio/wav | F81: 60bc97c5b412655fb2c3b5d68881e5109ff802c9e46b302c96dbfda977d9a958 | G81: 503084 | H81: 60/60bc97c5b412655fb2c3b5d68881e5109ff802c9e46b302c96dbfda977d9a958.wav | I81: 15.72 | J81: {"asr": {"text": "Congratulations, you are shortlisted for a remote job at 45 ,000 per month. Pay the refundable security deposit of 15 ,000 rupees today to receive your offer letter. Only a few seats are left.", "language": "en", "language_p": 1.0, "words": [{"w": "Congratulations,", "t0": 0.0, "t1": 0.88, "p": 0.94}, {"w": "you", "t0": 1.5, "t1": 1.7, "p": 0.98}, {"w": "are", "t0": 1.7, "t1": 1.82, "p": 0.97}, {"w": "shortlisted", "t0": 1.82, "t1": 2.42, "p": 0.93}, {"w": "for", "t0": 2.42, "t1": 2.7, "p": 1.0}, {"w": "a", "t0": 2.7, "t1": 2.84, "p": 0.99}, {"w": "remote", "t0": 2.84, "t1": 3.1, "p": 0.98}, {"w": "job", "t0": 3.1, "t1": 3.44, "p": 1.0}, {"w": "at", "t0": 3.44, "t1": 3.78, "p": 0.97}, {"w": "45", "t0": 3.78, "t1": 4.38, "p": 0.86}, {"w": ",000", "t0": 4.38, "t1": 4.98, "p": 0.9}, {"w": "per", "t0": 4.98, "t1": 5.14, "p": 0.92}, {"w": "month.", "t0": 5.14, "t1": 5.56, "p": 1.0}, {"w": "Pay", "t0": 6.3, "t1": 6.7, "p": 0.92}, {"w": "the", "t0": 6.7, "t1": 6.84, "p": 0.99}, {"w": "refundable", "t0": 6.84, "t1": 7.5, "p": 0.98}, {"w": "security", "t0": 7.5, "t1": 8.06, "p": 0.99}, {"w": "deposit", "t0": 8.06, "t1": 8.54, "p": 1.0}, {"w": "of", "t0": 8.54, "t1": 8.82, "p": 0.99}, {"w": "15", "t0": 8.82, "t1": 9.28, "p": 0.86}, {"w": ",000", "t0": 9.28, "t1": 9.78, "p": 0.99}, {"w": "rupees", "t0": 9.78, "t1": 10.04, "p": 0.82}, {"w": "today", "t0": 10.04, "t1": 10.46, "p": 0.92}, {"w": "to", "t0": 10.46, "t1": 10.66, "p": 0.99}, {"w": "receive", "t0": 10.66, "t1": 10.98, "p": 1.0}, {"w": "your", "t0": 10.98, "t1": 11.26, "p": 0.99}, {"w": "offer", "t0": 11.26, "t1": 11.56, "p": 0.99}, {"w": "letter.", "t0": 11.56, "t1": 11.98, "p": 0.99}, {"w": "Only", "t0": 12.92, "t1": 13.4, "p": 0.99}, {"w": "a", "t0": 13.4, "t1": 13.62, "p": 0.98}, {"w": "few", "t0": 13.62, "t1": 13.86, "p": 1.0}, {"w": "seats", "t0": 13.86, "t1": 14.18, "p": 0.97}, {"w": "are", "t0": 14.18, "t1": 14.46, "p": 0.99}, {"w": "left.", "t0": 14.46, "t1": 14.76, "p": 1.0}], "engine": "fas …(truncated)
A82: 81 | B82: MRG-0547 | C82: audio | D82: voice_note.wav | E82: audio/wav | F82: 417a58a03346779a5608e8287b571dfc8e2805fd4e3c3d084193f1e7f7f91faa | G82: 361004 | H82: 41/417a58a03346779a5608e8287b571dfc8e2805fd4e3c3d084193f1e7f7f91faa.wav | I82: 11.28 | J82: {"asr": {"text": "Hi everyone, a quick reminder, the quarterly town hall moves to Friday at 4pm the agenda is in your calendar invite. See you there!", "language": "en", "language_p": 1.0, "words": [{"w": "Hi", "t0": 0.0, "t1": 0.38, "p": 0.9}, {"w": "everyone,", "t0": 0.38, "t1": 0.94, "p": 0.84}, {"w": "a", "t0": 1.36, "t1": 1.5, "p": 0.77}, {"w": "quick", "t0": 1.5, "t1": 1.74, "p": 0.94}, {"w": "reminder,", "t0": 1.74, "t1": 2.28, "p": 0.99}, {"w": "the", "t0": 2.72, "t1": 2.9, "p": 0.84}, {"w": "quarterly", "t0": 2.9, "t1": 3.34, "p": 0.74}, {"w": "town", "t0": 3.34, "t1": 3.68, "p": 0.76}, {"w": "hall", "t0": 3.68, "t1": 3.92, "p": 0.94}, {"w": "moves", "t0": 3.92, "t1": 4.26, "p": 0.96}, {"w": "to", "t0": 4.26, "t1": 4.56, "p": 0.99}, {"w": "Friday", "t0": 4.56, "t1": 4.9, "p": 0.96}, {"w": "at", "t0": 4.9, "t1": 5.34, "p": 0.97}, {"w": "4pm", "t0": 5.34, "t1": 6.04, "p": 0.66}, {"w": "the", "t0": 6.04, "t1": 6.3, "p": 0.65}, {"w": "agenda", "t0": 6.3, "t1": 6.72, "p": 0.96}, {"w": "is", "t0": 6.72, "t1": 7.1, "p": 0.97}, {"w": "in", "t0": 7.1, "t1": 7.28, "p": 1.0}, {"w": "your", "t0": 7.28, "t1": 7.5, "p": 0.99}, {"w": "calendar", "t0": 7.5, "t1": 7.96, "p": 0.98}, {"w": "invite.", "t0": 7.96, "t1": 8.56, "p": 0.82}, {"w": "See", "t0": 9.5, "t1": 9.82, "p": 0.99}, {"w": "you", "t0": 9.82, "t1": 10.04, "p": 0.98}, {"w": "there!", "t0": 10.04, "t1": 10.28, "p": 0.99}], "engine": "faster-whisper/base"}}
A83: 82 | B83: MRG-0548 | C83: audio | D83: call_recording.wav | E83: audio/wav | F83: fcaf7b2c06868b15a6121f5a4d463df8da24801e8dbdd7316379c23212b77b49 | G83: 791084 | H83: fc/fcaf7b2c06868b15a6121f5a4d463df8da24801e8dbdd7316379c23212b77b49.wav | I83: 24.72 | J83: {"asr": {"text": "This is Inspector Rajiv Rathard from the CBI Cyber Cell. A parcel in your name with illegal drugs was seized at Mumbai Customs. You are under digital arrest. Stay on this call, do not tell your family and transfer 50 ,000 rupees to the RBI verification account within 1R to clear your name.", "language": "en", "language_p": 1.0, "words": [{"w": "This", "t0": 0.0, "t1": 0.38, "p": 0.93}, {"w": "is", "t0": 0.38, "t1": 0.62, "p": 1.0}, {"w": "Inspector", "t0": 0.62, "t1": 1.3, "p": 0.9}, {"w": "Rajiv", "t0": 1.3, "t1": 1.96, "p": 0.82}, {"w": "Rathard", "t0": 1.96, "t1": 2.4, "p": 0.59}, {"w": "from", "t0": 2.4, "t1": 2.72, "p": 0.97}, {"w": "the", "t0": 2.72, "t1": 2.88, "p": 0.97}, {"w": "CBI", "t0": 2.88, "t1": 3.38, "p": 0.78}, {"w": "Cyber", "t0": 3.38, "t1": 3.92, "p": 0.86}, {"w": "Cell.", "t0": 3.92, "t1": 4.16, "p": 0.38}, {"w": "A", "t0": 5.0, "t1": 5.26, "p": 0.72}, {"w": "parcel", "t0": 5.26, "t1": 5.6, "p": 0.93}, {"w": "in", "t0": 5.6, "t1": 5.98, "p": 0.98}, {"w": "your", "t0": 5.98, "t1": 6.18, "p": 0.99}, {"w": "name", "t0": 6.18, "t1": 6.52, "p": 0.98}, {"w": "with", "t0": 6.52, "t1": 6.94, "p": 0.94}, {"w": "illegal", "t0": 6.94, "t1": 7.32, "p": 0.95}, {"w": "drugs", "t0": 7.32, "t1": 7.82, "p": 1.0}, {"w": "was", "t0": 7.82, "t1": 8.38, "p": 0.91}, {"w": "seized", "t0": 8.38, "t1": 8.88, "p": 0.97}, {"w": "at", "t0": 8.88, "t1": 9.24, "p": 0.99}, {"w": "Mumbai", "t0": 9.24, "t1": 9.52, "p": 0.99}, {"w": "Customs.", "t0": 9.52, "t1": 10.88, "p": 0.86}, {"w": "You", "t0": 11.0, "t1": 11.26, "p": 0.97}, {"w": "are", "t0": 11.26, "t1": 11.48, "p": 0.99}, {"w": "under", "t0": 11.48, "t1": 11.86, "p": 0.97}, {"w": "digital", "t0": 11.86, "t1": 12.34, "p": 0.48}, {"w": "arrest.", "t0": 12.34, "t1": 12.76, "p": 0.99}, {"w": "Stay", "t0": 13.88, "t1": 14.02, "p": 0.96}, {"w": "on", "t0": 14.02, "t1": 14.3, "p": 1.0}, {"w": "this", "t0": 14.3, "t1": 14.52, "p": 0.98}, {"w": "call,", "t0": 14.52, "t1": 14.88, "p": 0.99}, {"w": "do", "t0": 15. …(truncated)
A84: 83 | B84: MRG-0549 | C84: audio | D84: call_recording.wav | E84: audio/wav | F84: 11b3a9ed8864206557c26e306ac06152c27b674200f9ffbbf25a6f6885203d6c | G84: 400172 | H84: 11/11b3a9ed8864206557c26e306ac06152c27b674200f9ffbbf25a6f6885203d6c.wav | I84: 12.5 | J84: {"asr": {"text": "Priya Grahag, I am speaking with the bank. Your food will be closed today. But where OTP is now, which is on your phone.", "language": "hi-Latn (Hinglish)", "language_p": 1.0, "words": [{"w": "Priya", "t0": 0.14, "t1": 0.58, "p": 0.68}, {"w": "Grahag,", "t0": 0.58, "t1": 1.06, "p": 0.36}, {"w": "I", "t0": 1.5, "t1": 1.6, "p": 0.92}, {"w": "am", "t0": 1.6, "t1": 2.24, "p": 0.87}, {"w": "speaking", "t0": 2.24, "t1": 2.72, "p": 0.6}, {"w": "with", "t0": 2.72, "t1": 2.72, "p": 0.43}, {"w": "the", "t0": 2.72, "t1": 2.72, "p": 0.67}, {"w": "bank.", "t0": 2.72, "t1": 2.72, "p": 0.94}, {"w": "Your", "t0": 3.94, "t1": 4.82, "p": 0.92}, {"w": "food", "t0": 4.82, "t1": 5.2, "p": 0.22}, {"w": "will", "t0": 5.2, "t1": 5.68, "p": 0.85}, {"w": "be", "t0": 5.68, "t1": 5.68, "p": 0.75}, {"w": "closed", "t0": 5.68, "t1": 5.96, "p": 0.48}, {"w": "today.", "t0": 5.96, "t1": 6.38, "p": 0.82}, {"w": "But", "t0": 7.42, "t1": 7.92, "p": 0.23}, {"w": "where", "t0": 7.92, "t1": 8.28, "p": 0.11}, {"w": "OTP", "t0": 8.28, "t1": 8.68, "p": 0.71}, {"w": "is", "t0": 8.68, "t1": 9.16, "p": 0.23}, {"w": "now,", "t0": 9.16, "t1": 9.24, "p": 0.04}, {"w": "which", "t0": 9.24, "t1": 9.6, "p": 0.27}, {"w": "is", "t0": 9.6, "t1": 10.04, "p": 0.65}, {"w": "on", "t0": 10.04, "t1": 10.04, "p": 0.28}, {"w": "your", "t0": 10.04, "t1": 10.46, "p": 0.91}, {"w": "phone.", "t0": 10.46, "t1": 10.84, "p": 0.92}], "engine": "faster-whisper/base"}}
A85: 84 | B85: MRG-0550 | C85: image | D85: 01_ai_police_officer_portrait.jpg | E85: image/jpeg | F85: aa79ba2d41deb0db87a1585bee216ba280462e38f6031f691163da18f97ab5a0 | G85: 67649 | H85: aa/aa79ba2d41deb0db87a1585bee216ba280462e38f6031f691163da18f97ab5a0.jpg | J85: {"ocr": {"text": "MIRAGE RED TEAM\u00b7SYNTHETIC", "lines": [{"text": "MIRAGE RED TEAM\u00b7SYNTHETIC", "conf": 0.98, "box": [0.6895, 0.9688, 0.3008, 0.0273]}], "engine": "rapidocr"}}
A86: 85 | B86: MRG-0551 | C86: image | D86: 04_real_photo_astronaut_nasa.jpg | E86: image/jpeg | F86: 370adb9cb9dd03ca911ea316fb227495e01095398bc1f71188a3995209b9c81a | G86: 74962 | H86: 37/370adb9cb9dd03ca911ea316fb227495e01095398bc1f71188a3995209b9c81a.jpg | J86: {}
A87: 86 | B87: MRG-0552 | C87: audio | D87: call_recording.wav | E87: audio/wav | F87: b7d0f0c2525a53002f9c46a6ce4dbdb20ead1e497f2bdb1c2945d94abc52e4dc | G87: 917036 | H87: b7/b7d0f0c2525a53002f9c46a6ce4dbdb20ead1e497f2bdb1c2945d94abc52e4dc.wav | I87: 28.66 | J87: {"asr": {"text": "Hello, this is Inspector Rajeev Rathard from the Cybercrime Cell. Your father has been arrested in a hit and run case and is in our custody. To avoid an FIR and Jail tonight, you must deposit 50 ,000 rupees as bail immediately to the verification account I send you. Do not tell anyone about this and do not disconnect the call or the case will become series.", "language": "en", "language_p": 1.0, "words": [{"w": "Hello,", "t0": 0.0, "t1": 0.44, "p": 0.9}, {"w": "this", "t0": 0.84, "t1": 1.04, "p": 0.8}, {"w": "is", "t0": 1.04, "t1": 1.3, "p": 0.99}, {"w": "Inspector", "t0": 1.3, "t1": 1.86, "p": 0.86}, {"w": "Rajeev", "t0": 1.86, "t1": 2.54, "p": 0.82}, {"w": "Rathard", "t0": 2.54, "t1": 2.96, "p": 0.58}, {"w": "from", "t0": 2.96, "t1": 3.28, "p": 0.95}, {"w": "the", "t0": 3.28, "t1": 3.44, "p": 0.84}, {"w": "Cybercrime", "t0": 3.44, "t1": 4.18, "p": 0.67}, {"w": "Cell.", "t0": 4.18, "t1": 4.46, "p": 0.92}, {"w": "Your", "t0": 5.24, "t1": 5.64, "p": 0.95}, {"w": "father", "t0": 5.64, "t1": 6.1, "p": 0.95}, {"w": "has", "t0": 6.1, "t1": 6.42, "p": 0.99}, {"w": "been", "t0": 6.42, "t1": 6.68, "p": 0.99}, {"w": "arrested", "t0": 6.68, "t1": 7.22, "p": 1.0}, {"w": "in", "t0": 7.22, "t1": 7.6, "p": 0.99}, {"w": "a", "t0": 7.6, "t1": 7.74, "p": 1.0}, {"w": "hit", "t0": 7.74, "t1": 7.98, "p": 0.96}, {"w": "and", "t0": 7.98, "t1": 8.38, "p": 0.79}, {"w": "run", "t0": 8.38, "t1": 8.56, "p": 0.96}, {"w": "case", "t0": 8.56, "t1": 8.92, "p": 0.98}, {"w": "and", "t0": 8.92, "t1": 9.58, "p": 0.87}, {"w": "is", "t0": 9.58, "t1": 9.78, "p": 0.97}, {"w": "in", "t0": 9.78, "t1": 9.94, "p": 1.0}, {"w": "our", "t0": 9.94, "t1": 10.1, "p": 0.89}, {"w": "custody.", "t0": 10.1, "t1": 10.54, "p": 1.0}, {"w": "To", "t0": 11.46, "t1": 11.68, "p": 1.0}, {"w": "avoid", "t0": 11.68, "t1": 12.04, "p": 1.0}, {"w": "an", "t0": 12.04, "t1": 12.32, "p": 0.97}, {"w": "FIR", "t0": 12.32, "t1": 12.68, "p": 0.95}, {"w": "and", "t0": 12.68, "t1": 13.22, "p": 0.95}, {"w": "Jail", "t0": 1 …(truncated)
A88: 87 | B88: MRG-0553 | C88: audio | D88: cfo_voice_note.wav | E88: audio/wav | F88: 0c6356b156fe3da29f708117352f28de11c438d0cdb8244ab289e7c8728114d2 | G88: 530346 | H88: 0c/0c6356b156fe3da29f708117352f28de11c438d0cdb8244ab289e7c8728114d2.wav | I88: 16.57 | J88: {"asr": {"text": "Hi, it's Rajesh. I'm in a board meeting and can't take calls. Please process 48 .50 ,000 rupees to the new vendor account before 4PM very urgent. Keep this between us, AuditWale .co .ubi Matt Batina", "language": "en", "language_p": 1.0, "words": [{"w": "Hi,", "t0": 0.0, "t1": 0.34, "p": 0.77}, {"w": "it's", "t0": 0.68, "t1": 1.02, "p": 0.81}, {"w": "Rajesh.", "t0": 1.02, "t1": 1.34, "p": 0.87}, {"w": "I'm", "t0": 2.26, "t1": 2.64, "p": 0.98}, {"w": "in", "t0": 2.64, "t1": 2.68, "p": 0.98}, {"w": "a", "t0": 2.68, "t1": 2.78, "p": 0.92}, {"w": "board", "t0": 2.78, "t1": 2.98, "p": 0.91}, {"w": "meeting", "t0": 2.98, "t1": 3.3, "p": 1.0}, {"w": "and", "t0": 3.3, "t1": 3.56, "p": 1.0}, {"w": "can't", "t0": 3.56, "t1": 3.92, "p": 0.97}, {"w": "take", "t0": 3.92, "t1": 4.06, "p": 1.0}, {"w": "calls.", "t0": 4.06, "t1": 4.54, "p": 1.0}, {"w": "Please", "t0": 5.58, "t1": 5.8, "p": 0.96}, {"w": "process", "t0": 5.8, "t1": 6.28, "p": 0.96}, {"w": "48", "t0": 6.28, "t1": 6.84, "p": 0.98}, {"w": ".50", "t0": 6.84, "t1": 7.54, "p": 0.54}, {"w": ",000", "t0": 7.54, "t1": 8.08, "p": 0.71}, {"w": "rupees", "t0": 8.08, "t1": 8.42, "p": 0.81}, {"w": "to", "t0": 8.42, "t1": 8.7, "p": 1.0}, {"w": "the", "t0": 8.7, "t1": 8.82, "p": 0.99}, {"w": "new", "t0": 8.82, "t1": 8.98, "p": 0.8}, {"w": "vendor", "t0": 8.98, "t1": 9.24, "p": 0.92}, {"w": "account", "t0": 9.24, "t1": 9.6, "p": 1.0}, {"w": "before", "t0": 9.6, "t1": 9.96, "p": 0.99}, {"w": "4PM", "t0": 9.96, "t1": 10.68, "p": 0.64}, {"w": "very", "t0": 10.68, "t1": 11.1, "p": 0.62}, {"w": "urgent.", "t0": 11.1, "t1": 11.46, "p": 1.0}, {"w": "Keep", "t0": 12.28, "t1": 12.66, "p": 0.98}, {"w": "this", "t0": 12.66, "t1": 12.88, "p": 0.99}, {"w": "between", "t0": 12.88, "t1": 13.24, "p": 0.99}, {"w": "us,", "t0": 13.24, "t1": 13.54, "p": 1.0}, {"w": "AuditWale", "t0": 14.0, "t1": 14.46, "p": 0.57}, {"w": ".co", "t0": 14.46, "t1": 14.8, "p": 0.34}, {"w": ".ubi", "t0": 14.8, "t1": 15.1, "p": 0.33}, {"w": "Matt", "t0": 15 …(truncated)

Sheet DB audit_log
A1: id | B1: case_id | C1: actor | D1: action | E1: payload_hash | F1: prev_hash | G1: this_hash | H1: ts
A2: 1 | B2: MRG-0412 | C2: analyst | D2: case.created | E2: 36ca9efde112ba8425d02c168c9385009c4f646e90e23505877d0c20d578f648 | F2: 0000000000000000000000000000000000000000000000000000000000000000 | G2: 1c33b76f31e9639444676ce76b77db53fd6f37faa172e15ec25b2487981fe1e8 | H2: 2026-10-31 14:52:57.635922
A3: 2 | B3: MRG-0413 | C3: employee | D3: case.created | E3: 040644a78b7efc692eb14c2d9db21081268d0ca93bf1c8da80c3ab74e42aa12f | F3: 1c33b76f31e9639444676ce76b77db53fd6f37faa172e15ec25b2487981fe1e8 | G3: 4bdf9519350fcd693862a52cd84ab2b06bb1011fe5ecb0d603e3c532b69886f8 | H3: 2026-10-31 14:52:57.649968
A4: 3 | B4: MRG-0414 | C4: employee | D4: case.created | E4: 9aafa1300dc316300397e555842cc0c38bd40b989a44f1b8e38462bb4d70ef4b | F4: 4bdf9519350fcd693862a52cd84ab2b06bb1011fe5ecb0d603e3c532b69886f8 | G4: 66a96f557b4c9a2b73a4ba858add4b72a8124081a59dcce40c3a0b3cc9f05777 | H4: 2026-10-31 14:52:57.660480
A5: 4 | B5: MRG-0415 | C5: analyst | D5: case.created | E5: 903c10a30295a68d19998b109273603ea570ae354fa7862aeec7527259aa8a0c | F5: 66a96f557b4c9a2b73a4ba858add4b72a8124081a59dcce40c3a0b3cc9f05777 | G5: 1821d4b36326b46247db927e01634502a7843ab69b7ce805d2e0345769880fca | H5: 2026-10-31 14:52:57.671187
A6: 5 | B6: MRG-0416 | C6: analyst | D6: case.created | E6: 82d652e4b524b31a8bc90bfdbb8a574d6858d4a3470be2dc95588253df5e534e | F6: 1821d4b36326b46247db927e01634502a7843ab69b7ce805d2e0345769880fca | G6: c47ac8ce646e7a64c4f1f43c5054ce7cb84170c2ab7adcfa5c27157c9f8ee996 | H6: 2026-10-31 14:52:57.682233
A7: 6 | B7: MRG-0417 | C7: employee | D7: case.created | E7: 6c7023b69c7ee67ad54e976e068af401a7c01eb43e965442825e17eba9142d5b | F7: c47ac8ce646e7a64c4f1f43c5054ce7cb84170c2ab7adcfa5c27157c9f8ee996 | G7: 86136434ee6d6c6674d9401a52334a2dd69798fd490c2592d5c41127ab4629ff | H7: 2026-10-31 14:52:57.691758
A8: 7 | B8: MRG-0418 | C8: employee | D8: case.created | E8: 8824c5cd166cfc7463fb5fb44816b19a2a5bb4ccae90eb7f6f7ed0a6d500ee6b | F8: 86136434ee6d6c6674d9401a52334a2dd69798fd490c2592d5c41127ab4629ff | G8: 32d04b934bb37f55779b96bc1b5db6a7867d11019fc87d973b5a97bd49c583da | H8: 2026-10-31 14:52:57.702277
A9: 8 | B9: MRG-0419 | C9: employee | D9: case.created | E9: a0ff113571a7e3973331141e71386b7e11ef6912aa52a6ba65c238e7945a92bb | F9: 32d04b934bb37f55779b96bc1b5db6a7867d11019fc87d973b5a97bd49c583da | G9: 5e3415781ede06116a7139fa09f76f40f09fb0b55bc6d28913a6f19e07481220 | H9: 2026-10-31 14:52:57.711418
A10: 9 | B10: MRG-0420 | C10: employee | D10: case.created | E10: 3042d47b3fedf5d984accc3fe00eb8bbe865e003a0af9096541642430e9eef84 | F10: 5e3415781ede06116a7139fa09f76f40f09fb0b55bc6d28913a6f19e07481220 | G10: 0fa788bfd31870e87691d7265f2fecc1dc13476ba5f7c639ead399ba85dd82bb | H10: 2026-10-31 14:52:57.728528
A11: 10 | B11: MRG-0421 | C11: employee | D11: case.created | E11: 1b4b0d543c2309da28457c5f2431662c7fe5ea4074ea70630a5123ab9f6ffce6 | F11: 0fa788bfd31870e87691d7265f2fecc1dc13476ba5f7c639ead399ba85dd82bb | G11: 1b9be8b34464e8696aa48363ba2494d6e9f33d070f8b7c668f4d0339bd47b369 | H11: 2026-10-31 14:52:57.738563
A12: 11 | B12: MRG-0422 | C12: employee | D12: case.created | E12: d01cb68450ebd275dbfecba85e5328b8e807687ad71f813ea83aafccdfabb194 | F12: 1b9be8b34464e8696aa48363ba2494d6e9f33d070f8b7c668f4d0339bd47b369 | G12: f3c07e4a534e6bee9f15fa7f0c3df963fd313f4de649812d1f1bbb2a8537539d | H12: 2026-10-31 14:52:57.748596
A13: 12 | B13: MRG-0423 | C13: analyst | D13: case.created | E13: 07626ffacd5f6d4709a9b461fee270681bd0e8f4edc894f56efa29456087e703 | F13: f3c07e4a534e6bee9f15fa7f0c3df963fd313f4de649812d1f1bbb2a8537539d | G13: 0bb4f6b0e36790906cf164bb9e6b7b1aa93690a43e4d69dfcb717d214e6af9db | H13: 2026-10-31 14:52:57.757108
... A107: 106 | B107: MRG-0464 | C107: system | D107: verdict.issued | E107: 26d2e76b020f3c2dd73b48b38223fdaea2f89670fe58746437b14ffb238af3ab | F107: 01b19ae9adbdd9c58f7b06f7549656d9ff5090c636b22db0c313d7518e8e31ec | G107: 3c5266dc9b7400d14424fd357842b74840b617e33f27b99f3e34f4db2f097ead | H107: 2026-10-31 14:53:51.741112
A108: 107 | C108: analyst | D108: auth.login | E108: f7a69667982ec6fcc30c42ad86e5b0bc5d5a2cea81a6623ef0fa90ffe5f6739b | F108: 3c5266dc9b7400d14424fd357842b74840b617e33f27b99f3e34f4db2f097ead | G108: 1e37b54e5bad5af1c84d17ce4cf33bb72e13f211f960f2c7487edaf5cecf8a1e | H108: 2026-10-31 14:54:46.348351
A109: 108 | C109: analyst | D109: auth.login | E109: f7a69667982ec6fcc30c42ad86e5b0bc5d5a2cea81a6623ef0fa90ffe5f6739b | F109: 1e37b54e5bad5af1c84d17ce4cf33bb72e13f211f960f2c7487edaf5cecf8a1e | G109: 908e15090f8e575c1d81970b0b4fa5949e36135feb0a0d2de97c9c1656fbad8b | H109: 2026-10-31 14:55:04.117825
A110: 109 | B110: MRG-0465 | C110: analyst | D110: case.created | E110: 0bd3b0744a399344f2654e8ca9a771fbbb31582a69f7c6dad14a3c5cd5ce4cf5 | F110: 908e15090f8e575c1d81970b0b4fa5949e36135feb0a0d2de97c9c1656fbad8b | G110: 3ebc2e80ad3985c91f431813bfdc2a376860e4bbe3cc04b258647d86f0fdba98 | H110: 2026-10-31 14:55:57.609318
A111: 110 | B111: MRG-0465 | C111: system | D111: verdict.issued | E111: f633c7db5b951fbdf60558de048c2b176d260f78a15f80ea7e789ffa2068074c | F111: 3ebc2e80ad3985c91f431813bfdc2a376860e4bbe3cc04b258647d86f0fdba98 | G111: 819ac7c7181ab78a09ac4ea6a16e4ffef7225a59d8975e183de5c60d7819fe93 | H111: 2026-10-31 14:56:11.088146
A112: 111 | C112: analyst | D112: auth.login | E112: f7a69667982ec6fcc30c42ad86e5b0bc5d5a2cea81a6623ef0fa90ffe5f6739b | F112: 819ac7c7181ab78a09ac4ea6a16e4ffef7225a59d8975e183de5c60d7819fe93 | G112: 6db19e00d168f90ee03419be039f1e3a1b0f04b4d9363ca5967da843a14f6313 | H112: 2026-10-31 16:41:56.334049
A113: 112 | B113: MRG-0466 | C113: analyst | D113: case.created | E113: 59dd4f792f9dd65aac9b83d4427867d0f4aa6460bd303d59450296660b2ba6e2 | F113: 6db19e00d168f90ee03419be039f1e3a1b0f04b4d9363ca5967da843a14f6313 | G113: a00ccf63bb57332c6b789342ba2e7f8cc4c0c82a7553d06026a5cbbfaafa09c4 | H113: 2026-10-31 16:41:56.633646
A114: 113 | B114: MRG-0466 | C114: system | D114: verdict.issued | E114: f633c7db5b951fbdf60558de048c2b176d260f78a15f80ea7e789ffa2068074c | F114: a00ccf63bb57332c6b789342ba2e7f8cc4c0c82a7553d06026a5cbbfaafa09c4 | G114: 0d234154166e6d4114906cb0a864761cd38e1c3a1af2853dc75f77f3672abfc4 | H114: 2026-10-31 16:42:10.685807
A115: 114 | B115: MRG-0467 | C115: analyst | D115: case.created | E115: e131474e5e942e1e7959105490577386bd2b329385cdfb6c47869dfe9b501120 | F115: 0d234154166e6d4114906cb0a864761cd38e1c3a1af2853dc75f77f3672abfc4 | G115: b7900990dd9561c974be62e0b284118ca9cd793784daaf78a74a0b37187510d6 | H115: 2026-10-31 16:42:11.327208
A116: 115 | B116: MRG-0467 | C116: system | D116: verdict.issued | E116: 55dd235284d68412a38f96870a951b89de455922d40505b3f5236614908c99a7 | F116: b7900990dd9561c974be62e0b284118ca9cd793784daaf78a74a0b37187510d6 | G116: dd523ebd6db74b7350b642d30eda0b266e55a429c7031224c1c2aa23e13f1cbd | H116: 2026-10-31 16:42:31.015565
A117: 116 | B117: MRG-0468 | C117: analyst | D117: case.created | E117: 7a3c881572c05b51dff479742ac1e7dc863a8fd7967b5dd3fd2bc2aaf5e6621b | F117: dd523ebd6db74b7350b642d30eda0b266e55a429c7031224c1c2aa23e13f1cbd | G117: eee003127807e8acb9ada12de0008602c5e1a2b4ac0ab538e7b1715cf0739f97 | H117: 2026-10-31 16:42:31.775477
A118: 117 | B118: MRG-0468 | C118: system | D118: verdict.issued | E118: 416856881b9f73142d484dffd3271cac14163e7f227dd086c0d2eb254367f9d2 | F118: eee003127807e8acb9ada12de0008602c5e1a2b4ac0ab538e7b1715cf0739f97 | G118: 9d77bba9167b633c516f10b36730a815d665202f39e8103486bd1e6a01aad277 | H118: 2026-10-31 16:42:42.205611
A119: 118 | B119: MRG-0469 | C119: analyst | D119: case.created | E119: a272fe2f20a4fd8440550ce34e5e4b85828880b4338bc9a845bc9328d8be9ea2 | F119: 9d77bba9167b633c516f10b36730a815d665202f39e8103486bd1e6a01aad277 | G119: 2ac52d2b06af929bd7c2f690b97f4954cdfc88ad82fccb547b5ef4600d7fd262 | H119: 2026-10-31 16:42:43.020751
A120: 119 | B120: MRG-0469 | C120: system | D120: verdict.issued | E120: 18143e6fed7ea2ced47b9e785b56b08519b1d118b31e10e0aeced938fdeea145 | F120: 2ac52d2b06af929bd7c2f690b97f4954cdfc88ad82fccb547b5ef4600d7fd262 | G120: 285ecf49effd52476eaa286480ab81efb4c3d54d3fa87ff4cb71ed61311bd37f | H120: 2026-10-31 16:42:51.035858
A121: 120 | B121: MRG-0470 | C121: analyst | D121: case.created | E121: 53d396bac26bdcb08de2e099c548a5726d5de14981c6c53886b5a2f3ef8bc530 | F121: 285ecf49effd52476eaa286480ab81efb4c3d54d3fa87ff4cb71ed61311bd37f | G121: b2a1a5a87cad1cf53364f3e1d5ccd65e3578725ed90bed005aedc20ab8d456f3 | H121: 2026-10-31 16:42:51.272303
A122: 121 | B122: MRG-0470 | C122: system | D122: verdict.issued | E122: 6e3203ef55e84bf9e81967f259526d311732616d50847b0dce9a29b866d55133 | F122: b2a1a5a87cad1cf53364f3e1d5ccd65e3578725ed90bed005aedc20ab8d456f3 | G122: e5c290e6f6407c21ad6008ea59ff052eb41027892315ade37d1535b4b3635960 | H122: 2026-10-31 16:43:00.323575
A123: 122 | B123: MRG-0471 | C123: analyst | D123: case.created | E123: 708cb0ada2deb872024bf7664e914e8611974654e3d532fa1649808f278f6432 | F123: e5c290e6f6407c21ad6008ea59ff052eb41027892315ade37d1535b4b3635960 | G123: 462c61f8d8be8bdbc1681b6aca3caf3b471d094e6cb5edec35805831571d4a95 | H123: 2026-10-31 16:43:00.547932
A124: 123 | B124: MRG-0471 | C124: system | D124: verdict.issued | E124: f633c7db5b951fbdf60558de048c2b176d260f78a15f80ea7e789ffa2068074c | F124: 462c61f8d8be8bdbc1681b6aca3caf3b471d094e6cb5edec35805831571d4a95 | G124: 46fcc74e6fdb0a2a1e6c7e0e3255d84b16da657a1a20faf266b93a63108f122f | H124: 2026-10-31 16:43:11.289445
... A130: 129 | B130: MRG-0474 | C130: system | D130: verdict.issued | E130: 902976612d721c595deedb83c5fa546ce28c3fcef073d01e52a69320e582c238 | F130: 1b2137383d4b02955a1b27fa9c655902148fc2e2fdbdb5e6021dc70f43ae2d98 | G130: 83f19135a60cef956d9647826ffa9a79d5a48b2aeb53d1dfeacc5a3ca72ad9c7 | H130: 2026-10-31 16:43:23.809381
A131: 130 | C131: analyst | D131: auth.login | E131: f7a69667982ec6fcc30c42ad86e5b0bc5d5a2cea81a6623ef0fa90ffe5f6739b | F131: 83f19135a60cef956d9647826ffa9a79d5a48b2aeb53d1dfeacc5a3ca72ad9c7 | G131: ea088b9f4be707f2aa470c0b7f938081bbb094c86861fac17229bb129dbec734 | H131: 2026-10-31 16:43:35.826236
A132: 131 | C132: analyst | D132: auth.login | E132: f7a69667982ec6fcc30c42ad86e5b0bc5d5a2cea81a6623ef0fa90ffe5f6739b | F132: ea088b9f4be707f2aa470c0b7f938081bbb094c86861fac17229bb129dbec734 | G132: a18dd20a26222b86db8a8f02f918a3056f9b9e24b87246584e06e23f4fc8cd8d | H132: 2026-10-31 16:56:35.498036
A133: 132 | C133: analyst | D133: redteam.generated | E133: d03238eb080d0c1236913b5469dff21788351c065a40eaeecfae4b105cd081b9 | F133: a18dd20a26222b86db8a8f02f918a3056f9b9e24b87246584e06e23f4fc8cd8d | G133: 606ca7834adfdac03421984d31f77fcc9ecbecc55f1a19d4b7b8f2213f949c4b | H133: 2026-10-31 16:56:49.787600
A134: 133 | C134: analyst | D134: auth.login | E134: f7a69667982ec6fcc30c42ad86e5b0bc5d5a2cea81a6623ef0fa90ffe5f6739b | F134: 606ca7834adfdac03421984d31f77fcc9ecbecc55f1a19d4b7b8f2213f949c4b | G134: 44ae87595104ae20e4ac2c3de91a615b55212fba35707dd30da3efd296807722 | H134: 2026-10-31 16:57:14.241846
A135: 134 | C135: analyst | D135: redteam.campaign | E135: 3cc877d99811710274c527866cdc6fec3a893c3b05fc5c3a0331856329894f73 | F135: 44ae87595104ae20e4ac2c3de91a615b55212fba35707dd30da3efd296807722 | G135: adc36e7a69a134fcf5be85356309b1796edc26900c70f33e542cc806e1006070 | H135: 2026-10-31 16:57:14.261397
A136: 135 | C136: admin | D136: auth.login | E136: 59b8ed2e133ce47e73e3e40d7040734c4346d1d530093a2cf54494c331c3fcd0 | F136: adc36e7a69a134fcf5be85356309b1796edc26900c70f33e542cc806e1006070 | G136: 65274d7735ccc3a1a23372c1d74b2aeecff31a670def9030815a8715a2ba1192 | H136: 2026-10-31 17:16:05.459665
A137: 136 | C137: analyst | D137: auth.login | E137: f7a69667982ec6fcc30c42ad86e5b0bc5d5a2cea81a6623ef0fa90ffe5f6739b | F137: 65274d7735ccc3a1a23372c1d74b2aeecff31a670def9030815a8715a2ba1192 | G137: 3166eb9deaee1b6bb2577feeebfb1809b436b1baf5bf5ad6b1e8e37fc09ad8b3 | H137: 2026-10-31 17:16:46.544075
A138: 137 | C138: analyst | D138: redteam.generated | E138: f86d0c5426a708c062e613277ce32c8f78f29002f58c6a924391273178f85c44 | F138: 3166eb9deaee1b6bb2577feeebfb1809b436b1baf5bf5ad6b1e8e37fc09ad8b3 | G138: e9d9b0cfffec9693b164103f26592aebb752aa77c42bfe50647e11e054430df8 | H138: 2026-10-31 17:17:03.949318
A139: 138 | C139: analyst | D139: redteam.generated | E139: 517cd6cf9799990eb76d14edc021dad0369f606b35229ab89fdb540b556c6345 | F139: e9d9b0cfffec9693b164103f26592aebb752aa77c42bfe50647e11e054430df8 | G139: 809a84ac75027cec0a9d4048af7149c769d91057d028cdd00409fbfb2dfc8fb2 | H139: 2026-10-31 17:17:08.778095
A140: 139 | C140: analyst | D140: redteam.generated | E140: 6959516498f2e73baac91c98eb7e0b9f3a00f622b483acfaf5cfe496731efa66 | F140: 809a84ac75027cec0a9d4048af7149c769d91057d028cdd00409fbfb2dfc8fb2 | G140: e06ca2f0d625c7b51d8696e99fb0265d8a5be4cd42b51d9bc324b79811b26cc0 | H140: 2026-10-31 17:17:23.296564
A141: 140 | C141: analyst | D141: redteam.campaign | E141: 16cfcaa67e4fbd0dd1ecff999b0922ca7db26171b14fd16edfeffbf09c3dc3ee | F141: e06ca2f0d625c7b51d8696e99fb0265d8a5be4cd42b51d9bc324b79811b26cc0 | G141: d5e580be3abf2741645b0791ecda06af0f6a8693a08ed1b6ce06a4942cebbfe4 | H141: 2026-10-31 17:17:50.787859
A142: 141 | C142: analyst | D142: auth.login | E142: f7a69667982ec6fcc30c42ad86e5b0bc5d5a2cea81a6623ef0fa90ffe5f6739b | F142: d5e580be3abf2741645b0791ecda06af0f6a8693a08ed1b6ce06a4942cebbfe4 | G142: 644e52af7caadeb031c9d04224f3495c406af1d332b84ac8da960b5df8814185 | H142: 2026-10-31 17:19:11.297227
... A148: 147 | C148: analyst | D148: redteam.generated | E148: 286171700e7f074796b1ee92b7e22b4f436e19f14e607d22f3fba0dd4cb435b5 | F148: fcc794f81dcdf89e30ba6501b6c56ce8971944e5e9a4b09fca381bc633f607c3 | G148: 6d2fb0e5c367e2f69d44929fa13d4f74f2c9de11aa08a3e86cf395ff7156285d | H148: 2026-10-31 19:48:46.425569
A149: 148 | B149: MRG-0475 | C149: analyst | D149: case.created | E149: 326c344f5272a52fb57bccfecfa95c3dac9394cd8de2ebf266da06905700d67f | F149: 6d2fb0e5c367e2f69d44929fa13d4f74f2c9de11aa08a3e86cf395ff7156285d | G149: d1a2bab740ca16d67650f1c75c6a77f115bde4d6658f23bf5bdcd1fee4140adb | H149: 2026-10-31 19:49:33.006887
A150: 149 | B150: MRG-0475 | C150: system | D150: verdict.issued | E150: 9bd38378e6fdd084328ee3275dda9c097db4a3576140e2af12f3a3e06c161eda | F150: d1a2bab740ca16d67650f1c75c6a77f115bde4d6658f23bf5bdcd1fee4140adb | G150: 6d8636ae9af4603a0c795ec882e47b7c397e5368aec571951691a1932b7cd37c | H150: 2026-10-31 19:49:50.371891
A151: 150 | C151: analyst | D151: auth.login | E151: f7a69667982ec6fcc30c42ad86e5b0bc5d5a2cea81a6623ef0fa90ffe5f6739b | F151: 6d8636ae9af4603a0c795ec882e47b7c397e5368aec571951691a1932b7cd37c | G151: e573c50a19fdb29fa5bc0d333911a83cc4586a4298320b9d36436eab8de2c7b2 | H151: 2026-10-31 19:59:37.109775
A152: 151 | B152: MRG-0466 | C152: analyst | D152: cure.hold_payment | E152: 283fc2e8aad4073f54b048258af93e41dad8bbb423f3cd12c83ce24d37f0e8f3 | F152: e573c50a19fdb29fa5bc0d333911a83cc4586a4298320b9d36436eab8de2c7b2 | G152: c2cff865a92ee4cf0987244a76a68421d1bbab01c80380dd586fe6cce0a73d7c | H152: 2026-10-31 19:59:37.490304
A153: 152 | C153: analyst | D153: auth.login | E153: f7a69667982ec6fcc30c42ad86e5b0bc5d5a2cea81a6623ef0fa90ffe5f6739b | F153: c2cff865a92ee4cf0987244a76a68421d1bbab01c80380dd586fe6cce0a73d7c | G153: 0fbce5d670470e0d922586b3637ba50fbff21b7352dec69d40fcdc7c5b9d80aa | H153: 2026-10-31 19:59:57.466050
A154: 153 | B154: MRG-0466 | C154: analyst | D154: cure.hold_payment | E154: 283fc2e8aad4073f54b048258af93e41dad8bbb423f3cd12c83ce24d37f0e8f3 | F154: 0fbce5d670470e0d922586b3637ba50fbff21b7352dec69d40fcdc7c5b9d80aa | G154: 363eac62e5771e031f26908e6a8bb8c439a674a24d0c8122470e06b637c54a00 | H154: 2026-10-31 19:59:57.791640
A155: 154 | B155: MRG-0466 | C155: analyst | D155: cure.paid | E155: ac8378e0333ee06f600629603799398a93e8af42a06a7c68601b5e7ad780d04a | F155: 363eac62e5771e031f26908e6a8bb8c439a674a24d0c8122470e06b637c54a00 | G155: 65451b4fb1d045feb64106ced0382b86740322a1a2b7a4314b16cbe4937f1d3a | H155: 2026-10-31 19:59:57.868232
A156: 155 | B156: MRG-0466 | C156: analyst | D156: cure.block_identifiers | E156: 1a812a1a7ffb84009b705b00ae3a8fab597ba8787dc66185ddfc8feb7144d4d1 | F156: 65451b4fb1d045feb64106ced0382b86740322a1a2b7a4314b16cbe4937f1d3a | G156: b55b037249c6e45bb95f6e3b5ceab8d3b79749fde40a72f5070072b7dc193aee | H156: 2026-10-31 19:59:57.968667
A157: 156 | B157: MRG-0466 | C157: analyst | D157: cure.evidence_pack | E157: ae5921b00d4cd0f72ce2f4745c9a06ba7ee7c663dbdc03df04241ba7a86850d3 | F157: b55b037249c6e45bb95f6e3b5ceab8d3b79749fde40a72f5070072b7dc193aee | G157: 78b6cd81290addb67daf3095d14c6bf8383afcf0b4563dddd2a033a462d02a2d | H157: 2026-10-31 19:59:58.585128
A158: 157 | C158: analyst | D158: auth.login | E158: f7a69667982ec6fcc30c42ad86e5b0bc5d5a2cea81a6623ef0fa90ffe5f6739b | F158: 78b6cd81290addb67daf3095d14c6bf8383afcf0b4563dddd2a033a462d02a2d | G158: f268dd9e9a454477036df5517ab3cc025a44323b68048365b321346bcc1b1837 | H158: 2026-10-31 20:02:44.669125
A159: 158 | B159: MRG-0471 | C159: analyst | D159: cure.paid | E159: 3f5c295d1bea61a5ea2523f71c04a5ba78f8a625f29ad176d6a1e543947d877b | F159: f268dd9e9a454477036df5517ab3cc025a44323b68048365b321346bcc1b1837 | G159: bca335ac28946c0cf59440699930f64a7c97e9b3010b576787bb8f6b708e0631 | H159: 2026-10-31 20:02:44.763837
A160: 159 | B160: MRG-0471 | C160: analyst | D160: cure.stop_engaging | E160: 2c78750f1ca8f6d78f480172bd62e3594eb306451427d91810e44aa6f977ae84 | F160: bca335ac28946c0cf59440699930f64a7c97e9b3010b576787bb8f6b708e0631 | G160: 1f03cc0e34c7de1d9b4734c7eca66595538bf6a51643d9110722b1481df841f8 | H160: 2026-10-31 20:02:44.841408
A161: 160 | B161: MRG-0471 | C161: analyst | D161: cure.paid.clear | E161: 44136fa355b3678a1146ad16f7e8649e94fb4fc21fe77e8310c060f61caaff8a | F161: 1f03cc0e34c7de1d9b4734c7eca66595538bf6a51643d9110722b1481df841f8 | G161: fc154a325a9b7ef537cdb868b144a9542b81ce9af38a021e32b7c3e976a47a66 | H161: 2026-10-31 20:02:45.034452
A162: 161 | B162: MRG-0471 | C162: analyst | D162: cure.stop_engaging.undo | E162: 2c78750f1ca8f6d78f480172bd62e3594eb306451427d91810e44aa6f977ae84 | F162: fc154a325a9b7ef537cdb868b144a9542b81ce9af38a021e32b7c3e976a47a66 | G162: 9a4a6f9349e28051ed945047df73876d777f80e63ef614b6d5afa81d1f9f01cd | H162: 2026-10-31 20:02:45.108122
A163: 162 | B163: MRG-0466 | C163: analyst | D163: cure.hold_payment.undo | E163: 2c78750f1ca8f6d78f480172bd62e3594eb306451427d91810e44aa6f977ae84 | F163: 9a4a6f9349e28051ed945047df73876d777f80e63ef614b6d5afa81d1f9f01cd | G163: 1a02e623aa335bc3eb3559268f0c4f047e545fa8425964763bf00bedfd3baa2b | H163: 2026-10-31 20:02:45.184213
A164: 163 | B164: MRG-0466 | C164: analyst | D164: cure.block_identifiers.undo | E164: 2c78750f1ca8f6d78f480172bd62e3594eb306451427d91810e44aa6f977ae84 | F164: 1a02e623aa335bc3eb3559268f0c4f047e545fa8425964763bf00bedfd3baa2b | G164: c7e725fb01b784ebbcdc97a203f3373bac80bfdd00227fa69e2868269a53220b | H164: 2026-10-31 20:02:45.269731
A165: 164 | B165: MRG-0466 | C165: analyst | D165: cure.paid.clear | E165: 44136fa355b3678a1146ad16f7e8649e94fb4fc21fe77e8310c060f61caaff8a | F165: c7e725fb01b784ebbcdc97a203f3373bac80bfdd00227fa69e2868269a53220b | G165: 68e18acc46d604b34d6cbbb6840fe10bb790a6e9536a0214d61a6db82491832b | H165: 2026-10-31 20:02:45.343508
A166: 165 | B166: MRG-0466 | C166: analyst | D166: cure.hold_payment | E166: 283fc2e8aad4073f54b048258af93e41dad8bbb423f3cd12c83ce24d37f0e8f3 | F166: 68e18acc46d604b34d6cbbb6840fe10bb790a6e9536a0214d61a6db82491832b | G166: 770d073491275b6e222a203989422111f3626124dfda202ba1d6f44b0f684248 | H166: 2026-10-31 20:18:25.288953
A167: 166 | B167: MRG-0466 | C167: analyst | D167: cure.paid | E167: d15e7ed1fd7e179baaef7ee7841d48eaa91864d65dd6214303e87b176e992b8f | F167: 770d073491275b6e222a203989422111f3626124dfda202ba1d6f44b0f684248 | G167: 938a702e3bf43c03b413e80ed6b09a203f4bb371401114700ed4c649ca55d4cf | H167: 2026-10-31 20:18:27.618780
A168: 167 | C168: analyst | D168: auth.login | E168: f7a69667982ec6fcc30c42ad86e5b0bc5d5a2cea81a6623ef0fa90ffe5f6739b | F168: 938a702e3bf43c03b413e80ed6b09a203f4bb371401114700ed4c649ca55d4cf | G168: 8806a25a0de9c7431cc29d82fde20b14dc6f3f0528a24ace5caf70ef8e30d8c0 | H168: 2026-10-31 20:27:04.133790
A169: 168 | B169: MRG-0466 | C169: analyst | D169: cure.hold_payment | E169: 283fc2e8aad4073f54b048258af93e41dad8bbb423f3cd12c83ce24d37f0e8f3 | F169: 8806a25a0de9c7431cc29d82fde20b14dc6f3f0528a24ace5caf70ef8e30d8c0 | G169: b49b5d8aab071a79a4b11aabcb4c8093edf238552c5acecf509b8b2954bbd47c | H169: 2026-10-31 20:27:04.160757
A170: 169 | B170: MRG-0466 | C170: analyst | D170: cure.stop_engaging | E170: 2c78750f1ca8f6d78f480172bd62e3594eb306451427d91810e44aa6f977ae84 | F170: b49b5d8aab071a79a4b11aabcb4c8093edf238552c5acecf509b8b2954bbd47c | G170: 66fc2fa5982dc98e92fb6ee77517610a60a9a84d5bda6485840551148b76377a | H170: 2026-10-31 20:27:04.242376
A171: 170 | B171: MRG-0466 | C171: analyst | D171: cure.paid | E171: b37890a8456eb2b894a8cacc4f089f5653f622176cdbb6846aa44fbcb9f308fd | F171: 66fc2fa5982dc98e92fb6ee77517610a60a9a84d5bda6485840551148b76377a | G171: f411d06667a1119ed4184d5edd3b518d9bd55929dd56a9d98c784d3055868be6 | H171: 2026-10-31 20:27:04.310107
A172: 171 | B172: MRG-0466 | C172: analyst | D172: cure.hold_payment.undo | E172: 2c78750f1ca8f6d78f480172bd62e3594eb306451427d91810e44aa6f977ae84 | F172: f411d06667a1119ed4184d5edd3b518d9bd55929dd56a9d98c784d3055868be6 | G172: afe2a50d80d8465c78c3a484eb8754dd52301937bd91ea16c1260a882c347666 | H172: 2026-10-31 20:28:26.707455
A173: 172 | B173: MRG-0466 | C173: analyst | D173: cure.stop_engaging.undo | E173: 2c78750f1ca8f6d78f480172bd62e3594eb306451427d91810e44aa6f977ae84 | F173: afe2a50d80d8465c78c3a484eb8754dd52301937bd91ea16c1260a882c347666 | G173: a183173bead21632f21be03ce850989d1e4c581a06bc7e2ccf6f6108c2525e24 | H173: 2026-10-31 20:28:26.796541
A174: 173 | B174: MRG-0466 | C174: analyst | D174: cure.paid.clear | E174: 44136fa355b3678a1146ad16f7e8649e94fb4fc21fe77e8310c060f61caaff8a | F174: a183173bead21632f21be03ce850989d1e4c581a06bc7e2ccf6f6108c2525e24 | G174: 359bf426e8b60fb3d88299b4f820429f36635cde9940cb2080d2e88230767bd7 | H174: 2026-10-31 20:28:26.867949
A175: 174 | C175: analyst | D175: auth.login | E175: f7a69667982ec6fcc30c42ad86e5b0bc5d5a2cea81a6623ef0fa90ffe5f6739b | F175: 359bf426e8b60fb3d88299b4f820429f36635cde9940cb2080d2e88230767bd7 | G175: 9b96e118d9f673096f6b1c23af3fedc474ac311f0cd56aaf7b56364d1ed4a4d6 | H175: 2026-10-31 20:29:20.610809
A176: 175 | B176: MRG-0466 | C176: analyst | D176: cure.hold_payment | E176: 283fc2e8aad4073f54b048258af93e41dad8bbb423f3cd12c83ce24d37f0e8f3 | F176: 9b96e118d9f673096f6b1c23af3fedc474ac311f0cd56aaf7b56364d1ed4a4d6 | G176: d3688f9d8bb9f112d36d49d515e5dee2b7c9fb6051b3c416873956a2d74d8e07 | H176: 2026-10-31 20:29:20.640331
A177: 176 | B177: MRG-0466 | C177: analyst | D177: cure.stop_engaging | E177: 2c78750f1ca8f6d78f480172bd62e3594eb306451427d91810e44aa6f977ae84 | F177: d3688f9d8bb9f112d36d49d515e5dee2b7c9fb6051b3c416873956a2d74d8e07 | G177: d9f99bcbbc23f90cac1b6b9c91afb9a5cc47c4cfd980d4a15335898bb49ef411 | H177: 2026-10-31 20:29:20.724983
A178: 177 | B178: MRG-0466 | C178: analyst | D178: cure.paid | E178: e20ef1b94fbaeb6da742897ac20ca5931c8b463bdfc403aafb25f39a8b125d86 | F178: d9f99bcbbc23f90cac1b6b9c91afb9a5cc47c4cfd980d4a15335898bb49ef411 | G178: ca93491b804a24dce37aa886940afb2df31a9eada95ce3c409ee047d0f14c2b6 | H178: 2026-10-31 20:29:20.798747
A179: 178 | B179: MRG-0466 | C179: analyst | D179: cure.hold_payment.undo | E179: 2c78750f1ca8f6d78f480172bd62e3594eb306451427d91810e44aa6f977ae84 | F179: ca93491b804a24dce37aa886940afb2df31a9eada95ce3c409ee047d0f14c2b6 | G179: eded04f42d202960ca63db0d6a35d12ac8fe472cf6f0567df81cb753ef79dea0 | H179: 2026-10-31 20:30:35.046353
A180: 179 | B180: MRG-0466 | C180: analyst | D180: cure.stop_engaging.undo | E180: 2c78750f1ca8f6d78f480172bd62e3594eb306451427d91810e44aa6f977ae84 | F180: eded04f42d202960ca63db0d6a35d12ac8fe472cf6f0567df81cb753ef79dea0 | G180: 7dae4da2e7f5c8c51f740a5221fbb122d4ad1c1c6cec0f6b934f6f9734f96ed2 | H180: 2026-10-31 20:30:35.143444
A181: 180 | B181: MRG-0466 | C181: analyst | D181: cure.paid.clear | E181: 44136fa355b3678a1146ad16f7e8649e94fb4fc21fe77e8310c060f61caaff8a | F181: 7dae4da2e7f5c8c51f740a5221fbb122d4ad1c1c6cec0f6b934f6f9734f96ed2 | G181: 0b1530020b649ea6cb98aaba919d4211b772fa1c0d08c4fc5784125ca28863e2 | H181: 2026-10-31 20:30:35.214892
A182: 181 | C182: admin | D182: auth.login | E182: 59b8ed2e133ce47e73e3e40d7040734c4346d1d530093a2cf54494c331c3fcd0 | F182: 0b1530020b649ea6cb98aaba919d4211b772fa1c0d08c4fc5784125ca28863e2 | G182: 8a63fbcda90ca97539c385d3431005a2f67ae4d4b892d6f8ea3e13375feed826 | H182: 2026-10-31 21:05:52.740448
A183: 182 | C183: admin | D183: redteam.generated | E183: f2d5a3cead1db37ecde7b010fb8310baad860f261c33d0d9373b29220d6f85be | F183: 8a63fbcda90ca97539c385d3431005a2f67ae4d4b892d6f8ea3e13375feed826 | G183: 8c2af5cd7b5b64914dd068f0d327284dd18c71f7aa07f52548f296be429e5e6e | H183: 2026-10-31 21:06:36.254901
A184: 183 | C184: admin | D184: redteam.campaign | E184: de391ab36b24ae885ee0b1940d5eb9dd61f65de7f729d83be3d33910da7b6697 | F184: 8c2af5cd7b5b64914dd068f0d327284dd18c71f7aa07f52548f296be429e5e6e | G184: 5d7932237d60e4f66a894abf96ec18496c2e1d109cde34fe015aa7998986c857 | H184: 2026-10-31 21:07:11.469610
A185: 184 | B185: MRG-0476 | C185: admin | D185: case.created | E185: 53d396bac26bdcb08de2e099c548a5726d5de14981c6c53886b5a2f3ef8bc530 | F185: 5d7932237d60e4f66a894abf96ec18496c2e1d109cde34fe015aa7998986c857 | G185: c17a8f468555f28b33ac97eb302fbeacb64226b56f5756954964158184da509b | H185: 2026-10-31 21:07:41.340709
A186: 185 | B186: MRG-0476 | C186: system | D186: verdict.issued | E186: 6e3203ef55e84bf9e81967f259526d311732616d50847b0dce9a29b866d55133 | F186: c17a8f468555f28b33ac97eb302fbeacb64226b56f5756954964158184da509b | G186: d50a2e98275d7934cef668a38a5d246bcedd922229f5e81ae3273e6ffa945266 | H186: 2026-10-31 21:07:52.205024
A187: 186 | C187: analyst | D187: auth.login | E187: f7a69667982ec6fcc30c42ad86e5b0bc5d5a2cea81a6623ef0fa90ffe5f6739b | F187: d50a2e98275d7934cef668a38a5d246bcedd922229f5e81ae3273e6ffa945266 | G187: d639246a755466e9798f83821eeb47b04bb6a5a3cc7bb7ef082a79aef0f0c152 | H187: 2026-10-31 21:12:04.342561
A188: 187 | B188: MRG-0477 | C188: analyst | D188: case.created | E188: bf5e732a1254116a13a769b5a973f9cb3500675e5d8296d4ece274dd5c31d7e1 | F188: d639246a755466e9798f83821eeb47b04bb6a5a3cc7bb7ef082a79aef0f0c152 | G188: 69af91707cbc54e10d329072c329dedaf398db75928d392816182c5a7328e272 | H188: 2026-10-31 21:13:54.757945
A189: 188 | B189: MRG-0477 | C189: system | D189: verdict.issued | E189: 1a8d76fca23b9c2df181adc1ef06051928fe4e424def9ec140b30de60d78084e | F189: 69af91707cbc54e10d329072c329dedaf398db75928d392816182c5a7328e272 | G189: 75bcbff9d374583721c86a8dc587498102e3117ad80bfa3ac92d012eeee6ae13 | H189: 2026-10-31 21:14:02.034262
A190: 189 | B190: MRG-0478 | C190: analyst | D190: case.created | E190: 999640f8c3152c28b3c5ae8685e744251a1750e8a77ea076d39d8a9f434a4a3d | F190: 75bcbff9d374583721c86a8dc587498102e3117ad80bfa3ac92d012eeee6ae13 | G190: 8bebaaf325d0d93e6426327e437d24fd87db80288e199752ec067119530c1331 | H190: 2026-10-31 21:14:02.519961
A191: 190 | B191: MRG-0478 | C191: system | D191: verdict.issued | E191: 1cffe00f95984ba412b7af901998f953e4388a273382c556c257b3b4d5d81f13 | F191: 8bebaaf325d0d93e6426327e437d24fd87db80288e199752ec067119530c1331 | G191: d97edd8456f9935449a760607431b11c2efbb261352671b58c00601ec11386ac | H191: 2026-10-31 21:14:04.958224
A192: 191 | B192: MRG-0479 | C192: analyst | D192: case.created | E192: 5595b84276f3d8388efa3a61037c93e39c0af8f9968deabd971319ff1f4ba4e0 | F192: d97edd8456f9935449a760607431b11c2efbb261352671b58c00601ec11386ac | G192: 08a536ea62a13b677f4d21fa3d7a4aea3694e28b4306cabdb2fa36d85ffe65a9 | H192: 2026-10-31 21:14:05.286258
A193: 192 | B193: MRG-0479 | C193: system | D193: verdict.issued | E193: 301e000697dbbdeddfa7009106525f2ada8829d4b977f8d5cf71f0478fdba2f7 | F193: 08a536ea62a13b677f4d21fa3d7a4aea3694e28b4306cabdb2fa36d85ffe65a9 | G193: 361d4c8443c71ecdffcdb8a75617e1a7ae0c2ccb08b2f535c1bfd88985fd0b54 | H193: 2026-10-31 21:14:07.733253
A194: 193 | B194: MRG-0480 | C194: analyst | D194: case.created | E194: ea4a3e89f5af4f1187c88a9567d84edf0014a1d5b799a62138147011e582ac25 | F194: 361d4c8443c71ecdffcdb8a75617e1a7ae0c2ccb08b2f535c1bfd88985fd0b54 | G194: d5e8b1f74057f794c88a6c5ae5dd25163a0d1e39ca63b31c66fe31374c7a0934 | H194: 2026-10-31 21:14:08.020099
A195: 194 | B195: MRG-0480 | C195: system | D195: verdict.issued | E195: ac4b13d6c3f93ca05f57ed8919633fb728ba85bebb53ee0a49107aa85be33b2f | F195: d5e8b1f74057f794c88a6c5ae5dd25163a0d1e39ca63b31c66fe31374c7a0934 | G195: d3adc39612b9a3c01899ca2a09a2ff69c27130a0fcfae3f5c2f0fb1445f03e8c | H195: 2026-10-31 21:14:10.396421
A196: 195 | B196: MRG-0481 | C196: analyst | D196: case.created | E196: 198de2659418ce5e81745fb529454810f3c0bf8a7a54c93df2a4a5f36c114ba5 | F196: d3adc39612b9a3c01899ca2a09a2ff69c27130a0fcfae3f5c2f0fb1445f03e8c | G196: 01871bc8bf5f2dac317b69fe0dca4d2d7ddd00d80fef1fe5f012c62446331825 | H196: 2026-10-31 21:14:10.693267
A197: 196 | B197: MRG-0481 | C197: system | D197: verdict.issued | E197: 472f2fdc3434e76e560dd69a63037125313864701691ca36d715624e0ed40673 | F197: 01871bc8bf5f2dac317b69fe0dca4d2d7ddd00d80fef1fe5f012c62446331825 | G197: 3ebd3f10347b895d444e49ca870030b63b1fa12b306a408d24a6cd73e4a4cf4c | H197: 2026-10-31 21:14:13.004363
A198: 197 | B198: MRG-0482 | C198: analyst | D198: case.created | E198: 8f3260fd7365d47d84db1119fb2f2715589c973d0dd2c27634b66df4bbb22af0 | F198: 3ebd3f10347b895d444e49ca870030b63b1fa12b306a408d24a6cd73e4a4cf4c | G198: fa333d305388484cdd447f3e38b9ef59dd4ec671d9f516ac919c8540ead7bd5c | H198: 2026-10-31 21:14:13.468951
A199: 198 | B199: MRG-0482 | C199: system | D199: verdict.issued | E199: f633c7db5b951fbdf60558de048c2b176d260f78a15f80ea7e789ffa2068074c | F199: fa333d305388484cdd447f3e38b9ef59dd4ec671d9f516ac919c8540ead7bd5c | G199: 646be43617f0a1fec013024fb7bd115e6e5c1c8ec7dbf2f38165908ea3b7f958 | H199: 2026-10-31 21:14:27.363947
... A207: 206 | B207: MRG-0486 | C207: system | D207: verdict.issued | E207: c5f2ecbf6851a30e37e9c407b949d478861e2aca2911d4287b8abd23b4ee31d8 | F207: 1c461e24442816212d5cf9c6f3050f5b52c52cdc26842e6a43a11ce0198691be | G207: 9f78ff94b809ec37e41b962e4a20c2fe9b07a85e2d80965110ecaf8665480d9f | H207: 2026-10-31 21:15:17.362325
A208: 207 | C208: analyst | D208: auth.login | E208: f7a69667982ec6fcc30c42ad86e5b0bc5d5a2cea81a6623ef0fa90ffe5f6739b | F208: 9f78ff94b809ec37e41b962e4a20c2fe9b07a85e2d80965110ecaf8665480d9f | G208: f91d35642a310c42e23f7ca9e9d83202bab39d570bc4dec88eaaa7dba7017db3 | H208: 2026-10-31 21:15:46.795312
A209: 208 | C209: analyst | D209: auth.login | E209: f7a69667982ec6fcc30c42ad86e5b0bc5d5a2cea81a6623ef0fa90ffe5f6739b | F209: f91d35642a310c42e23f7ca9e9d83202bab39d570bc4dec88eaaa7dba7017db3 | G209: 6c96ac096b82ad6a6f44e6b53372e7f56a09e3e9e35f7b8eb61ebd4efd33994b | H209: 2026-10-31 21:20:38.878519
A210: 209 | B210: MRG-0487 | C210: analyst | D210: case.created | E210: bf5e732a1254116a13a769b5a973f9cb3500675e5d8296d4ece274dd5c31d7e1 | F210: 6c96ac096b82ad6a6f44e6b53372e7f56a09e3e9e35f7b8eb61ebd4efd33994b | G210: f1c5f42a76b1a18fa4470382e8f83e4bd52e5976c55be8d0df9a30cf02056ffe | H210: 2026-10-31 21:22:56.572753
...

Sheet DB beneficiaries
A1: id | B1: label | C1: identifier | D1: kind | E1: trust_level | F1: first_seen | G1: linked_person_id
A2: 1 | B2: Orbit Supplies (vendor) | C2: 50200011223344 | D2: account | E2: trusted | F2: 2026-10-31 14:51:57.524017
A3: 2 | B3: Sunrise Exports (vendor) | C3: 00401100223355 | D3: account | E3: trusted | F3: 2026-10-31 14:51:57.524017
A4: 3 | B4: BlueLine Consulting (vendor) | C4: blueline.billing@okhdfcbank | D4: upi | E4: trusted | F4: 2026-10-31 14:51:57.524017
A5: 4 | B5: Acme payroll pool | C5: acmepayroll@icici | D5: upi | E5: trusted | F5: 2026-10-31 14:51:57.524017
A6: 5 | B6: Papa savings | C6: suresh.panchal@oksbi | D6: upi | E6: trusted | F6: 2026-10-31 14:51:57.524017 | G6: 61
A7: 6 | B7: Reported mule account | C7: safeacct.rbi@oksbi | D7: upi | E7: flagged | F7: 2026-10-31 14:51:57.524017
A8: 7 | B8: Blocked from MRG-0466 | C8: 918273645501 | D8: account | E8: flagged | F8: 2026-10-31 19:59:57.971668
A9: 8 | B9: Blocked from MRG-0566 | C9: family.help@ibl | D9: upi | E9: flagged | F9: 2026-11-01 02:18:42.863336

Sheet DB cases
A1: id | B1: title | C1: submitted_by | D1: claimed_person_id | E1: claimed_sender | F1: channel | G1: sender_contact | H1: message_text | I1: scenario | J1: status | K1: stage | L1: progress | M1: received_at | N1: created_at | O1: closed | P1: outcome
A2: MRG-0412 | B2: Your electricity connection will be disconnected tonight at 9:30 PM. Call our officer at +91 97879 37354 immed | C2: analyst | E2: SBI Alerts | F2: sms | G2: +91 60011 00110 | H2: Your electricity connection will be disconnected tonight at 9:30 PM. Call our officer at +91 97879 37354 immediately. ASAP | J2: complete | K2: verdict | L2: 1 | M2: 2026-10-30 15:33:51.350731 | N2: 2026-11-01 02:36:11.391582 | O2: 0
A3: MRG-0413 | B3: Can you pick up milk on the way back? Also I've paid the electricity bill through the app. Regards. | C3: employee | E3: Mummy | F3: whatsapp | G3: +91 98920 45111 | H3: Can you pick up milk on the way back? Also I've paid the electricity bill through the app. Regards. | J3: complete | K3: verdict | L3: 1 | M3: 2026-10-24 12:44:26.782830 | N3: 2026-11-01 02:36:11.404556 | O3: 1 | P3: verified_genuine
A4: MRG-0414 | B4: expense report submitted for the pune client visit, receipts attached in concur. Thanks. | C4: employee | E4: Ananya Iyer | F4: email | G4: ananya.iyer@acmefintech.in | H4: expense report submitted for the pune client visit, receipts attached in concur. Thanks. | J4: complete | K4: verdict | L4: 1 | M4: 2026-10-28 09:29:40.924661 | N4: 2026-11-01 02:36:11.412556 | O4: 1 | P4: verified_genuine
A5: MRG-0415 | B5: बधाई हो, आपने ₹18.5 lakh जीते हैं। दावा करने के लिए शुल्क zenith.pay@okhdfcbank पर भेजें। 🙏 | C5: analyst | E5: HR Recruiter | F5: whatsapp | G5: +91 77889 66554 | H5: बधाई हो, आपने ₹18.5 lakh जीते हैं। दावा करने के लिए शुल्क zenith.pay@okhdfcbank पर भेजें। 🙏 | J5: complete | K5: verdict | L5: 1 | M5: 2026-10-15 18:40:22.139482 | N5: 2026-11-01 02:36:11.420563 | O5: 0
A6: MRG-0416 | B6: Ananya here. Can't talk now. Need a favour, process the payment to Zenith Logistics today, the usual approvals | C6: analyst | E6: Rajesh Mehta (CFO) | F6: whatsapp | G6: +91 93321 45008 | H6: Ananya here. Can't talk now. Need a favour, process the payment to Zenith Logistics today, the usual approvals will slow us down. Reply once done. Thanks. | J6: complete | K6: verdict | L6: 1 | M6: 2026-10-15 21:59:45.123342 | N6: 2026-11-01 02:36:11.427561 | O6: 0
A7: MRG-0417 | B7: Running 10 minutes late, start without me. | C7: employee | E7: Mummy | F7: whatsapp | G7: +91 98920 45111 | H7: Running 10 minutes late, start without me. | J7: complete | K7: verdict | L7: 1 | M7: 2026-10-27 10:52:39.204001 | N7: 2026-11-01 02:36:11.434583 | O7: 1 | P7: verified_genuine
A8: MRG-0418 | B8: आपका लॉगिन OTP 122290 है। इसे किसी के साथ साझा न करें। ok? | C8: employee | F8: sms | H8: आपका लॉगिन OTP 122290 है। इसे किसी के साथ साझा न करें। ok? | J8: complete | K8: verdict | L8: 1 | M8: 2026-10-22 09:04:08.447176 | N8: 2026-11-01 02:36:11.441714 | O8: 1 | P8: verified_genuine
A9: MRG-0419 | B9: IT team se bol raha hoon, aapka account reset ho raha hai. Jo OTP aaya hai woh bata do jaldi, 15 minute mein l | C9: employee | E9: IT helpdesk | F9: phone | G9: +91 88002 31109 | H9: IT team se bol raha hoon, aapka account reset ho raha hai. Jo OTP aaya hai woh bata do jaldi, 15 minute mein lock ho jayega. 🙏 | J9: complete | K9: verdict | L9: 1 | M9: 2026-10-13 14:58:24.746034 | N9: 2026-11-01 02:36:11.448722 | O9: 1 | P9: confirmed_fraud
A10: MRG-0420 | B10: Aapka order ship ho gaya hai, Tuesday tak aa jayega. App mein track karein. ok? | C10: employee | F10: sms | H10: Aapka order ship ho gaya hai, Tuesday tak aa jayega. App mein track karein. ok? | J10: complete | K10: verdict | L10: 1 | M10: 2026-10-23 12:56:06.249304 | N10: 2026-11-01 02:36:11.456243 | O10: 0
A11: MRG-0421 | B11: Mummy main hoon, accident ho gaya hai, phone toot gaya. Paise abhi bhejo vendorpay2026@ybl pe, kisi ko mat bat | C11: employee | E11: Papa | F11: whatsapp | G11: +91 73040 99812 | H11: Mummy main hoon, accident ho gaya hai, phone toot gaya. Paise abhi bhejo vendorpay2026@ybl pe, kisi ko mat batana please. Sent from my iPhone | J11: complete | K11: verdict | L11: 1 | M11: 2026-10-13 13:39:27.444454 | N11: 2026-11-01 02:36:11.463240 | O11: 0
A12: MRG-0422 | B12: Following our call, attached is the revised invoice from NovaChem Traders. Payment must reach the updated acco | C12: employee | E12: Zenith Logistics accounts | F12: email | G12: accounts@zenith-logistic.co | H12: Following our call, attached is the revised invoice from NovaChem Traders. Payment must reach the updated account right now to avoid a penalty. ok? | J12: complete | K12: verdict | L12: 1 | M12: 2026-10-07 22:06:21.915778 | N12: 2026-11-01 02:36:11.469755 | O12: 0
A13: MRG-0423 | B13: Mom I'm in trouble, police stopped me.. I need ₹9,80,000 urgently on vendorpay2026@ybl.. Please don't call, ju | C13: analyst | E13: Bhaiya | F13: whatsapp | G13: +91 99001 22113 | H13: Mom I'm in trouble, police stopped me.. I need ₹9,80,000 urgently on vendorpay2026@ybl.. Please don't call, just send.. Regards. | J13: complete | K13: verdict | L13: 1 | M13: 2026-10-26 14:29:15.307278 | N13: 2026-11-01 02:36:11.475755 | O13: 0
A14: MRG-0424 | B14: The server patching window is Saturday 10 PM to 2 AM. Services may be briefly unavailable. | C14: analyst | E14: Ananya Iyer | F14: email | G14: ananya.iyer@acmefintech.in | H14: The server patching window is Saturday 10 PM to 2 AM. Services may be briefly unavailable. | J14: complete | K14: verdict | L14: 1 | M14: 2026-10-20 15:30:20.069461 | N14: 2026-11-01 02:36:11.483274 | O14: 0
A15: MRG-0425 | B15: Urgent and confidential: transfer Rs 2,40,000 to account 73530465220 IFSC ICIC0007890 abhi turant.. I am trave | C15: employee | E15: Ashok Raman | F15: sms | G15: +91 81234 77120 | H15: Urgent and confidential: transfer Rs 2,40,000 to account 73530465220 IFSC ICIC0007890 abhi turant.. I am travelling, message me on WhatsApp only.. | J15: complete | K15: verdict | L15: 1 | M15: 2026-10-18 20:59:37.293241 | N15: 2026-11-01 02:36:11.489272 | O15: 0
A16: MRG-0426 | B16: आपका खाता बंद होने वाला है। जो OTP आया है वह तुरंत बताइए। | C16: analyst | E16: IT Service Desk | F16: email | G16: it-helpdesk@acme-reset.org | H16: आपका खाता बंद होने वाला है। जो OTP आया है वह तुरंत बताइए। | J16: complete | K16: verdict | L16: 1 | M16: 2026-10-14 12:07:22.918282 | N16: 2026-11-01 02:36:11.496272 | O16: 1 | P16: confirmed_fraud
A17: MRG-0427 | B17: Reminder: your car insurance renews next month. No action needed if auto-renew is on. Regards. | C17: analyst | F17: sms | H17: Reminder: your car insurance renews next month. No action needed if auto-renew is on. Regards. | J17: complete | K17: verdict | L17: 1 | M17: 2026-10-17 22:18:27.283535 | N17: 2026-11-01 02:36:11.502273 | O17: 1 | P17: verified_genuine
A18: MRG-0428 | B18: Leave approve ho gayi hai 12 se 14 Nov tak, enjoy karo! ASAP | C18: employee | E18: Priya Nair | F18: teams | H18: Leave approve ho gayi hai 12 se 14 Nov tak, enjoy karo! ASAP | J18: complete | K18: verdict | L18: 1 | M18: 2026-10-16 09:00:10.178680 | N18: 2026-11-01 02:36:11.510789 | O18: 1 | P18: verified_genuine
A19: MRG-0429 | B19: Your electricity connection will be disconnected tonight at 9:30 PM. Call our officer at +91 97723 75747 immed | C19: analyst | E19: SBI Alerts | F19: sms | G19: +91 60011 00110 | H19: Your electricity connection will be disconnected tonight at 9:30 PM. Call our officer at +91 97723 75747 immediately. pls | J19: complete | K19: verdict | L19: 1 | M19: 2026-10-31 09:37:02.445303 | N19: 2026-11-01 02:36:11.516795 | O19: 0
A20: MRG-0430 | B20: Dear customer, your KYC has expired and your account will be blocked today. Update now at https://hdfc-secure- | C20: analyst | E20: SBI Alerts | F20: sms | G20: +91 60011 00110 | H20: Dear customer, your KYC has expired and your account will be blocked today. Update now at https://hdfc-secure-login.net/kyc. | J20: complete | K20: verdict | L20: 1 | M20: 2026-10-19 21:19:00.017242 | N20: 2026-11-01 02:36:11.524797 | O20: 0
A21: MRG-0431 | B21: You won a lucky draw worth Rs 2,40,000. Pay the processing fee to safeacct.rbi@oksbi within 1 hour to claim. A | C21: employee | E21: HR Recruiter | F21: whatsapp | G21: +91 77889 66554 | H21: You won a lucky draw worth Rs 2,40,000. Pay the processing fee to safeacct.rbi@oksbi within 1 hour to claim. ASAP | J21: complete | K21: verdict | L21: 1 | M21: 2026-10-28 18:09:34.632001 | N21: 2026-11-01 02:36:11.532828 | O21: 0
A22: MRG-0432 | B22: Can you pick up milk on the way back? Also I've paid the electricity bill through the app. pls | C22: analyst | E22: Rohan Panchal | F22: whatsapp | G22: +91 98920 45112 | H22: Can you pick up milk on the way back? Also I've paid the electricity bill through the app. pls | J22: complete | K22: verdict | L22: 1 | M22: 2026-10-19 11:53:37.096237 | N22: 2026-11-01 02:36:11.539834 | O22: 1 | P22: verified_genuine
A23: MRG-0433 | B23: Urgent and confidential: transfer Rs. 49,999 to account 21916273235 IFSC SBIN0004567 by EOD today. I am travel | C23: analyst | E23: Rajesh Mehta (CFO) | F23: whatsapp | G23: +91 93321 45008 | H23: Urgent and confidential: transfer Rs. 49,999 to account 21916273235 IFSC SBIN0004567 by EOD today. I am travelling, message me on WhatsApp only. | J23: complete | K23: verdict | L23: 1 | M23: 2026-10-09 08:56:34.495221 | N23: 2026-11-01 02:36:11.546837 | O23: 1 | P23: confirmed_fraud
A24: MRG-0434 | B24: दिवाली की हार्दिक शुभकामनाएं! Regards. | C24: analyst | E24: Rohan Panchal | F24: whatsapp | G24: +91 98920 45112 | H24: दिवाली की हार्दिक शुभकामनाएं! Regards. | J24: complete | K24: verdict | L24: 1 | M24: 2026-10-03 08:25:52.548508 | N24: 2026-11-01 02:36:11.553866 | O24: 0
A25: MRG-0435 | B25: Rohan here. Can't talk now. Need a favour, process the payment to Orbit Supplies today, the usual approvals wi | C25: analyst | E25: Rajesh Mehta (CFO) | F25: whatsapp | G25: +91 93321 45008 | H25: Rohan here. Can't talk now. Need a favour, process the payment to Orbit Supplies today, the usual approvals will slow us down. Reply once done. pls | J25: complete | K25: verdict | L25: 1 | M25: 2026-10-20 09:20:30.307151 | N25: 2026-11-01 02:36:11.560868 | O25: 0
A26: MRG-0436 | B26: Movie tickets ke ₹500 GPay kar diye, check kar lena. ok? | C26: analyst | E26: Mummy | F26: whatsapp | G26: +91 98920 45111 | H26: Movie tickets ke ₹500 GPay kar diye, check kar lena. ok? | J26: complete | K26: verdict | L26: 1 | M26: 2026-10-13 18:32:44.696781 | N26: 2026-11-01 02:36:11.567427 | O26: 0
A27: MRG-0437 | B27: तुरंत INR 12,00,000 ट्रांसफर करें, अप्रूवल मैं बाद में दूँगा। ऑडिट को अभी कुछ न बताएं। 🙏 | C27: analyst | E27: Ashok Raman | F27: sms | G27: +91 81234 77120 | H27: तुरंत INR 12,00,000 ट्रांसफर करें, अप्रूवल मैं बाद में दूँगा। ऑडिट को अभी कुछ न बताएं। 🙏 | J27: complete | K27: verdict | L27: 1 | M27: 2026-10-17 19:01:45.940484 | N27: 2026-11-01 02:36:11.574434 | O27: 0
A28: MRG-0438 | B28: बधाई हो, आपने ₹25,000 जीते हैं। दावा करने के लिए शुल्क refund.help@okaxis पर भेजें। Regards. | C28: employee | E28: HR Recruiter | F28: whatsapp | G28: +91 77889 66554 | H28: बधाई हो, आपने ₹25,000 जीते हैं। दावा करने के लिए शुल्क refund.help@okaxis पर भेजें। Regards. | J28: complete | K28: verdict | L28: 1 | M28: 2026-10-04 10:22:24.273824 | N28: 2026-11-01 02:36:11.579951 | O28: 0
A29: MRG-0439 | B29: आपका लॉगिन OTP 410109 है। इसे किसी के साथ साझा न करें। | C29: employee | F29: sms | H29: आपका लॉगिन OTP 410109 है। इसे किसी के साथ साझा न करें। | J29: complete | K29: verdict | L29: 1 | M29: 2026-10-18 18:34:58.129453 | N29: 2026-11-01 02:36:11.587464 | O29: 0
A30: MRG-0440 | B30: Papa ki train late hai, main station se le aaunga.. 🙏 | C30: employee | E30: Mummy | F30: whatsapp | G30: +91 98920 45111 | H30: Papa ki train late hai, main station se le aaunga.. 🙏 | J30: complete | K30: verdict | L30: 1 | M30: 2026-10-29 08:25:42.559565 | N30: 2026-11-01 02:36:11.594465 | O30: 0
A31: MRG-0441 | B31: Aapka order ship ho gaya hai, Tuesday tak aa jayega. App mein track karein. Thanks. | C31: analyst | F31: sms | H31: Aapka order ship ho gaya hai, Tuesday tak aa jayega. App mein track karein. Thanks. | J31: complete | K31: verdict | L31: 1 | M31: 2026-10-10 22:49:27.888537 | N31: 2026-11-01 02:36:11.600982 | O31: 1 | P31: verified_genuine
A32: MRG-0442 | B32: Notice from Mumbai Police: your Aadhaar is linked to money laundering. Do not disconnect or inform anyone. Pay | C32: employee | E32: Inspector Sharma | F32: video | G32: +91 90011 22334 | H32: Notice from Mumbai Police: your Aadhaar is linked to money laundering. Do not disconnect or inform anyone. Pay the security deposit of ₹3.2 crore to clear your name. | J32: complete | K32: verdict | L32: 1 | M32: 2026-10-26 19:22:32.744277 | N32: 2026-11-01 02:36:11.607990 | O32: 0
A33: MRG-0443 | B33: घर पहुँच गया, खाना खाकर फोन करता हूँ। | C33: analyst | E33: Rohan Panchal | F33: whatsapp | G33: +91 98920 45112 | H33: घर पहुँच गया, खाना खाकर फोन करता हूँ। | J33: complete | K33: verdict | L33: 1 | M33: 2026-10-27 11:36:12.524373 | N33: 2026-11-01 02:36:11.615989 | O33: 1 | P33: verified_genuine
A34: MRG-0444 | B34: papa, it's me. i've had an accident and my phone broke, this is a friend's number. please send inr 12,00,000 t | C34: analyst | E34: Bhaiya | F34: whatsapp | G34: +91 99001 22113 | H34: papa, it's me. i've had an accident and my phone broke, this is a friend's number. please send inr 12,00,000 to rk.urgent@paytm right now, don't tell anyone at home. Regards. | J34: complete | K34: verdict | L34: 1 | M34: 2026-10-30 20:38:16.200407 | N34: 2026-11-01 02:36:11.622496 | O34: 0
A35: MRG-0445 | B35: Payroll will be processed on the 28th. Contact HR through the portal if your bank details changed. pls | C35: analyst | E35: Rajesh Mehta | F35: email | G35: rajesh.mehta@acmefintech.in | H35: Payroll will be processed on the 28th. Contact HR through the portal if your bank details changed. pls | J35: complete | K35: verdict | L35: 1 | M35: 2026-10-07 17:20:26.446327 | N35: 2026-11-01 02:36:11.630043 | O35: 1 | P35: verified_genuine
A36: MRG-0446 | B36: Grandma wants everyone home for dinner on Sunday. | C36: analyst | E36: Mummy | F36: whatsapp | G36: +91 98920 45111 | H36: Grandma wants everyone home for dinner on Sunday. | J36: complete | K36: verdict | L36: 1 | M36: 2026-10-27 12:18:24.140033 | N36: 2026-11-01 02:36:11.637076 | O36: 0
A37: MRG-0447 | B37: lunch order for the offsite: reply with veg or non-veg by noon so admin can book the caterer. pls | C37: employee | E37: Priya Nair | F37: teams | H37: lunch order for the offsite: reply with veg or non-veg by noon so admin can book the caterer. pls | J37: complete | K37: verdict | L37: 1 | M37: 2026-10-29 10:44:54.927801 | N37: 2026-11-01 02:36:11.644085 | O37: 1 | P37: verified_genuine
A38: MRG-0448 | B38: Main CBI officer bol raha hoon, aapke naam pe case hai. Video call disconnect mat karna, kisi ko mat batana, ₹ | C38: employee | E38: Inspector Sharma | F38: video | G38: +91 90011 22334 | H38: Main CBI officer bol raha hoon, aapke naam pe case hai. Video call disconnect mat karna, kisi ko mat batana, ₹75,000 verification ke liye bhejo. Thanks. | J38: complete | K38: verdict | L38: 1 | M38: 2026-10-04 18:35:13.314458 | N38: 2026-11-01 02:36:11.650602 | O38: 0
A39: MRG-0449 | B39: Launch ke liye sabko badhai, Friday shaam celebration hai cafeteria mein! 🙏 | C39: employee | E39: Priya Nair | F39: teams | H39: Launch ke liye sabko badhai, Friday shaam celebration hai cafeteria mein! 🙏 | J39: complete | K39: verdict | L39: 1 | M39: 2026-10-17 19:32:32.656345 | N39: 2026-11-01 02:36:11.657785 | O39: 0
A40: MRG-0450 | B40: You won a lucky draw worth ₹18.5 lakh. Pay the processing fee to vendorpay2026@ybl within 1 hour to claim. ok? | C40: analyst | E40: HR Recruiter | F40: whatsapp | G40: +91 77889 66554 | H40: You won a lucky draw worth ₹18.5 lakh. Pay the processing fee to vendorpay2026@ybl within 1 hour to claim. ok? | J40: complete | K40: verdict | L40: 1 | M40: 2026-10-15 14:19:57.948522 | N40: 2026-11-01 02:36:11.664786 | O40: 1 | P40: confirmed_fraud
A41: MRG-0451 | B41: आपका लॉगिन otp 744420 है। इसे किसी के साथ साझा न करें। pls | C41: analyst | F41: sms | H41: आपका लॉगिन otp 744420 है। इसे किसी के साथ साझा न करें। pls | J41: complete | K41: verdict | L41: 1 | M41: 2026-10-20 18:58:25.050853 | N41: 2026-11-01 02:36:11.671794 | O41: 0
A42: MRG-0452 | B42: Your OTP for login is 197883.. Do not share it with anyone.. Bank staff will never ask for your OTP.. | C42: employee | F42: sms | H42: Your OTP for login is 197883.. Do not share it with anyone.. Bank staff will never ask for your OTP.. | J42: complete | K42: verdict | L42: 1 | M42: 2026-10-20 11:07:03.080796 | N42: 2026-11-01 02:36:11.677791 | O42: 1 | P42: verified_genuine
A43: MRG-0453 | B43: Following our call, attached is the revised invoice from Apex Infra Pvt Ltd. Payment must reach the updated ac | C43: employee | E43: Zenith Logistics accounts | F43: email | G43: accounts@zenith-logistic.co | H43: Following our call, attached is the revised invoice from Apex Infra Pvt Ltd. Payment must reach the updated account within 1 hour to avoid a penalty. 🙏 | J43: complete | K43: verdict | L43: 1 | M43: 2026-10-19 14:33:18.746897 | N43: 2026-11-01 02:36:11.685227 | O43: 0
